Workbook

Sheet Старт
B2: ФИНАНСОВАЯ МОДЕЛЬ VERTOV — С ЧЕГО НАЧАТЬ
B3: Правило одно: СИНИЕ ячейки — меняешь ты, все остальные считаются сами. После любого изменения смотри проверку внизу P&L.
B5: КАК ПОЛЬЗОВАТЬСЯ — 4 ШАГА
B6: ШАГ 1 · Задай цели прибыли | C6: Блок «ЦЕЛИ ПРИБЫЛИ» вверху «Технического». Три группы клиентов (тратят 50% / 75% / 100% лимита): укажи долю каждой группы и какую чистую маржу хочешь с неё. Модель выведет среднюю цель и минимальную гарантированную маржу тарифов.
B7: ШАГ 2 · Задай размер тарифов | C7: Строка «КРЕДИТОВ В ТАРИФЕ»: сколько кредитов входит в Start / Pro / Studio / Elite. Цены посчитаются сами из целей прибыли и округлятся до …99. «Поправка маржи» — дорогие тарифы дают дешевле кредит.
B8: ШАГ 3 · Заполни каталог моделей | C8: Матрица «Модели из прода»: 22 реальные модели с ценами. Меняй кредиты за единицу и длину клипа; впиши токены Syntx (колонка Q) — сравнение посчитается.
B9: ШАГ 4 · Проверь прибыль | C9: P&L: полный отчёт о прибыли за месяц. Внизу — блок «Проверка»: чистая маржа, если клиенты тратят 50% / 75% / весь лимит, и сходимость с твоей целью.
B11: КАРТА ЛИСТОВ
B12: Экзекьютив | C12: Сводка на одну страницу: тарифы, экономика одной генерации, P&L, текущие настройки. Показывать инвестору.
B13: Тарифы | C13: Тарифы — утвержденные цены, кредиты, CM2 и единая матрица Vertov / Syntx / Higgsfield.
B14: Юнит-экономика | C14: Экономика одной генерации в 3 шага: во сколько обходится нам → сколько зарабатываем → то же на объёме за месяц.
B15: P&L | C15: Прибыль за месяц: выручка (подписки + докупки) → себестоимость → комиссии → постоянные расходы → маркетинг → налог → чистая прибыль. Внизу — проверка по сценариям.
B16: Технический | C16: Аудит цен — вендор, источник и confidence; обновлять перед инвест-пакетом.
B18: ЧАСТЫЕ ДЕЙСТВИЯ — ГДЕ МЕНЯТЬ
B19: Хочу другую маржу / другие цены | C19: Цели прибыли (доли групп и целевые маржи) — цены пересчитаются.
B20: Хочу дать больше/меньше генераций | C20: Размер тарифа в генерациях Seedance 2.0.
B21: Сменить банк перевода (A7 ↔ ВТБ) | C21: Переключатель коридора: 1 = A7 (0,37%), 2 = ВТБ (8,2%).
B22: Изменить долю резервного провайдера Nano | C22: Доля запросов через kie.ai — влияет на себестоимость картинок.
B23: Доля оплат СБП / карты | C23: Меняет комиссию эквайринга (СБП 0,7% vs карта 3,2%).
B24: УСН 6% ↔ 15% | C24: Переключатель налогового режима.
B25: Хостинг: грант / self-host / managed | C25: Сценарий постоянных расходов на инфраструктуру.
B26: Число клиентов, отток, стоимость привлечения | C26: Блок «Портфель и поведение».
B27: Цены докупки кредитов | C27: Блок «Top-up»: номиналы и ₽/кредит.
B29: Термины, если что-то непонятно — «Технический», блок «Справка» в самом низу.

Sheet Экзекьютив
B2: VERTOV — ЭКЗЕКЬЮТИВ-СВОДКА
B3: Утвержденная pricing-модель запуска: тарифы, CM2, Net margin P&L, себестоимость SKU и сравнение Vertov · Syntx · Higgsfield.
B5: 1. ТАРИФНАЯ СЕТКА (цена из пола маржи)
B6: Тариф | C6: Цена ₽/мес | D6: Видео veo-fast, ген/мес | E6: Картинки g3-pro, ген/мес | F6: ₽ за генерацию | G6: Мин. маржа
B7: Start | C7: =Тарифы!C7 -> 599 | D7: =Тарифы!C11 -> 5.5164319 | E7: =Тарифы!C15 -> 37.903226 | F7: =Тарифы!C17 -> 108.58468 | G7: =Тарифы!C8 -> 0.32307421
B8: Pro | C8: =Тарифы!D7 -> 1649 | D8: =Тарифы!D11 -> 20.657277 | E8: =Тарифы!D15 -> 141.93548 | F8: =Тарифы!D17 -> 79.826591 | G8: =Тарифы!D8 -> 0.11316117
B9: Studio | C9: =Тарифы!E7 -> 3799 | D9: =Тарифы!E11 -> 48.356808 | E9: =Тарифы!E15 -> 332.25806 | F9: =Тарифы!E17 -> 78.561845 | G9: =Тарифы!E8 -> 0.10040149
B10: Elite | C10: =Тарифы!F7 -> 5799 | D10: =Тарифы!F11 -> 74.647887 | E10: =Тарифы!F15 -> 512.90323 | F10: =Тарифы!F17 -> 77.684717 | G10: =Тарифы!F8 -> 0.091308413
B11: Ultra | C11: =Тарифы!G7 -> 11699 | D11: =Тарифы!G11 -> 152.58216 | E11: =Тарифы!G15 -> 1048.3871 | F11: =Тарифы!G17 -> 76.673446 | G11: =Тарифы!G8 -> 0.08056648
B12: 2. ЭКОНОМИКА ОДНОЙ ГЕНЕРАЦИИ
B13: Себестоимость 1 ген. veo-3-1 (8с), ₽ | C13: ='Юнит-экономика'!I18 -> 125.79871
B14: Себестоимость 1 ген. gemini-3-pro-image, ₽ | C14: ='Юнит-экономика'!I13 -> 9.0575072
B15: Продаём 1 видео-ген. (veo-fast) за, ₽ | C15: =TEXT(Тарифы!C17,"0")&"–"&TEXT(Тарифы!F17,"0")&" ₽" -> 109–78 ₽
B16: Прибыль с 1 видео-ген. на Elite (после комиссий и УСН) | C16: ='Юнит-экономика'!H20 -> 2.2991803
B18: 3. P&L ПРИ 1000 КЛИЕНТАХ
B19: Выручка (подписки + top-up) | C19: ='P&L'!C8 -> 2352000
B20: Валовая прибыль | C20: ='P&L'!C16 -> 1443226.6
B21: Чистая прибыль | C21: ='P&L'!C32 -> 924550.65
B22: Чистая маржа | C22: ='P&L'!C35 -> 0.39309126
B23: Worst Net margin при 100% расходовании | C23: ='P&L'!E44 -> 0.0029000331
B25: 4. КОНФИГУРАЦИЯ (текущие переключатели)
B26: Коридор | C26: =IF(Технический!C20=1,"A7 · 0,37%","ВТБ · 8,22%") -> A7 · 0,37%
B27: УСН | C27: =IF(Технический!C64=1,"Доходы 6% (взносы в зачёт)","Д−Р 15%") -> Доходы 6% (взносы в зачёт)
B28: Хостинг | C28: =CHOOSE(Технический!C73,"Грант (0 ₽)","Self-host 18k","Managed 52k") -> Managed 52k
B29: Доля оплат через СБП / доля резервного провайдера Nano | C29: =TEXT(Технический!C53,"0%")&" / "&TEXT(Технический!C38,"0%") -> 55% / 10%
B30: Курс ЦБ / использование | C30: =TEXT(Технический!C17,"0.0")&" ₽/$ / "&TEXT(Технический!C87,"0%") -> 85.0 ₽/$ / 66%
B32: 5. ГЕНЕРАЦИЙ КАЖДОЙ МОДЕЛИ В ТАРИФЕ (из матрицы)
B33: Модель | C33: Start | D33: Pro | E33: Studio | F33: Elite | G33: Ultra
B34: =Тарифы!$B$54 -> nano-banana | C34: =Тарифы!$M$54 -> 146.875 | D34: =Тарифы!$N$54 -> 550 | E34: =Тарифы!$O$54 -> 1287.5 | F34: =Тарифы!$P$54 -> 1987.5 | G34: =Тарифы!$Q$54 -> 4062.5
B35: =Тарифы!$B$55 -> recraft-v4 | C35: =Тарифы!$M$55 -> 47 | D35: =Тарифы!$N$55 -> 176 | E35: =Тарифы!$O$55 -> 412 | F35: =Тарифы!$P$55 -> 636 | G35: =Тарифы!$Q$55 -> 1300
B36: =Тарифы!$B$56 -> gpt-image-2 | C36: =Тарифы!$M$56 -> 117.5 | D36: =Тарифы!$N$56 -> 440 | E36: =Тарифы!$O$56 -> 1030 | F36: =Тарифы!$P$56 -> 1590 | G36: =Тарифы!$Q$56 -> 3250
B37: =Тарифы!$B$57 -> recraft-v4-vector | C37: =Тарифы!$M$57 -> 29.375 | D37: =Тарифы!$N$57 -> 110 | E37: =Тарифы!$O$57 -> 257.5 | F37: =Тарифы!$P$57 -> 397.5 | G37: =Тарифы!$Q$57 -> 812.5
B38: =Тарифы!$B$58 -> nano-banana-2-lite | C38: =Тарифы!$M$58 -> 146.875 | D38: =Тарифы!$N$58 -> 550 | E38: =Тарифы!$O$58 -> 1287.5 | F38: =Тарифы!$P$58 -> 1987.5 | G38: =Тарифы!$Q$58 -> 4062.5
B39: =Тарифы!$B$59 -> nano-banana-2 | C39: =Тарифы!$M$59 -> 69.117647 | D39: =Тарифы!$N$59 -> 258.82353 | E39: =Тарифы!$O$59 -> 605.88235 | F39: =Тарифы!$P$59 -> 935.29412 | G39: =Тарифы!$Q$59 -> 1911.7647
B40: =Тарифы!$B$60 -> nano-banana-pro | C40: =Тарифы!$M$60 -> 37.903226 | D40: =Тарифы!$N$60 -> 141.93548 | E40: =Тарифы!$O$60 -> 332.25806 | F40: =Тарифы!$P$60 -> 512.90323 | G40: =Тарифы!$Q$60 -> 1048.3871
B41: =Тарифы!$B$61 -> flux-2-pro · 2MP | C41: =Тарифы!$M$61 -> 23.5 | D41: =Тарифы!$N$61 -> 88 | E41: =Тарифы!$O$61 -> 206 | F41: =Тарифы!$P$61 -> 318 | G41: =Тарифы!$Q$61 -> 650
B42: =Тарифы!$B$62 -> seedream-4-5 · до 4K | C42: =Тарифы!$M$62 -> 78.333333 | D42: =Тарифы!$N$62 -> 293.33333 | E42: =Тарифы!$O$62 -> 686.66667 | F42: =Тарифы!$P$62 -> 1060 | G42: =Тарифы!$Q$62 -> 2166.6667
B43: =Тарифы!$B$64 -> happyhorse-1-0 | C43: =Тарифы!$M$64 -> 5.0646552 | D43: =Тарифы!$N$64 -> 18.965517 | E43: =Тарифы!$O$64 -> 44.396552 | F43: =Тарифы!$P$64 -> 68.534483 | G43: =Тарифы!$Q$64 -> 140.08621
B44: =Тарифы!$B$65 -> happyhorse-1-1 | C44: =Тарифы!$M$65 -> 5.0646552 | D44: =Тарифы!$N$65 -> 18.965517 | E44: =Тарифы!$O$65 -> 44.396552 | F44: =Тарифы!$P$65 -> 68.534483 | G44: =Тарифы!$Q$65 -> 140.08621
B45: =Тарифы!$B$66 -> veo-3-1 Quality · 720p | C45: =Тарифы!$M$66 -> 0 | D45: =Тарифы!$N$66 -> 0 | E45: =Тарифы!$O$66 -> 0 | F45: =Тарифы!$P$66 -> 0 | G45: =Тарифы!$Q$66 -> 0
B46: =Тарифы!$B$67 -> veo-3-1-fast · 720p | C46: =Тарифы!$M$67 -> 0 | D46: =Тарифы!$N$67 -> 0 | E46: =Тарифы!$O$67 -> 0 | F46: =Тарифы!$P$67 -> 0 | G46: =Тарифы!$Q$67 -> 0
B47: =Тарифы!$B$68 -> veo-3-1-lite · 720p | C47: =Тарифы!$M$68 -> 0 | D47: =Тарифы!$N$68 -> 0 | E47: =Тарифы!$O$68 -> 0 | F47: =Тарифы!$P$68 -> 0 | G47: =Тарифы!$Q$68 -> 0
B49: =Тарифы!$B$70 -> grok-imagine · 720p · Kie | C49: =Тарифы!$M$70 -> 26.111111 | D49: =Тарифы!$N$70 -> 97.777778 | E49: =Тарифы!$O$70 -> 228.88889 | F49: =Тарифы!$P$70 -> 353.33333 | G49: =Тарифы!$Q$70 -> 722.22222
B50: =Тарифы!$B$71 -> gemini-omni-flash · 720p | C50: =Тарифы!$M$71 -> 4.1666667 | D50: =Тарифы!$N$71 -> 15.602837 | E50: =Тарифы!$O$71 -> 36.524823 | F50: =Тарифы!$P$71 -> 56.382979 | G50: =Тарифы!$Q$71 -> 115.24823
B51: =Тарифы!$B$72 -> seedance-2-0 · 1080p · OpenRouter | C51: =Тарифы!$M$72 -> 1.8302181 | D51: =Тарифы!$N$72 -> 6.8535826 | E51: =Тарифы!$O$72 -> 16.043614 | F51: =Тарифы!$P$72 -> 24.766355 | G51: =Тарифы!$Q$72 -> 50.623053
B52: =Тарифы!$B$73 -> seedance-2-0-fast · 720p | C52: =Тарифы!$M$73 -> 5.6490385 | D52: =Тарифы!$N$73 -> 21.153846 | E52: =Тарифы!$O$73 -> 49.519231 | F52: =Тарифы!$P$73 -> 76.442308 | G52: =Тарифы!$Q$73 -> 156.25
B53: =Тарифы!$B$74 -> wan-2-7 · 720p (kie) | C53: =Тарифы!$M$74 -> 0 | D53: =Тарифы!$N$74 -> 0 | E53: =Тарифы!$O$74 -> 0 | F53: =Тарифы!$P$74 -> 0 | G53: =Тарифы!$Q$74 -> 0
B54: =Тарифы!$B$75 -> kling-v3-standard | C54: =Тарифы!$M$75 -> 3.3571429 | D54: =Тарифы!$N$75 -> 12.571429 | E54: =Тарифы!$O$75 -> 29.428571 | F54: =Тарифы!$P$75 -> 45.428571 | G54: =Тарифы!$Q$75 -> 92.857143
B55: =Тарифы!$B$91 -> seedream-5-0-pro · 1K | C55: =Тарифы!$M$91 -> 78.333333 | D55: =Тарифы!$N$91 -> 293.33333 | E55: =Тарифы!$O$91 -> 686.66667 | F55: =Тарифы!$P$91 -> 1060 | G55: =Тарифы!$Q$91 -> 2166.6667
B56: =Тарифы!$B$92 -> seedream-5-0-lite | C56: =Тарифы!$M$92 -> 117.5 | D56: =Тарифы!$N$92 -> 440 | E56: =Тарифы!$O$92 -> 1030 | F56: =Тарифы!$P$92 -> 1590 | G56: =Тарифы!$Q$92 -> 3250
B57: Видео — при типовой длине клипа из матрицы.

Sheet Сводная
B2: СВОДНАЯ — ЦЕНЫ ($ и ₽) И ГЕНЕРАЦИИ ПО МОДЕЛЯМ: МЫ · SYNTX · HIGGSFIELD
B3: ₽-цена конкурентов = $ × курс × (1+5% потерь ВТБ при оплате из РФ). Наша $-цена — справочно (₽ ÷ курс).
B5: VERTOV
B6: Цена, $/мес → | C6: =Тарифы!C7/Технический!$C$17 -> 7.0470588 | D6: =Тарифы!D7/Технический!$C$17 -> 19.4 | E6: =Тарифы!E7/Технический!$C$17 -> 44.694118 | F6: =Тарифы!F7/Технический!$C$17 -> 68.223529 | G6: =Тарифы!G7/Технический!$C$17 -> 137.63529
B7: Цена, ₽/мес (для РФ) → | C7: =Тарифы!C7 -> 599 | D7: =Тарифы!D7 -> 1649 | E7: =Тарифы!E7 -> 3799 | F7: =Тарифы!F7 -> 5799 | G7: =Тарифы!G7 -> 11699
B8: Модель | C8: Start | D8: Pro | E8: Studio | F8: Elite | G8: Ultra
B9: =Тарифы!$B$54 -> nano-banana | C9: =Тарифы!$M$54 -> 146.875 | D9: =Тарифы!$N$54 -> 550 | E9: =Тарифы!$O$54 -> 1287.5 | F9: =Тарифы!$P$54 -> 1987.5 | G9: =Тарифы!$Q$54 -> 4062.5
B10: =Тарифы!$B$55 -> recraft-v4 | C10: =Тарифы!$M$55 -> 47 | D10: =Тарифы!$N$55 -> 176 | E10: =Тарифы!$O$55 -> 412 | F10: =Тарифы!$P$55 -> 636 | G10: =Тарифы!$Q$55 -> 1300
B11: =Тарифы!$B$56 -> gpt-image-2 | C11: =Тарифы!$M$56 -> 117.5 | D11: =Тарифы!$N$56 -> 440 | E11: =Тарифы!$O$56 -> 1030 | F11: =Тарифы!$P$56 -> 1590 | G11: =Тарифы!$Q$56 -> 3250
B12: =Тарифы!$B$57 -> recraft-v4-vector | C12: =Тарифы!$M$57 -> 29.375 | D12: =Тарифы!$N$57 -> 110 | E12: =Тарифы!$O$57 -> 257.5 | F12: =Тарифы!$P$57 -> 397.5 | G12: =Тарифы!$Q$57 -> 812.5
B13: =Тарифы!$B$58 -> nano-banana-2-lite | C13: =Тарифы!$M$58 -> 146.875 | D13: =Тарифы!$N$58 -> 550 | E13: =Тарифы!$O$58 -> 1287.5 | F13: =Тарифы!$P$58 -> 1987.5 | G13: =Тарифы!$Q$58 -> 4062.5
B14: =Тарифы!$B$59 -> nano-banana-2 | C14: =Тарифы!$M$59 -> 69.117647 | D14: =Тарифы!$N$59 -> 258.82353 | E14: =Тарифы!$O$59 -> 605.88235 | F14: =Тарифы!$P$59 -> 935.29412 | G14: =Тарифы!$Q$59 -> 1911.7647
B15: =Тарифы!$B$60 -> nano-banana-pro | C15: =Тарифы!$M$60 -> 37.903226 | D15: =Тарифы!$N$60 -> 141.93548 | E15: =Тарифы!$O$60 -> 332.25806 | F15: =Тарифы!$P$60 -> 512.90323 | G15: =Тарифы!$Q$60 -> 1048.3871
B16: =Тарифы!$B$61 -> flux-2-pro · 2MP | C16: =Тарифы!$M$61 -> 23.5 | D16: =Тарифы!$N$61 -> 88 | E16: =Тарифы!$O$61 -> 206 | F16: =Тарифы!$P$61 -> 318 | G16: =Тарифы!$Q$61 -> 650
B17: =Тарифы!$B$62 -> seedream-4-5 · до 4K | C17: =Тарифы!$M$62 -> 78.333333 | D17: =Тарифы!$N$62 -> 293.33333 | E17: =Тарифы!$O$62 -> 686.66667 | F17: =Тарифы!$P$62 -> 1060 | G17: =Тарифы!$Q$62 -> 2166.6667
B18: =Тарифы!$B$64 -> happyhorse-1-0 | C18: =Тарифы!$M$64 -> 5.0646552 | D18: =Тарифы!$N$64 -> 18.965517 | E18: =Тарифы!$O$64 -> 44.396552 | F18: =Тарифы!$P$64 -> 68.534483 | G18: =Тарифы!$Q$64 -> 140.08621
B19: =Тарифы!$B$65 -> happyhorse-1-1 | C19: =Тарифы!$M$65 -> 5.0646552 | D19: =Тарифы!$N$65 -> 18.965517 | E19: =Тарифы!$O$65 -> 44.396552 | F19: =Тарифы!$P$65 -> 68.534483 | G19: =Тарифы!$Q$65 -> 140.08621
B20: =Тарифы!$B$66 -> veo-3-1 Quality · 720p | C20: =Тарифы!$M$66 -> 0 | D20: =Тарифы!$N$66 -> 0 | E20: =Тарифы!$O$66 -> 0 | F20: =Тарифы!$P$66 -> 0 | G20: =Тарифы!$Q$66 -> 0
B21: =Тарифы!$B$67 -> veo-3-1-fast · 720p | C21: =Тарифы!$M$67 -> 0 | D21: =Тарифы!$N$67 -> 0 | E21: =Тарифы!$O$67 -> 0 | F21: =Тарифы!$P$67 -> 0 | G21: =Тарифы!$Q$67 -> 0
B22: =Тарифы!$B$68 -> veo-3-1-lite · 720p | C22: =Тарифы!$M$68 -> 0 | D22: =Тарифы!$N$68 -> 0 | E22: =Тарифы!$O$68 -> 0 | F22: =Тарифы!$P$68 -> 0 | G22: =Тарифы!$Q$68 -> 0
B24: =Тарифы!$B$70 -> grok-imagine · 720p · Kie | C24: =Тарифы!$M$70 -> 26.111111 | D24: =Тарифы!$N$70 -> 97.777778 | E24: =Тарифы!$O$70 -> 228.88889 | F24: =Тарифы!$P$70 -> 353.33333 | G24: =Тарифы!$Q$70 -> 722.22222
B25: =Тарифы!$B$71 -> gemini-omni-flash · 720p | C25: =Тарифы!$M$71 -> 4.1666667 | D25: =Тарифы!$N$71 -> 15.602837 | E25: =Тарифы!$O$71 -> 36.524823 | F25: =Тарифы!$P$71 -> 56.382979 | G25: =Тарифы!$Q$71 -> 115.24823
B26: =Тарифы!$B$72 -> seedance-2-0 · 1080p · OpenRouter | C26: =Тарифы!$M$72 -> 1.8302181 | D26: =Тарифы!$N$72 -> 6.8535826 | E26: =Тарифы!$O$72 -> 16.043614 | F26: =Тарифы!$P$72 -> 24.766355 | G26: =Тарифы!$Q$72 -> 50.623053
B27: =Тарифы!$B$73 -> seedance-2-0-fast · 720p | C27: =Тарифы!$M$73 -> 5.6490385 | D27: =Тарифы!$N$73 -> 21.153846 | E27: =Тарифы!$O$73 -> 49.519231 | F27: =Тарифы!$P$73 -> 76.442308 | G27: =Тарифы!$Q$73 -> 156.25
B28: =Тарифы!$B$74 -> wan-2-7 · 720p (kie) | C28: =Тарифы!$M$74 -> 0 | D28: =Тарифы!$N$74 -> 0 | E28: =Тарифы!$O$74 -> 0 | F28: =Тарифы!$P$74 -> 0 | G28: =Тарифы!$Q$74 -> 0
B29: =Тарифы!$B$75 -> kling-v3-standard | C29: =Тарифы!$M$75 -> 3.3571429 | D29: =Тарифы!$N$75 -> 12.571429 | E29: =Тарифы!$O$75 -> 29.428571 | F29: =Тарифы!$P$75 -> 45.428571 | G29: =Тарифы!$Q$75 -> 92.857143
B30: =Тарифы!$B$91 -> seedream-5-0-pro · 1K | C30: =Тарифы!$M$91 -> 78.333333 | D30: =Тарифы!$N$91 -> 293.33333 | E30: =Тарифы!$O$91 -> 686.66667 | F30: =Тарифы!$P$91 -> 1060 | G30: =Тарифы!$Q$91 -> 2166.6667
B31: =Тарифы!$B$92 -> seedream-5-0-lite | C31: =Тарифы!$M$92 -> 117.5 | D31: =Тарифы!$N$92 -> 440 | E31: =Тарифы!$O$92 -> 1030 | F31: =Тарифы!$P$92 -> 1590 | G31: =Тарифы!$Q$92 -> 3250
B33: SYNTX (прямой конкурент)
B34: Цена, $/мес → | C34: =Технический!C107/Технический!$C$17 -> 10.470588 | D34: =Технический!D107/Технический!$C$17 -> 19.882353 | E34: =Технический!E107/Технический!$C$17 -> 46.941176 | F34: =Технический!F107/Технический!$C$17 -> 70.470588 | G34: =Технический!G107/Технический!$C$17 -> 141.05882
B35: Цена, ₽/мес (для РФ) → | C35: =Технический!C107 -> 890 | D35: =Технический!D107 -> 1690 | E35: =Технический!E107 -> 3990 | F35: =Технический!F107 -> 5990 | G35: =Технический!G107 -> 11990
B36: Модель | C36: Basic | D36: Pro | E36: VIP | F36: Elite | G36: Ultra El.
B37: =Тарифы!$B$54 -> nano-banana | C37: =Тарифы!$S$54 -> 173.33333 | D37: =Тарифы!$T$54 -> 457 | E37: =Тарифы!$U$54 -> 1133.3333 | F37: =Тарифы!$V$54 -> 1733.3333 | G37: =Тарифы!$W$54 -> 2000
B38: =Тарифы!$B$55 -> recraft-v4 | C38: =Тарифы!$S$55 | D38: =Тарифы!$T$55 | E38: =Тарифы!$U$55 | F38: =Тарифы!$V$55 | G38: =Тарифы!$W$55
B39: =Тарифы!$B$56 -> gpt-image-2 | C39: =Тарифы!$S$56 -> 130 | D39: =Тарифы!$T$56 -> 342.75 | E39: =Тарифы!$U$56 -> 850 | F39: =Тарифы!$V$56 -> 1300 | G39: =Тарифы!$W$56 -> 1500
B40: =Тарифы!$B$57 -> recraft-v4-vector | C40: =Тарифы!$S$57 | D40: =Тарифы!$T$57 | E40: =Тарифы!$U$57 | F40: =Тарифы!$V$57 | G40: =Тарифы!$W$57
B41: =Тарифы!$B$58 -> nano-banana-2-lite | C41: =Тарифы!$S$58 -> 200 | D41: =Тарифы!$T$58 -> 527.30769 | E41: =Тарифы!$U$58 -> 1307.6923 | F41: =Тарифы!$V$58 -> 2000 | G41: =Тарифы!$W$58 -> 2307.6923
B42: =Тарифы!$B$59 -> nano-banana-2 | C42: =Тарифы!$S$59 -> 86.666667 | D42: =Тарифы!$T$59 -> 228.5 | E42: =Тарифы!$U$59 -> 566.66667 | F42: =Тарифы!$V$59 -> 866.66667 | G42: =Тарифы!$W$59 -> 1000
B43: =Тарифы!$B$60 -> nano-banana-pro | C43: =Тарифы!$S$60 -> 130 | D43: =Тарифы!$T$60 -> 342.75 | E43: =Тарифы!$U$60 -> 850 | F43: =Тарифы!$V$60 -> 1300 | G43: =Тарифы!$W$60 -> 1500
B44: =Тарифы!$B$61 -> flux-2-pro · 2MP | C44: =Тарифы!$S$61 | D44: =Тарифы!$T$61 | E44: =Тарифы!$U$61 | F44: =Тарифы!$V$61 | G44: =Тарифы!$W$61
B45: =Тарифы!$B$62 -> seedream-4-5 · до 4K | C45: =Тарифы!$S$62 -> 130 | D45: =Тарифы!$T$62 -> 342.75 | E45: =Тарифы!$U$62 -> 850 | F45: =Тарифы!$V$62 -> 1300 | G45: =Тарифы!$W$62 -> 1500
B46: =Тарифы!$B$64 -> happyhorse-1-0 | C46: =Тарифы!$S$64 -> 5.7777778 | D46: =Тарифы!$T$64 -> 15.233333 | E46: =Тарифы!$U$64 -> 37.777778 | F46: =Тарифы!$V$64 -> 57.777778 | G46: =Тарифы!$W$64 -> 66.666667
B47: =Тарифы!$B$65 -> happyhorse-1-1 | C47: =Тарифы!$S$65 -> 5.7777778 | D47: =Тарифы!$T$65 -> 15.233333 | E47: =Тарифы!$U$65 -> 37.777778 | F47: =Тарифы!$V$65 -> 57.777778 | G47: =Тарифы!$W$65 -> 66.666667
B48: =Тарифы!$B$66 -> veo-3-1 Quality · 720p | C48: =Тарифы!$S$66 -> 0 | D48: =Тарифы!$T$66 -> 0 | E48: =Тарифы!$U$66 -> 0 | F48: =Тарифы!$V$66 -> 0 | G48: =Тарифы!$W$66 -> 0
B49: =Тарифы!$B$67 -> veo-3-1-fast · 720p | C49: =Тарифы!$S$67 -> 0 | D49: =Тарифы!$T$67 -> 0 | E49: =Тарифы!$U$67 -> 0 | F49: =Тарифы!$V$67 -> 0 | G49: =Тарифы!$W$67 -> 0
B50: =Тарифы!$B$68 -> veo-3-1-lite · 720p | C50: =Тарифы!$S$68 -> 0 | D50: =Тарифы!$T$68 -> 0 | E50: =Тарифы!$U$68 -> 0 | F50: =Тарифы!$V$68 -> 0 | G50: =Тарифы!$W$68 -> 0
B52: =Тарифы!$B$70 -> grok-imagine · 720p · Kie | C52: =Тарифы!$S$70 -> 32.5 | D52: =Тарифы!$T$70 -> 85.6875 | E52: =Тарифы!$U$70 -> 212.5 | F52: =Тарифы!$V$70 -> 325 | G52: =Тарифы!$W$70 -> 375
B53: =Тарифы!$B$71 -> gemini-omni-flash · 720p | C53: =Тарифы!$S$71 -> 9.2857143 | D53: =Тарифы!$T$71 -> 24.482143 | E53: =Тарифы!$U$71 -> 60.714286 | F53: =Тарифы!$V$71 -> 92.857143 | G53: =Тарифы!$W$71 -> 107.14286
B54: =Тарифы!$B$72 -> seedance-2-0 · 1080p · OpenRouter | C54: =Тарифы!$S$72 -> 2.3152271 | D54: =Тарифы!$T$72 -> 6.1041852 | E54: =Тарифы!$U$72 -> 15.138023 | F54: =Тарифы!$V$72 -> 23.152271 | G54: =Тарифы!$W$72 -> 26.714159
B55: =Тарифы!$B$73 -> seedance-2-0-fast · 720p | C55: =Тарифы!$S$73 -> 7.1625344 | D55: =Тарифы!$T$73 -> 18.884298 | E55: =Тарифы!$U$73 -> 46.831956 | F55: =Тарифы!$V$73 -> 71.625344 | G55: =Тарифы!$W$73 -> 82.644628
B56: =Тарифы!$B$74 -> wan-2-7 · 720p (kie) | C56: =Тарифы!$S$74 -> 0 | D56: =Тарифы!$T$74 -> 0 | E56: =Тарифы!$U$74 -> 0 | F56: =Тарифы!$V$74 -> 0 | G56: =Тарифы!$W$74 -> 0
B57: =Тарифы!$B$75 -> kling-v3-standard | C57: =Тарифы!$S$75 -> 10.4 | D57: =Тарифы!$T$75 -> 27.42 | E57: =Тарифы!$U$75 -> 68 | F57: =Тарифы!$V$75 -> 104 | G57: =Тарифы!$W$75 -> 120
B58: =Тарифы!$B$91 -> seedream-5-0-pro · 1K | C58: =Тарифы!$S$91 -> 86.666667 | D58: =Тарифы!$T$91 -> 228.5 | E58: =Тарифы!$U$91 -> 566.66667 | F58: =Тарифы!$V$91 -> 866.66667 | G58: =Тарифы!$W$91 -> 1000
B59: =Тарифы!$B$92 -> seedream-5-0-lite | C59: =Тарифы!$S$92 -> 130 | D59: =Тарифы!$T$92 -> 342.75 | E59: =Тарифы!$U$92 -> 850 | F59: =Тарифы!$V$92 -> 1300 | G59: =Тарифы!$W$92 -> 1500
B61: HIGGSFIELD (глобальный конкурент)
B62: Цена, $/мес → | C62: =Технический!H112 -> 19 | D62: =Технический!H110 -> 59 | E62: =Технический!H111 -> 129
B63: Цена, ₽/мес (для РФ) → | C63: =Технический!H112*Технический!$C$17*(1+Технический!$C$111) -> 1695.75 | D63: =Технический!H110*Технический!$C$17*(1+Технический!$C$111) -> 5265.75 | E63: =Технический!H111*Технический!$C$17*(1+Технический!$C$111) -> 11513.25
B64: Модель | C64: Starter | D64: Plus | E64: Ultra
B65: =Тарифы!$B$54 -> nano-banana | C65: =Тарифы!$Y$54 -> 270 | D65: =Тарифы!$Z$54 -> 1200 | E65: =Тарифы!$AA$54 -> 3000
B66: =Тарифы!$B$55 -> recraft-v4 | C66: =Тарифы!$Y$55 -> 216 | D66: =Тарифы!$Z$55 -> 960 | E66: =Тарифы!$AA$55 -> 2400
B67: =Тарифы!$B$56 -> gpt-image-2 | C67: =Тарифы!$Y$56 -> 135 | D67: =Тарифы!$Z$56 -> 600 | E67: =Тарифы!$AA$56 -> 1500
B68: =Тарифы!$B$57 -> recraft-v4-vector | C68: =Тарифы!$Y$57 -> 108 | D68: =Тарифы!$Z$57 -> 480 | E68: =Тарифы!$AA$57 -> 1200
B69: =Тарифы!$B$58 -> nano-banana-2-lite | C69: =Тарифы!$Y$58 -> 270 | D69: =Тарифы!$Z$58 -> 1200 | E69: =Тарифы!$AA$58 -> 3000
B70: =Тарифы!$B$59 -> nano-banana-2 | C70: =Тарифы!$Y$59 -> 135 | D70: =Тарифы!$Z$59 -> 600 | E70: =Тарифы!$AA$59 -> 1500
B71: =Тарифы!$B$60 -> nano-banana-pro | C71: =Тарифы!$Y$60 -> 135 | D71: =Тарифы!$Z$60 -> 600 | E71: =Тарифы!$AA$60 -> 1500
B72: =Тарифы!$B$61 -> flux-2-pro · 2MP | C72: =Тарифы!$Y$61 -> 180 | D72: =Тарифы!$Z$61 -> 800 | E72: =Тарифы!$AA$61 -> 2000
B73: =Тарифы!$B$62 -> seedream-4-5 · до 4K | C73: =Тарифы!$Y$62 -> 270 | D73: =Тарифы!$Z$62 -> 1200 | E73: =Тарифы!$AA$62 -> 3000
B74: =Тарифы!$B$64 -> happyhorse-1-0 | C74: =Тарифы!$Y$64 -> 12 | D74: =Тарифы!$Z$64 -> 53.333333 | E74: =Тарифы!$AA$64 -> 133.33333
B75: =Тарифы!$B$65 -> happyhorse-1-1 | C75: =Тарифы!$Y$65 -> 12 | D75: =Тарифы!$Z$65 -> 53.333333 | E75: =Тарифы!$AA$65 -> 133.33333
B76: =Тарифы!$B$66 -> veo-3-1 Quality · 720p | C76: =Тарифы!$Y$66 -> 0 | D76: =Тарифы!$Z$66 -> 0 | E76: =Тарифы!$AA$66 -> 0
B77: =Тарифы!$B$67 -> veo-3-1-fast · 720p | C77: =Тарифы!$Y$67 -> 0 | D77: =Тарифы!$Z$67 -> 0 | E77: =Тарифы!$AA$67 -> 0
B78: =Тарифы!$B$68 -> veo-3-1-lite · 720p | C78: =Тарифы!$Y$68 -> 0 | D78: =Тарифы!$Z$68 -> 0 | E78: =Тарифы!$AA$68 -> 0
B80: =Тарифы!$B$70 -> grok-imagine · 720p · Kie | C80: =Тарифы!$Y$70 -> 30 | D80: =Тарифы!$Z$70 -> 133.33333 | E80: =Тарифы!$AA$70 -> 333.33333
B81: =Тарифы!$B$71 -> gemini-omni-flash · 720p | C81: =Тарифы!$Y$71 -> 11.25 | D81: =Тарифы!$Z$71 -> 50 | E81: =Тарифы!$AA$71 -> 125
B82: =Тарифы!$B$72 -> seedance-2-0 · 1080p · OpenRouter | C82: =Тарифы!$Y$72 -> 6 | D82: =Тарифы!$Z$72 -> 26.666667 | E82: =Тарифы!$AA$72 -> 66.666667
B83: =Тарифы!$B$73 -> seedance-2-0-fast · 720p | C83: =Тарифы!$Y$73 -> 15.428571 | D83: =Тарифы!$Z$73 -> 68.571429 | E83: =Тарифы!$AA$73 -> 171.42857
B84: =Тарифы!$B$74 -> wan-2-7 · 720p (kie) | C84: =Тарифы!$Y$74 -> 0 | D84: =Тарифы!$Z$74 -> 0 | E84: =Тарифы!$AA$74 -> 0
B85: =Тарифы!$B$75 -> kling-v3-standard | C85: =Тарифы!$Y$75 -> 27 | D85: =Тарифы!$Z$75 -> 120 | E85: =Тарифы!$AA$75 -> 300
B86: =Тарифы!$B$91 -> seedream-5-0-pro · 1K | C86: =Тарифы!$Y$91 -> 180 | D86: =Тарифы!$Z$91 -> 800 | E86: =Тарифы!$AA$91 -> 2000
B87: =Тарифы!$B$92 -> seedream-5-0-lite | C87: =Тарифы!$Y$92 -> 180 | D87: =Тарифы!$Z$92 -> 800 | E87: =Тарифы!$AA$92 -> 2000
B89: RUNWAY и другие
B90: Поле готово — тот же скрейп-промпт, подставь их URL.

Sheet Сетка FX
A1: ГЛАВНЫЙ ЛИСТ. Цены — колонка O «КРЕДИТОВ/КЛИП». Курс 85, кредит 0,331 ₽. ВНИМАНИЕ: колонка I — бенчмарк, на котором построены цены, — содержит ошибку: одно значение продублировано на все разрешения модели. Проверенные значения в колонке T, ФАКТИЧЕСКОЕ сравнение с Syntx в колонке V. Цены заморожены сознательно — решение о снижении отложено. Колонки W–Y показывают цену, сравнение и маржу, если снижение принять.
A2: Правило: кредитов = максимум из трёх (потолок щедрости +28% к Syntx / маржа 25% / безубыток при уходе на резерв). Маржа — ВАЛОВАЯ, только вендорская себестоимость. Fallback legs signed 2026-08-14: gemini-2.5 flash image Kie $0.02 t2i/edit; GPT Image 2 Kie $0.03/$0.05/$0.08 by low/medium/high and t2i/i2i. GPT quality reserves are costed for margin governance but remain unarmed until Kie quality mapping is approved; sell prices unchanged.
A3: КУРС USD/RUB → | B3: 85 | C3: ЕДИНЫЙ КУРС КНИГИ. Синхронизирован с «Технический» C17 и «Аудит цен». Обновлён 03.08.2026. | E3: Landed ₽/$ OpenRouter | F3: =$B$3*1.2492 -> 106.182
A4: Цена кредита, ₽ | B4: 0.331111 | C4: самый дешёвый продаваемый кредит | E4: Landed ₽/$ direct (kie/lao) | F4: =$B$3*1.1839 -> 100.6315
A5: Целевая валовая маржа | B5: 0.25 | C5: на основном поставщике
A6: Маржа в худшей длительности | B6: 0.15 | C6: для veo: маржа на 4-сек клипе при базовом курсе. 15% здесь = 0% при курсе 100 (не в убыток).
AJ7: ЛЕСТНИЦА НОГ ОТКРЫТА НА ТРЕТЬЮ ПОЗИЦИЮ 11.08.2026. Формат готов, НИ ОДНА ставка не подписана: все цифры новых вендоров — опубликованные карточки без инвойса. Правило T4 в силе: неоплаченная ставка не маршрутизируется. | AM7: БАЗА ТАРИФИКАЦИИ ПЕРЕЕХАЛА СО СТРОКИ НА НОГУ 11.08.2026. Раньше строка хранила одну базу на всю лестницу — это и есть дыра, о которой пишет dev: вендор с плоской ценой за клип и вендор с ценой за секунду не могут стоять на одной строке под одной базой. Пусто = нога тарифицируется так же, как строка. | AO7: ПЛОЩАДЬ ВЫДАЧИ В МЕГАПИКСЕЛЯХ — для ног, которые тарифицируются за мегапиксель. Ярлык ступени не является драйвером затрат: у kie «2K» это 1536x1536 = 2,36 МП, а 2048x2048 = 4,19 МП, разница в 1,8 раза при одинаковом названии. Аспект сюда же: 16:9 и 1:1 на «одной ступени» — разная площадь. | AP7: ПОДКЛЮЧЁННОСТЬ МАРШРУТА — ТРЕТЬЯ ОСЬ, ЗАВЕДЕНА 11.08.2026. Ставка отвечает «сколько стоит», выбор вендора — «к кому идём», и ни одна из двух не отвечает «а можем ли мы его позвать». Правило T4 дополняется: неоплаченная ставка не маршрутизируется, И неподключённый маршрут не продаётся. Пусто = не подтверждено; строка с неподключённой первой ногой в экспорт не выгружается.
A8: Модель | B8: Тарификация | C8: Сек в клипе | D8: Мин. сек | E8: Канал | F8: $ за ед. | G8: Резерв канал | H8: $ резерв | I8: I · Syntx ток. — ПРОВЕРЕНО 28.07, задаёт потолок щедрости | J8: J · ЦЕНА НА САЙТЕ сегодня | K8: Себест ₽/клип | L8: Потолок +28% | M8: По марже | N8: Безубыток резерв | O8: O · ЦЕНА ПО ПРАВИЛУ сетки | P8: Кредитов/сек | Q8: Маржа | R8: R · УСТАРЕЛО — считается от ошибочного I. НЕ ЧИТАТЬ | T8: T · Syntx токены — ПРОВЕРЕНО | U8: Источник / статус | V8: V · vs Syntx ФАКТ (при ценах O) | W8: Цена по проверенному потолку | X8: vs Syntx при этой цене | Y8: Маржа при этой цене | Z8: Z · ступень качества +15% | AA8: СПИСЫВАТЬ — кредитов | AB8: за сколько секунд | AC8: кредитов за секунду | AD8: Посредник — основная нога | AE8: Посредник — резервная нога | AF8: SKU у поставщика | AG8: Достоверность | AH8: ПОРОГ МАРЖИ строки | AI8: AI · РИСК МАРШРУТА | AJ8: AJ · Посредник — 3-я нога | AK8: AK · Канал 3-й ноги | AL8: AL · $ за ед., 3-я нога | AM8: AM · База тариф. — нога 2 | AN8: AN · База тариф. — нога 3 | AO8: AO · Площадь выдачи, МП | AP8: AP · Маршрут ноги 1 подключён | AQ8: AQ · Маршрут ноги 2 подключён | AR8: AR · Маршрут ноги 3 подключён
A9: Veo Quality 720p | B9: за клип | C9: 8 | D9: 8 | E9: direct | F9: 1.25 | G9: — | H9: — | I9: 119 | J9: 850 | K9: =F9*1*IF(E9="OpenRouter",$F$3,$F$4) -> 125.78938 | L9: =ROUNDUP(5.014*I9,0) -> 597 | M9: =ROUNDUP(K9*(C9/D9)/($B$4*(1-AH9)),0) -> 507 | N9: 0 | O9: =MAX(L9,M9,N9) -> 597 | P9: =ROUND(O9/C9,0) -> 75 | Q9: =1-K9/(O9*$B$4) -> 0.36365004 | T9: 119 | U9: публичный прайс Syntx, подтверждён владельцем 03.08.2026 | V9: =(4400/O9)/(685.5/T9)-1 -> 0.27943388 | W9: =MAX(ROUNDUP(5.014*T9,0),M9,N9) -> 597 | X9: =(4400/W9)/(685.5/T9)-1 -> 0.27943388 | Y9: =1-K9/(W9*$B$4) -> 0.36365004 | AA9: =O9 -> 597 | AB9: =C9 -> 8 | AC9: =IF(B9="шт","—",P9) -> 75 | AD9: Kie | AE9: — | AF9: veo-3-1 | AG9: HIGH — бенчмарк Syntx подтверждён владельцем 03.08.2026 | AH9: 0.25 | AP9: да
A10: Veo Quality 1080p | B10: за клип | C10: 8 | D10: 8 | E10: direct | F10: 1.275 | G10: — | H10: — | I10: 119 | J10: 867 | K10: =F10*1*IF(E10="OpenRouter",$F$3,$F$4) -> 128.30516 | L10: =ROUNDUP(5.014*I10,0) -> 597 | M10: =ROUNDUP(K10*(C10/D10)/($B$4*(1-AH10)),0) -> 517 | N10: 0 | O10: =MAX(L10,M10,N10) -> 597 | P10: =ROUND(O10/C10,0) -> 75 | Q10: =1-K10/(O10*$B$4) -> 0.35092304 | T10: 119 | U10: публичный прайс Syntx, подтверждён владельцем 03.08.2026 | V10: =(4400/O10)/(685.5/T10)-1 -> 0.27943388 | W10: =MAX(ROUNDUP(5.014*T10,0),M10,N10) -> 597 | X10: =(4400/W10)/(685.5/T10)-1 -> 0.27943388 | Y10: =1-K10/(W10*$B$4) -> 0.35092304 | AA10: =O10 -> 597 | AB10: =C10 -> 8 | AC10: =IF(B10="шт","—",P10) -> 75 | AD10: Kie | AE10: — | AF10: veo-3-1 | AG10: HIGH — бенчмарк Syntx подтверждён владельцем 03.08.2026 | AH10: 0.25 | AP10: да
A11: Veo Fast 720p | B11: за клип | C11: 8 | D11: 8 | E11: direct | F11: 0.3 | G11: — | H11: — | I11: 19 | J11: 213 | K11: =F11*1*IF(E11="OpenRouter",$F$3,$F$4) -> 30.18945 | L11: =ROUNDUP(5.014*I11,0) -> 96 | M11: =ROUNDUP(K11*(C11/D11)/($B$4*(1-AH11)),0) -> 122 | N11: 0 | O11: =MAX(L11,M11,N11) -> 122 | P11: =ROUND(O11/C11,0) -> 15 | Q11: =1-K11/(O11*$B$4) -> 0.25265392 | T11: 19 | U11: публичный прайс Syntx, подтверждён владельцем 03.08.2026 | V11: =(4400/O11)/(685.5/T11)-1 -> -0.00037067595 | W11: =MAX(ROUNDUP(5.014*T11,0),M11,N11) -> 122 | X11: =(4400/W11)/(685.5/T11)-1 -> -0.00037067595 | Y11: =1-K11/(W11*$B$4) -> 0.25265392 | AA11: =O11 -> 122 | AB11: =C11 -> 8 | AC11: =IF(B11="шт","—",P11) -> 15 | AD11: Kie | AE11: — | AF11: veo-3-1 | AG11: HIGH — бенчмарк Syntx подтверждён владельцем 03.08.2026 | AH11: 0.25 | AP11: да
A12: Veo Fast 1080p | B12: за клип | C12: 8 | D12: 8 | E12: direct | F12: 0.325 | G12: — | H12: — | I12: 19 | J12: 255 | K12: =F12*1*IF(E12="OpenRouter",$F$3,$F$4) -> 32.705238 | L12: =ROUNDUP(5.014*I12,0) -> 96 | M12: =ROUNDUP(K12*(C12/D12)/($B$4*(1-AH12)),0) -> 132 | N12: 0 | O12: =MAX(L12,M12,N12) -> 132 | P12: =ROUND(O12/C12,0) -> 17 | Q12: =1-K12/(O12*$B$4) -> 0.2517103 | T12: 19 | U12: публичный прайс Syntx, подтверждён владельцем 03.08.2026 | V12: =(4400/O12)/(685.5/T12)-1 -> -0.07610017 | W12: =MAX(ROUNDUP(5.014*T12,0),M12,N12) -> 132 | X12: =(4400/W12)/(685.5/T12)-1 -> -0.07610017 | Y12: =1-K12/(W12*$B$4) -> 0.2517103 | AA12: =O12 -> 132 | AB12: =C12 -> 8 | AC12: =IF(B12="шт","—",P12) -> 17 | AD12: Kie | AE12: — | AF12: veo-3-1 | AG12: HIGH — бенчмарк Syntx подтверждён владельцем 03.08.2026 | AH12: 0.25 | AP12: да
A13: Veo Lite 720p | B13: за клип | C13: 8 | D13: 8 | E13: direct | F13: 0.15 | G13: — | H13: — | I13: 13 | J13: 107 | K13: =F13*1*IF(E13="OpenRouter",$F$3,$F$4) -> 15.094725 | L13: =ROUNDUP(5.014*I13,0) -> 66 | M13: =ROUNDUP(K13*(C13/D13)/($B$4*(1-AH13)),0) -> 61 | N13: 0 | O13: =MAX(L13,M13,N13) -> 66 | P13: =ROUND(O13/C13,0) -> 8 | Q13: =1-K13/(O13*$B$4) -> 0.30927105 | T13: 13 | U13: публичный прайс Syntx, подтверждён владельцем 03.08.2026 | V13: =(4400/O13)/(685.5/T13)-1 -> 0.26428398 | W13: =MAX(ROUNDUP(5.014*T13,0),M13,N13) -> 66 | X13: =(4400/W13)/(685.5/T13)-1 -> 0.26428398 | Y13: =1-K13/(W13*$B$4) -> 0.30927105 | AA13: =O13 -> 66 | AB13: =C13 -> 8 | AC13: =IF(B13="шт","—",P13) -> 8 | AD13: Kie | AE13: — | AF13: veo-3-1 | AG13: HIGH — бенчмарк Syntx подтверждён владельцем 03.08.2026 | AH13: 0.25 | AP13: да
A14: Veo Lite 1080p | B14: за клип | C14: 8 | D14: 8 | E14: direct | F14: 0.175 | G14: — | H14: — | I14: 13 | J14: 170 | K14: =F14*1*IF(E14="OpenRouter",$F$3,$F$4) -> 17.610512 | L14: =ROUNDUP(5.014*I14,0) -> 66 | M14: =ROUNDUP(K14*(C14/D14)/($B$4*(1-AH14)),0) -> 71 | N14: 0 | O14: =MAX(L14,M14,N14) -> 71 | P14: =ROUND(O14/C14,0) -> 9 | Q14: =1-K14/(O14*$B$4) -> 0.25089959 | T14: 13 | U14: публичный прайс Syntx, подтверждён владельцем 03.08.2026 | V14: =(4400/O14)/(685.5/T14)-1 -> 0.17524989 | W14: =MAX(ROUNDUP(5.014*T14,0),M14,N14) -> 71 | X14: =(4400/W14)/(685.5/T14)-1 -> 0.17524989 | Y14: =1-K14/(W14*$B$4) -> 0.25089959 | AA14: =O14 -> 71 | AB14: =C14 -> 8 | AC14: =IF(B14="шт","—",P14) -> 9 | AD14: Kie | AE14: — | AF14: veo-3-1 | AG14: HIGH — бенчмарк Syntx подтверждён владельцем 03.08.2026 | AH14: 0.25 | AP14: да
A15: Seedance 2.0 4K | B15: сек | C15: 5 | D15: 5 | E15: direct | F15: 1.04 | G15: — | H15: — | I15: — | K15: =F15*C15*IF(E15="OpenRouter",$F$3,$F$4) -> 523.2838 | L15: 0 | M15: =ROUNDUP(K15*(C15/D15)/($B$4*(1-IF(B15="фикс",$B$6,AH15))),0) -> 2108 | N15: 0 | O15: =MAX(L15,M15,N15) -> 2108 | P15: =ROUND(O15/C15,0) -> 422 | Q15: =1-K15/(O15*$B$4) -> 0.2502904 | U15: ЦЕНА СНИЖЕНА 11.08.2026. Держал её член «безубыточность резерва»: цена выставлялась так, чтобы переключение на OpenRouter ($1,361/с) прошло в ноль. Но по R-11 от 27.07 Seedance 4K НИКОГДА не переключается — при 84,8 ₽ убытка на генерацию одна ступень съедала бы дневной лимит за шестьдесят роликов. То есть мы брали с клиента 75 кредитов за страховку, которой сами постановили не пользоваться. Цена теперь считается по единственной ноге, которая реально обслуживает: kie $1,040/с при 25%. ПРИНЦИП: мы берём деньги за страховку, которую готовы заявить, и не берём за ту, от которой отказались письменно. НОГА OPENROUTER СНЯТА, а не просто не оплачена: публиковать ногу, которой по R-11 запрещено пользоваться, значит разрешить движку ею воспользоваться. Строка обслуживается одним kie; при его недоступности 4K не отдаётся, клиенту предлагается 1080p — это и есть решение от 27.07, теперь выраженное данными, а не только текстом. | AA15: =O15 -> 2108 | AB15: =C15 -> 5 | AC15: =IF(B15="шт","—",P15) -> 422 | AD15: Kie | AE15: — | AF15: seedance-2-0 | AG15: HIGH — ставки платно подтверждены; имена посредников исправлены 10.08.2026 (были переставлены) | AH15: =$B$5 -> 0.25 | AP15: да
A16: Seedance 2.0 1080p | B16: сек | C16: 5 | D16: 5 | E16: OpenRouter | F16: 0.34 | G16: direct | H16: 0.51 | I16: 112.25 | J16: 642 | K16: =F16*C16*IF(E16="OpenRouter",$F$3,$F$4) -> 180.5094 | L16: =ROUNDUP(5.014*I16,0) -> 563 | M16: =ROUNDUP(K16*(C16/D16)/($B$4*(1-IF(B16="фикс",$B$6,AH16))),0) -> 727 | N16: =ROUNDUP(H16*C16*IF(G16="OpenRouter",$F$3,$F$4)/$B$4,0) -> 775 | O16: =MAX(L16,M16,N16) -> 775 | P16: =ROUND(O16/C16,0) -> 155 | Q16: =1-K16/(O16*$B$4) -> 0.29656413 | T16: 112.25 | U16: публичный прайс Syntx 28.07.2026, цена «итого», пересчёт на длину нашего клипа РЕШЕНИЕ ВЛАДЕЛЬЦА 11.08.2026 — НАДБАВКА ЗА РЕЗЕРВ ОСТАЁТСЯ. Правило цены остаётся из четырёх членов: MAX(потолок +28% vs Syntx; цена по марже 25%; БЕЗУБЫТОК РЕЗЕРВА; ступень качества +15%). Вопрос ставился и закрыт: четвёртый член перебивает цену на 8 строках из 91, и на этих строках клиент оплачивает вторую ногу. Владелец рассмотрел цену решения и принял её. ЧЕГО ЭТО СТОИТ, ЧТОБЫ НИКТО НЕ ПЕРЕСЧИТЫВАЛ ЗАНОВО: на Seedance 1080p 775 вместо 727 — это −7,0% против Syntx вместо −0,9%, то есть страховка стоит 6 п.п. конкурентоспособности. На Gemini Omni 273 вместо 257 — −34,2% вместо −30,1%. На остальных строках надбавка стоит 1-2 кредита и на сравнение с конкурентом не влияет. ЧТО ЭТО ПОКУПАЕТ: переключение на резерв бесплатно для нас в момент отказа — резерв на этих строках выходит ровно в ноль, а не в минус, поэтому R-1 выполняется без исключений и бюджет отказов по R-11 не расходуется. ИЗВЕСТНОЕ ПОБОЧНОЕ СЛЕДСТВИЕ: при этом правиле добавление ЛЮБОЙ новой ноги может цену только поднять, никогда не опустить. Третья нога, под которую 11.08 открыт формат, работает против клиента до тех пор, пока это правило действует. Пересматривать при подключении первого третьего вендора. | V16: =(4400/O16)/(685.5/T16)-1 -> -0.070327757 | W16: =MAX(ROUNDUP(5.014*T16,0),M16,N16) -> 775 | X16: =(4400/W16)/(685.5/T16)-1 -> -0.070327757 | Y16: =1-K16/(W16*$B$4) -> 0.29656413 | AA16: =O16 -> 775 | AB16: =C16 -> 5 | AC16: =IF(B16="шт","—",P16) -> 155 | AD16: OpenRouter | AE16: Kie | AF16: seedance-2-0 | AG16: HIGH | AH16: =$B$5 -> 0.25 | AP16: да | AQ16: да
A17: Seedance 2.0 720p | B17: сек | C17: 5 | D17: 5 | E17: OpenRouter | F17: 0.151 | G17: direct | H17: 0.205 | I17: 45.375 | J17: 282 | K17: =F17*C17*IF(E17="OpenRouter",$F$3,$F$4) -> 80.16741 | L17: =ROUNDUP(5.014*I17,0) -> 228 | M17: =ROUNDUP(K17*(C17/D17)/($B$4*(1-IF(B17="фикс",$B$6,AH17))),0) -> 323 | N17: =ROUNDUP(H17*C17*IF(G17="OpenRouter",$F$3,$F$4)/$B$4,0) -> 312 | O17: =MAX(L17,M17,N17) -> 323 | P17: =ROUND(O17/C17,0) -> 65 | Q17: =1-K17/(O17*$B$4) -> 0.25041356 | T17: 45.375 | U17: публичный прайс Syntx 28.07.2026, цена «итого», пересчёт на длину нашего клипа | V17: =(4400/O17)/(685.5/T17)-1 -> -0.098305682 | W17: =MAX(ROUNDUP(5.014*T17,0),M17,N17) -> 323 | X17: =(4400/W17)/(685.5/T17)-1 -> -0.098305682 | Y17: =1-K17/(W17*$B$4) -> 0.25041356 | AA17: =O17 -> 323 | AB17: =C17 -> 5 | AC17: =IF(B17="шт","—",P17) -> 65 | AD17: OpenRouter | AE17: Kie | AF17: seedance-2-0 | AG17: HIGH | AH17: =$B$5 -> 0.25 | AP17: да | AQ17: да
A18: Seedance 2.0 480p | B18: сек | C18: 5 | D18: 5 | E18: OpenRouter | F18: 0.067 | G18: direct | H18: 0.095 | I18: 20.375 | J18: 128 | K18: =F18*C18*IF(E18="OpenRouter",$F$3,$F$4) -> 35.57097 | L18: =ROUNDUP(5.014*I18,0) -> 103 | M18: =ROUNDUP(K18*(C18/D18)/($B$4*(1-IF(B18="фикс",$B$6,AH18))),0) -> 144 | N18: =ROUNDUP(H18*C18*IF(G18="OpenRouter",$F$3,$F$4)/$B$4,0) -> 145 | O18: =MAX(L18,M18,N18) -> 145 | P18: =ROUND(O18/C18,0) -> 29 | Q18: =1-K18/(O18*$B$4) -> 0.25910938 | T18: 20.375 | U18: публичный прайс Syntx 28.07.2026, цена «итого», пересчёт на длину нашего клипа РЕШЕНИЕ ВЛАДЕЛЬЦА 11.08.2026 — НАДБАВКА ЗА РЕЗЕРВ ОСТАЁТСЯ. Правило цены остаётся из четырёх членов: MAX(потолок +28% vs Syntx; цена по марже 25%; БЕЗУБЫТОК РЕЗЕРВА; ступень качества +15%). Вопрос ставился и закрыт: четвёртый член перебивает цену на 8 строках из 91, и на этих строках клиент оплачивает вторую ногу. Владелец рассмотрел цену решения и принял её. ЧЕГО ЭТО СТОИТ, ЧТОБЫ НИКТО НЕ ПЕРЕСЧИТЫВАЛ ЗАНОВО: на Seedance 1080p 775 вместо 727 — это −7,0% против Syntx вместо −0,9%, то есть страховка стоит 6 п.п. конкурентоспособности. На Gemini Omni 273 вместо 257 — −34,2% вместо −30,1%. На остальных строках надбавка стоит 1-2 кредита и на сравнение с конкурентом не влияет. ЧТО ЭТО ПОКУПАЕТ: переключение на резерв бесплатно для нас в момент отказа — резерв на этих строках выходит ровно в ноль, а не в минус, поэтому R-1 выполняется без исключений и бюджет отказов по R-11 не расходуется. ИЗВЕСТНОЕ ПОБОЧНОЕ СЛЕДСТВИЕ: при этом правиле добавление ЛЮБОЙ новой ноги может цену только поднять, никогда не опустить. Третья нога, под которую 11.08 открыт формат, работает против клиента до тех пор, пока это правило действует. Пересматривать при подключении первого третьего вендора. | V18: =(4400/O18)/(685.5/T18)-1 -> -0.098065847 | W18: =MAX(ROUNDUP(5.014*T18,0),M18,N18) -> 145 | X18: =(4400/W18)/(685.5/T18)-1 -> -0.098065847 | Y18: =1-K18/(W18*$B$4) -> 0.25910938 | AA18: =O18 -> 145 | AB18: =C18 -> 5 | AC18: =IF(B18="шт","—",P18) -> 29 | AD18: OpenRouter | AE18: Kie | AF18: seedance-2-0 | AG18: HIGH | AH18: =$B$5 -> 0.25 | AP18: да | AQ18: да
A19: Seedance Fast 720p | B19: сек | C19: 5 | D19: 5 | E19: OpenRouter | F19: 0.121 | G19: direct | H19: 0.165 | I19: 36.25 | J19: 208 | K19: =F19*C19*IF(E19="OpenRouter",$F$3,$F$4) -> 64.24011 | L19: =ROUNDUP(5.014*I19,0) -> 182 | M19: =ROUNDUP(K19*(C19/D19)/($B$4*(1-IF(B19="фикс",$B$6,AH19))),0) -> 259 | N19: =ROUNDUP(H19*C19*IF(G19="OpenRouter",$F$3,$F$4)/$B$4,0) -> 251 | O19: =MAX(L19,M19,N19) -> 259 | P19: =ROUND(O19/C19,0) -> 52 | Q19: =1-K19/(O19*$B$4) -> 0.25091189 | T19: 36.25 | U19: публичный прайс Syntx 28.07.2026, цена «итого», пересчёт на длину нашего клипа | V19: =(4400/O19)/(685.5/T19)-1 -> -0.10163367 | W19: =MAX(ROUNDUP(5.014*T19,0),M19,N19) -> 259 | X19: =(4400/W19)/(685.5/T19)-1 -> -0.10163367 | Y19: =1-K19/(W19*$B$4) -> 0.25091189 | AA19: =O19 -> 259 | AB19: =C19 -> 5 | AC19: =IF(B19="шт","—",P19) -> 52 | AD19: OpenRouter | AE19: Kie | AF19: seedance-2-0 | AG19: HIGH | AH19: =$B$5 -> 0.25 | AP19: да | AQ19: да
A20: Seedance Fast 480p | B20: сек | C20: 5 | D20: 5 | E20: OpenRouter | F20: 0.0538 | G20: direct | H20: 0.0775 | I20: 16.375 | J20: 98 | K20: =F20*C20*IF(E20="OpenRouter",$F$3,$F$4) -> 28.562958 | L20: =ROUNDUP(5.014*I20,0) -> 83 | M20: =ROUNDUP(K20*(C20/D20)/($B$4*(1-IF(B20="фикс",$B$6,AH20))),0) -> 116 | N20: =ROUNDUP(H20*C20*IF(G20="OpenRouter",$F$3,$F$4)/$B$4,0) -> 118 | O20: =MAX(L20,M20,N20) -> 118 | P20: =ROUND(O20/C20,0) -> 24 | Q20: =1-K20/(O20*$B$4) -> 0.26894919 | T20: 16.375 | U20: публичный прайс Syntx 28.07.2026, цена «итого», пересчёт на длину нашего клипа РЕШЕНИЕ ВЛАДЕЛЬЦА 11.08.2026 — НАДБАВКА ЗА РЕЗЕРВ ОСТАЁТСЯ. Правило цены остаётся из четырёх членов: MAX(потолок +28% vs Syntx; цена по марже 25%; БЕЗУБЫТОК РЕЗЕРВА; ступень качества +15%). Вопрос ставился и закрыт: четвёртый член перебивает цену на 8 строках из 91, и на этих строках клиент оплачивает вторую ногу. Владелец рассмотрел цену решения и принял её. ЧЕГО ЭТО СТОИТ, ЧТОБЫ НИКТО НЕ ПЕРЕСЧИТЫВАЛ ЗАНОВО: на Seedance 1080p 775 вместо 727 — это −7,0% против Syntx вместо −0,9%, то есть страховка стоит 6 п.п. конкурентоспособности. На Gemini Omni 273 вместо 257 — −34,2% вместо −30,1%. На остальных строках надбавка стоит 1-2 кредита и на сравнение с конкурентом не влияет. ЧТО ЭТО ПОКУПАЕТ: переключение на резерв бесплатно для нас в момент отказа — резерв на этих строках выходит ровно в ноль, а не в минус, поэтому R-1 выполняется без исключений и бюджет отказов по R-11 не расходуется. ИЗВЕСТНОЕ ПОБОЧНОЕ СЛЕДСТВИЕ: при этом правиле добавление ЛЮБОЙ новой ноги может цену только поднять, никогда не опустить. Третья нога, под которую 11.08 открыт формат, работает против клиента до тех пор, пока это правило действует. Пересматривать при подключении первого третьего вендора. | V20: =(4400/O20)/(685.5/T20)-1 -> -0.1092732 | W20: =MAX(ROUNDUP(5.014*T20,0),M20,N20) -> 118 | X20: =(4400/W20)/(685.5/T20)-1 -> -0.1092732 | Y20: =1-K20/(W20*$B$4) -> 0.26894919 | AA20: =O20 -> 118 | AB20: =C20 -> 5 | AC20: =IF(B20="шт","—",P20) -> 24 | AD20: OpenRouter | AE20: Kie | AF20: seedance-2-0 | AG20: HIGH | AH20: =$B$5 -> 0.25 | AP20: да | AQ20: да
A21: HappyHorse 1.1 720p | B21: сек | C21: 5 | D21: 5 | E21: OpenRouter | F21: 0.0988 | G21: direct | H21: 0.1125 | I21: 25 | J21: 232 | K21: =F21*C21*IF(E21="OpenRouter",$F$3,$F$4) -> 52.453908 | L21: =ROUNDUP(5.014*I21,0) -> 126 | M21: =ROUNDUP(K21*(C21/D21)/($B$4*(1-IF(B21="фикс",$B$6,AH21))),0) -> 212 | N21: =ROUNDUP(H21*C21*IF(G21="OpenRouter",$F$3,$F$4)/$B$4,0) -> 171 | O21: =MAX(L21,M21,N21) -> 212 | P21: =ROUND(O21/C21,0) -> 42 | Q21: =1-K21/(O21*$B$4) -> 0.25274577 | T21: 25 | U21: публичный прайс Syntx 28.07.2026, цена «итого», пересчёт на длину нашего клипа | V21: =(4400/O21)/(685.5/T21)-1 -> -0.24308107 | W21: =MAX(ROUNDUP(5.014*T21,0),M21,N21) -> 212 | X21: =(4400/W21)/(685.5/T21)-1 -> -0.24308107 | Y21: =1-K21/(W21*$B$4) -> 0.25274577 | AA21: =O21 -> 212 | AB21: =C21 -> 5 | AC21: =IF(B21="шт","—",P21) -> 42 | AD21: OpenRouter | AE21: Kie | AF21: alibaba/happyhorse-1.1 | AG21: HIGH | AH21: =$B$5 -> 0.25 | AP21: да | AQ21: да
A22: HappyHorse 1.1 1080p | B22: сек | C22: 5 | D22: 5 | E22: OpenRouter | F22: 0.1278 | G22: direct | H22: 0.145 | I22: 45 | J22: 301 | K22: =F22*C22*IF(E22="OpenRouter",$F$3,$F$4) -> 67.850298 | L22: =ROUNDUP(5.014*I22,0) -> 226 | M22: =ROUNDUP(K22*(C22/D22)/($B$4*(1-IF(B22="фикс",$B$6,AH22))),0) -> 274 | N22: =ROUNDUP(H22*C22*IF(G22="OpenRouter",$F$3,$F$4)/$B$4,0) -> 221 | O22: =MAX(L22,M22,N22) -> 274 | P22: =ROUND(O22/C22,0) -> 55 | Q22: =1-K22/(O22*$B$4) -> 0.25212746 | T22: 45 | U22: публичный прайс Syntx 28.07.2026, цена «итого», пересчёт на длину нашего клипа | V22: =(4400/O22)/(685.5/T22)-1 -> 0.054161542 | W22: =MAX(ROUNDUP(5.014*T22,0),M22,N22) -> 274 | X22: =(4400/W22)/(685.5/T22)-1 -> 0.054161542 | Y22: =1-K22/(W22*$B$4) -> 0.25212746 | AA22: =O22 -> 274 | AB22: =C22 -> 5 | AC22: =IF(B22="шт","—",P22) -> 55 | AD22: OpenRouter | AE22: Kie | AF22: alibaba/happyhorse-1.1 | AG22: HIGH | AH22: =$B$5 -> 0.25 | AP22: да | AQ22: да
A23: HappyHorse 1.0 720p — СНЯТО | B23: сек | C23: 5 | D23: 5 | E23: OpenRouter | F23: 0.0988 | G23: direct | H23: 0.14 | I23: 25 | J23: 232 | K23: =F23*C23*IF(E23="OpenRouter",$F$3,$F$4) -> 52.453908 | L23: =ROUNDUP(5.014*I23,0) -> 126 | M23: =ROUNDUP(K23*(C23/D23)/($B$4*(1-IF(B23="фикс",$B$6,AH23))),0) -> 212 | N23: 0 | O23: =MAX(L23,M23,N23) -> 212 | P23: =ROUND(O23/C23,0) -> 42 | Q23: =1-K23/(O23*$B$4) -> 0.25274577 | T23: 25 | U23: СНЯТО 03.08.2026. Версия 1.0 дороже 1.1 при том же результате. 1.1 покрывает t2v, i2v и r2v. | V23: =(4400/O23)/(685.5/T23)-1 -> -0.24308107 | W23: =MAX(ROUNDUP(5.014*T23,0),M23,N23) -> 212 | X23: =(4400/W23)/(685.5/T23)-1 -> -0.24308107 | Y23: =1-K23/(W23*$B$4) -> 0.25274577 | AA23: =O23 -> 212 | AB23: =C23 -> 5 | AC23: =IF(B23="шт","—",P23) -> 42 | AD23: OpenRouter | AE23: Kie | AF23: alibaba/happyhorse-1.1 | AG23: HIGH | AH23: =$B$5 -> 0.25
A24: HappyHorse 1.0 1080p — СНЯТО | B24: сек | C24: 5 | D24: 5 | E24: OpenRouter | F24: 0.1694 | G24: direct | H24: 0.24 | I24: 45 | J24: 400 | K24: =F24*C24*IF(E24="OpenRouter",$F$3,$F$4) -> 89.936154 | L24: =ROUNDUP(5.014*I24,0) -> 226 | M24: =ROUNDUP(K24*(C24/D24)/($B$4*(1-IF(B24="фикс",$B$6,AH24))),0) -> 363 | N24: =ROUNDUP(H24*C24*IF(G24="OpenRouter",$F$3,$F$4)/$B$4,0) -> 365 | O24: =MAX(L24,M24,N24) -> 365 | P24: =ROUND(O24/C24,0) -> 73 | Q24: =1-K24/(O24*$B$4) -> 0.2558374 | T24: 45 | U24: СНЯТО С ПРОДАЖИ 03.08.2026 — версия 1.0 дороже 1.1 при том же результате (решение владельца) РЕШЕНИЕ ВЛАДЕЛЬЦА 11.08.2026 — НАДБАВКА ЗА РЕЗЕРВ ОСТАЁТСЯ. Правило цены остаётся из четырёх членов: MAX(потолок +28% vs Syntx; цена по марже 25%; БЕЗУБЫТОК РЕЗЕРВА; ступень качества +15%). Вопрос ставился и закрыт: четвёртый член перебивает цену на 8 строках из 91, и на этих строках клиент оплачивает вторую ногу. Владелец рассмотрел цену решения и принял её. ЧЕГО ЭТО СТОИТ, ЧТОБЫ НИКТО НЕ ПЕРЕСЧИТЫВАЛ ЗАНОВО: на Seedance 1080p 775 вместо 727 — это −7,0% против Syntx вместо −0,9%, то есть страховка стоит 6 п.п. конкурентоспособности. На Gemini Omni 273 вместо 257 — −34,2% вместо −30,1%. На остальных строках надбавка стоит 1-2 кредита и на сравнение с конкурентом не влияет. ЧТО ЭТО ПОКУПАЕТ: переключение на резерв бесплатно для нас в момент отказа — резерв на этих строках выходит ровно в ноль, а не в минус, поэтому R-1 выполняется без исключений и бюджет отказов по R-11 не расходуется. ИЗВЕСТНОЕ ПОБОЧНОЕ СЛЕДСТВИЕ: при этом правиле добавление ЛЮБОЙ новой ноги может цену только поднять, никогда не опустить. Третья нога, под которую 11.08 открыт формат, работает против клиента до тех пор, пока это правило действует. Пересматривать при подключении первого третьего вендора. | V24: =(4400/O24)/(685.5/T24)-1 -> -0.20865681 | W24: =MAX(ROUNDUP(5.014*T24,0),M24,N24) -> 365 | X24: =(4400/W24)/(685.5/T24)-1 -> -0.20865681 | Y24: =1-K24/(W24*$B$4) -> 0.2558374 | AA24: =O24 -> 365 | AB24: =C24 -> 5 | AC24: =IF(B24="шт","—",P24) -> 73 | AD24: OpenRouter | AE24: Kie | AF24: alibaba/happyhorse-1.1 | AG24: HIGH | AH24: =$B$5 -> 0.25
A25: Wan 2.7 720p | B25: сек | C25: 5 | D25: 5 | E25: direct | F25: 0.08 | G25: OpenRouter | H25: 0.1 | I25: 30 | J25: 300 | K25: =F25*C25*IF(E25="OpenRouter",$F$3,$F$4) -> 40.2526 | L25: =ROUNDUP(5.014*I25,0) -> 151 | M25: =ROUNDUP(K25*(C25/D25)/($B$4*(1-IF(B25="фикс",$B$6,AH25))),0) -> 163 | N25: =ROUNDUP(H25*C25*IF(G25="OpenRouter",$F$3,$F$4)/$B$4,0) -> 161 | O25: =MAX(L25,M25,N25) -> 163 | P25: =ROUND(O25/C25,0) -> 33 | Q25: =1-K25/(O25*$B$4) -> 0.25418223 | T25: 30 | U25: публичный прайс Syntx 28.07.2026, цена «итого», пересчёт на длину нашего клипа | V25: =(4400/O25)/(685.5/T25)-1 -> 0.18135077 | W25: =MAX(ROUNDUP(5.014*T25,0),M25,N25) -> 163 | X25: =(4400/W25)/(685.5/T25)-1 -> 0.18135077 | Y25: =1-K25/(W25*$B$4) -> 0.25418223 | AA25: =O25 -> 163 | AB25: =C25 -> 5 | AC25: =IF(B25="шт","—",P25) -> 33 | AD25: Kie | AE25: OpenRouter | AF25: wan-2-7 | AG25: HIGH | AH25: =$B$5 -> 0.25 | AP25: да | AQ25: да
A26: Wan 2.7 1080p | B26: сек | C26: 5 | D26: 5 | E26: direct | F26: 0.12 | G26: OpenRouter | H26: 0.15 | I26: 40 | J26: 300 | K26: =F26*C26*IF(E26="OpenRouter",$F$3,$F$4) -> 60.3789 | L26: =ROUNDUP(5.014*I26,0) -> 201 | M26: =ROUNDUP(K26*(C26/D26)/($B$4*(1-IF(B26="фикс",$B$6,AH26))),0) -> 244 | N26: =ROUNDUP(H26*C26*IF(G26="OpenRouter",$F$3,$F$4)/$B$4,0) -> 241 | O26: =MAX(L26,M26,N26) -> 244 | P26: =ROUND(O26/C26,0) -> 49 | Q26: =1-K26/(O26*$B$4) -> 0.25265392 | T26: 40 | U26: публичный прайс Syntx 28.07.2026, цена «итого», пересчёт на длину нашего клипа | V26: =(4400/O26)/(685.5/T26)-1 -> 0.052241394 | W26: =MAX(ROUNDUP(5.014*T26,0),M26,N26) -> 244 | X26: =(4400/W26)/(685.5/T26)-1 -> 0.052241394 | Y26: =1-K26/(W26*$B$4) -> 0.25265392 | AA26: =O26 -> 244 | AB26: =C26 -> 5 | AC26: =IF(B26="шт","—",P26) -> 49 | AD26: Kie | AE26: OpenRouter | AF26: wan-2-7 | AG26: HIGH | AH26: =$B$5 -> 0.25 | AP26: да | AQ26: да
A27: Kling v3 720p (звук) | B27: сек | C27: 5 | D27: 5 | E27: OpenRouter | F27: 0.126 | G27: — | H27: — | I27: 25 | J27: 350 | K27: =F27*C27*IF(E27="OpenRouter",$F$3,$F$4) -> 66.89466 | L27: =ROUNDUP(5.014*I27,0) -> 126 | M27: =ROUNDUP(K27*(C27/D27)/($B$4*(1-IF(B27="фикс",$B$6,AH27))),0) -> 270 | N27: 0 | O27: =MAX(L27,M27,N27) -> 270 | P27: =ROUND(O27/C27,0) -> 54 | Q27: =1-K27/(O27*$B$4) -> 0.25173733 | U27: ЕДИНСТВЕННАЯ НОГА — OpenRouter. Ноги kie у этой модели не существует: ни слага в адаптере, ни переопределения шлюза, ни в контракте маршрута. Ставка kie, по которой строка была оценена в ред.10, относилась к маршруту, которого нет. Пересчитано от реальной ноги 04.08.2026. Standard $0,126/с со звуком, $0,084/с без звука (Pro $0,168/$0,112 не продаём). | AA27: =O27 -> 270 | AB27: =C27 -> 5 | AC27: =IF(B27="шт","—",P27) -> 54 | AD27: OpenRouter | AE27: — | AF27: kwaivgi/kling-v3.0-std | AG27: HIGH — прайс OpenRouter, Standard | AH27: =$B$5 -> 0.25 | AP27: да
A28: Grok 720p | B28: сек | C28: 6 | D28: 6 | E28: direct | F28: 0.0225 | G28: — | H28: — | I28: 8 | J28: 45 | K28: =F28*C28*IF(E28="OpenRouter",$F$3,$F$4) -> 13.585252 | L28: =ROUNDUP(5.014*I28,0) -> 41 | M28: =ROUNDUP(K28*(C28/D28)/($B$4*(1-IF(B28="фикс",$B$6,AH28))),0) -> 69 | N28: 0 | O28: =MAX(L28,M28,N28) -> 69 | P28: =ROUND(O28/C28,0) -> 12 | Q28: =1-K28/(O28*$B$4) -> 0.40537247 | T28: 8 | U28: Ставка подтверждена прайсом kie. Порог 40% по R-10 остаётся: xAI просит $0,05/$0,07, kie на 68-76% ниже, второй ноги нет, и kie уже двигал ставку на +50% за две недели. Оба условия правила в силе. | V28: =(4400/O28)/(685.5/T28)-1 -> -0.25580609 | W28: =MAX(ROUNDUP(5.014*T28,0),M28,N28) -> 69 | X28: =(4400/W28)/(685.5/T28)-1 -> -0.25580609 | Y28: =1-K28/(W28*$B$4) -> 0.40537247 | AA28: =O28 -> 69 | AB28: =C28 -> 6 | AC28: =IF(B28="шт","—",P28) -> 12 | AD28: Kie | AE28: — | AF28: grok-imagine-video | AG28: HIGH — прайс kie 04.08.2026. Порог 40% сохраняется по R-10: подтверждение источника снимает сомнение в чтении ставки, но не в её устойчивости. | AH28: 0.4 | AP28: да
A29: Grok 480p | B29: сек | C29: 6 | D29: 6 | E29: direct | F29: 0.012 | G29: — | H29: — | I29: 5 | J29: 24 | K29: =F29*C29*IF(E29="OpenRouter",$F$3,$F$4) -> 7.245468 | L29: =ROUNDUP(5.014*I29,0) -> 26 | M29: =ROUNDUP(K29*(C29/D29)/($B$4*(1-IF(B29="фикс",$B$6,AH29))),0) -> 37 | N29: 0 | O29: =MAX(L29,M29,N29) -> 37 | P29: =ROUND(O29/C29,0) -> 6 | Q29: =1-K29/(O29*$B$4) -> 0.40858667 | T29: 5 | U29: Ставка подтверждена прайсом kie. Порог 40% по R-10 остаётся: xAI просит $0,05/$0,07, kie на 68-76% ниже, второй ноги нет, и kie уже двигал ставку на +50% за две недели. Оба условия правила в силе. | V29: =(4400/O29)/(685.5/T29)-1 -> -0.13261182 | W29: =MAX(ROUNDUP(5.014*T29,0),M29,N29) -> 37 | X29: =(4400/W29)/(685.5/T29)-1 -> -0.13261182 | Y29: =1-K29/(W29*$B$4) -> 0.40858667 | AA29: =O29 -> 37 | AB29: =C29 -> 6 | AC29: =IF(B29="шт","—",P29) -> 6 | AD29: Kie | AE29: — | AF29: grok-imagine-video | AG29: HIGH — прайс kie 04.08.2026. Порог 40% сохраняется по R-10: подтверждение источника снимает сомнение в чтении ставки, но не в её устойчивости. | AH29: 0.4 | AP29: да
A30: Gemini Omni | B30: сек | C30: 8 | D30: 8 | E30: direct | F30: 0.079 | G30: direct | H30: 0.112 | I30: 28 | J30: 282 | K30: =F30*C30*IF(E30="OpenRouter",$F$3,$F$4) -> 63.599108 | L30: =ROUNDUP(5.014*I30,0) -> 141 | M30: =ROUNDUP(K30*(C30/D30)/($B$4*(1-IF(B30="фикс",$B$6,AH30))),0) -> 257 | N30: =ROUNDUP(H30*C30*IF(G30="OpenRouter",$F$3,$F$4)/$B$4,0) -> 273 | O30: =MAX(L30,M30,N30) -> 273 | P30: =ROUND(O30/C30,0) -> 34 | Q30: =1-K30/(O30*$B$4) -> 0.29641792 | U30: ДВЕ НОГИ ВОССТАНОВЛЕНЫ 04.08.2026. Решение от 03.08 снять AtlasCloud принималось при ставке $0,125-0,135, которая требовала 329 кредитов — плюс 21% клиенту за страховку. При подтверждённых $0,112 требуется 273, то есть плюс 6%. Модель несёт 8% потребления и не имеет альтернативного источника дешевле $0,084/с — за две ноги на такой строке 6% платить стоит. РЕШЕНИЕ ВЛАДЕЛЬЦА 11.08.2026 — НАДБАВКА ЗА РЕЗЕРВ ОСТАЁТСЯ. Правило цены остаётся из четырёх членов: MAX(потолок +28% vs Syntx; цена по марже 25%; БЕЗУБЫТОК РЕЗЕРВА; ступень качества +15%). Вопрос ставился и закрыт: четвёртый член перебивает цену на 8 строках из 91, и на этих строках клиент оплачивает вторую ногу. Владелец рассмотрел цену решения и принял её. ЧЕГО ЭТО СТОИТ, ЧТОБЫ НИКТО НЕ ПЕРЕСЧИТЫВАЛ ЗАНОВО: на Seedance 1080p 775 вместо 727 — это −7,0% против Syntx вместо −0,9%, то есть страховка стоит 6 п.п. конкурентоспособности. На Gemini Omni 273 вместо 257 — −34,2% вместо −30,1%. На остальных строках надбавка стоит 1-2 кредита и на сравнение с конкурентом не влияет. ЧТО ЭТО ПОКУПАЕТ: переключение на резерв бесплатно для нас в момент отказа — резерв на этих строках выходит ровно в ноль, а не в минус, поэтому R-1 выполняется без исключений и бюджет отказов по R-11 не расходуется. ИЗВЕСТНОЕ ПОБОЧНОЕ СЛЕДСТВИЕ: при этом правиле добавление ЛЮБОЙ новой ноги может цену только поднять, никогда не опустить. Третья нога, под которую 11.08 открыт формат, работает против клиента до тех пор, пока это правило действует. Пересматривать при подключении первого третьего вендора. | AA30: =O30 -> 273 | AB30: =C30 -> 8 | AC30: =IF(B30="шт","—",P30) -> 34 | AD30: Kie | AE30: AtlasCloud | AF30: gemini-omni-flash | AG30: HIGH — ставка подтверждена платно | AH30: =$B$5 -> 0.25 | AI30: ТАРИФ МАРШРУТА AtlasCloud: $0,112/с держится только на ступени -developer. Стандартная ступень $0,125-0,135, и при 273 кредитах это −11,3% вместо +0,25%. Риск управляется нами, а не поставщиком: суффикс закреплён именованной константой с тестом на три режима. Внешнего сигнала у потери суффикса нет — Atlas отвечает, отдаёт видео и просто выставляет счёт дороже. | AP30: да | AQ30: да
A31: nano-banana | B31: карт | C31: 1 | D31: 1 | E31: direct | F31: 0.02 | G31: direct | H31: 0.02 | I31: 1.5 | J31: 15 | K31: =F31*C31*IF(E31="OpenRouter",$F$3,$F$4) -> 2.01263 | L31: =ROUNDUP(5.014*I31,0) -> 8 | M31: =ROUNDUP(K31*(C31/D31)/($B$4*(1-IF(B31="фикс",$B$6,AH31))),0) -> 9 | N31: 0 | O31: =MAX(L31,M31,N31) -> 9 | P31: =ROUND(O31/C31,0) -> 9 | Q31: =1-K31/(O31*$B$4) -> 0.32462058 | U31: Kie fallback google/nano-banana $0.02/img; owner list 2026-07-25; t2i route connected. | AA31: =O31 -> 9 | AB31: =C31 -> 1 | AC31: =IF(B31="шт","—",P31) -> 9 | AD31: LaoZhang | AE31: Kie | AF31: gemini-2-5-flash-image | AG31: HIGH; ЕДИНСТВЕННАЯ НОГА — резерва не существует | AH31: =$B$5 -> 0.25 | AP31: да | AQ31: да
A32: nano-banana-2 1K | B32: карт | C32: 1 | D32: 1 | E32: direct | F32: 0.04 | G32: direct | H32: 0.055 | I32: 3 | J32: 25 | K32: =F32*C32*IF(E32="OpenRouter",$F$3,$F$4) -> 4.02526 | L32: =ROUNDUP(5.014*I32,0) -> 16 | M32: =ROUNDUP(K32*(C32/D32)/($B$4*(1-IF(B32="фикс",$B$6,AH32))),0) -> 17 | N32: =ROUNDUP(H32*C32*IF(G32="OpenRouter",$F$3,$F$4)/$B$4,0) -> 17 | O32: =MAX(L32,M32,N32) -> 17 | P32: =ROUND(O32/C32,0) -> 17 | Q32: =1-K32/(O32*$B$4) -> 0.28489238 | U32: Ноги поменяны местами 03.08: kie по опубликованной лестнице дешевле LaoZhang на этом рунге. | Z32: 0 | AA32: =O32 -> 17 | AB32: =C32 -> 1 | AC32: =IF(B32="шт","—",P32) -> 17 | AD32: Kie | AE32: LaoZhang | AF32: nano-banana-2 | AG32: HIGH | AH32: =$B$5 -> 0.25 | AP32: да | AQ32: да
A33: nano-banana-2-lite | B33: карт | C33: 1 | D33: 1 | E33: direct | F33: 0.02 | G33: direct | H33: 0.025 | I33: 1.3 | J33: 12 | K33: =F33*C33*IF(E33="OpenRouter",$F$3,$F$4) -> 2.01263 | L33: =ROUNDUP(5.014*I33,0) -> 7 | M33: =ROUNDUP(K33*(C33/D33)/($B$4*(1-IF(B33="фикс",$B$6,AH33))),0) -> 9 | N33: =ROUNDUP(H33*C33*IF(G33="OpenRouter",$F$3,$F$4)/$B$4,0) -> 8 | O33: =MAX(L33,M33,N33) -> 9 | P33: =ROUND(O33/C33,0) -> 9 | Q33: =1-K33/(O33*$B$4) -> 0.32462058 | U33: Ноги поменяны местами 03.08: kie по опубликованной лестнице дешевле LaoZhang на этом рунге. | AA33: =O33 -> 9 | AB33: =C33 -> 1 | AC33: =IF(B33="шт","—",P33) -> 9 | AD33: Kie | AE33: LaoZhang | AF33: nano-banana-2-lite | AG33: HIGH | AH33: =$B$5 -> 0.25 | AP33: да | AQ33: да
A34: nano-banana-pro 1K | B34: карт | C34: 1 | D34: 1 | E34: direct | F34: 0.09 | G34: — | H34: — | I34: 2 | J34: 40 | K34: =F34*C34*IF(E34="OpenRouter",$F$3,$F$4) -> 9.056835 | L34: =ROUNDUP(5.014*I34,0) -> 11 | M34: =ROUNDUP(K34*(C34/D34)/($B$4*(1-IF(B34="фикс",$B$6,AH34))),0) -> 37 | N34: 0 | O34: =MAX(L34,M34,N34) -> 37 | P34: =ROUND(O34/C34,0) -> 37 | Q34: =1-K34/(O34*$B$4) -> 0.26073334 | U34: ВТОРОЙ НОГИ НЕТ. В колонках резерва стояла побайтовая копия основной ставки без имени поставщика — заглушка, которую экспорт выгружал как настоящую ногу. Убрана 10.08.2026. Модель обслуживается одним LaoZhang: при его недоступности строка не переключается, а отказывает. Это факт для бюджета отказов, а не дефект цены — цена и маржа не менялись. | Z34: 0 | AA34: =O34 -> 37 | AB34: =C34 -> 1 | AC34: =IF(B34="шт","—",P34) -> 37 | AD34: LaoZhang | AE34: — | AF34: nano-banana-pro | AG34: HIGH; ЕДИНСТВЕННАЯ НОГА — резерва не существует | AH34: =$B$5 -> 0.25 | AP34: да
A35: nano-banana-pro 4K | B35: карт | C35: 1 | D35: 1 | E35: direct | F35: 0.09 | G35: direct | H35: 0.12 | I35: 2 | J35: 41 | K35: =F35*C35*IF(E35="OpenRouter",$F$3,$F$4) -> 9.056835 | L35: =ROUNDUP(5.014*I35,0) -> 11 | M35: =ROUNDUP(K35*(C35/D35)/($B$4*(1-IF(B35="фикс",$B$6,AH35))),0) -> 37 | N35: =ROUNDUP(H35*C35*IF(G35="OpenRouter",$F$3,$F$4)/$B$4,0) -> 37 | O35: =MAX(L35,M35,N35,Z35) -> 50 | P35: =ROUND(O35/C35,0) -> 50 | Q35: =1-K35/(O35*$B$4) -> 0.45294267 | U35: НЕ ПРОВЕРЕНО — публичным прайсом не подтверждено | Z35: =ROUNDUP(O46*1.15,0) -> 50 | AA35: =O35 -> 50 | AB35: =C35 -> 1 | AC35: =IF(B35="шт","—",P35) -> 50 | AD35: LaoZhang | AE35: Kie | AF35: nano-banana-pro | AG35: HIGH | AH35: =$B$5 -> 0.25 | AP35: да | AQ35: да
A36: gpt-image-2 1K (low) | B36: карт | C36: 1 | D36: 1 | E36: direct | F36: 0.03 | G36: direct | H36: 0.03 | I36: 2 | J36: 25 | K36: =F36*C36*IF(E36="OpenRouter",$F$3,$F$4) -> 3.018945 | L36: =ROUNDUP(5.014*I36,0) -> 11 | M36: =ROUNDUP(K36*(C36/D36)/($B$4*(1-IF(B36="фикс",$B$6,AH36))),0) -> 13 | N36: 0 | O36: =MAX(L36,M36,N36) -> 13 | P36: =ROUND(O36/C36,0) -> 13 | Q36: =1-K36/(O36*$B$4) -> 0.29864445 | U36: Kie fallback gpt-image-2-text-to-image $0.03/low; owner list 2026-07-25. Costed reserve; quality mapping remains unarmed. | AA36: =O36 -> 13 | AB36: =C36 -> 1 | AC36: =IF(B36="шт","—",P36) -> 13 | AD36: LaoZhang | AE36: Kie | AF36: gpt-image-2-vip | AG36: ЗАМЕРЕНО 09.08.2026 — платный вызов, счётчик откалиброван | AH36: =$B$5 -> 0.25 | AP36: да
A37: gpt-image-2 2K (medium) | B37: шт | C37: 1 | D37: 1 | E37: direct | F37: 0.03 | G37: direct | H37: 0.05 | I37: — | K37: =F37*C37*IF(E37="OpenRouter",$F$3,$F$4) -> 3.018945 | L37: 0 | M37: =ROUNDUP(K37*(C37/D37)/($B$4*(1-IF(B37="фикс",$B$6,AH37))),0) -> 13 | N37: 0 | O37: 21 | P37: =ROUND(O37/C37,0) -> 21 | Q37: =1-K37/(O37*$B$4) -> 0.56582751 | U37: Kie fallback gpt-image-2-text-to-image $0.05/medium; owner list 2026-07-25. Costed reserve; quality mapping remains unarmed. | AA37: =O37 -> 21 | AB37: =C37 -> 1 | AC37: =IF(B37="шт","—",P37) -> — | AD37: LaoZhang | AE37: Kie | AF37: gpt-image-2-vip | AG37: ЗАМЕРЕНО 09.08.2026 — платный вызов, счётчик откалиброван | AH37: =$B$5 -> 0.25 | AP37: да
A38: gpt-image-2 4K (high) | B38: шт | C38: 1 | D38: 1 | E38: direct | F38: 0.03 | G38: direct | H38: 0.08 | I38: — | K38: =F38*C38*IF(E38="OpenRouter",$F$3,$F$4) -> 3.018945 | L38: 0 | M38: =ROUNDUP(K38*(C38/D38)/($B$4*(1-IF(B38="фикс",$B$6,AH38))),0) -> 13 | N38: 0 | O38: 33 | P38: =ROUND(O38/C38,0) -> 33 | Q38: =1-K38/(O38*$B$4) -> 0.72370842 | U38: Kie fallback gpt-image-2-text-to-image $0.08/high; owner list 2026-07-25. Costed reserve; quality mapping remains unarmed. | AA38: =O38 -> 33 | AB38: =C38 -> 1 | AC38: =IF(B38="шт","—",P38) -> — | AD38: LaoZhang | AE38: Kie | AF38: gpt-image-2-vip | AG38: ЗАМЕРЕНО 09.08.2026 — платный вызов, счётчик откалиброван | AH38: =$B$5 -> 0.25 | AP38: да
A39: seedream-4.5 1K | B39: карт | C39: 1 | D39: 1 | E39: direct | F39: 0.0325 | G39: OpenRouter | H39: 0.04 | I39: 2 | J39: 15 | K39: =F39*C39*IF(E39="OpenRouter",$F$3,$F$4) -> 3.2705238 | L39: =ROUNDUP(5.014*I39,0) -> 11 | M39: =ROUNDUP(K39*(C39/D39)/($B$4*(1-IF(B39="фикс",$B$6,AH39))),0) -> 14 | N39: =ROUNDUP(H39*C39*IF(G39="OpenRouter",$F$3,$F$4)/$B$4,0) -> 13 | O39: =MAX(L39,M39,N39) -> 14 | P39: =ROUND(O39/C39,0) -> 14 | Q39: =1-K39/(O39*$B$4) -> 0.29446971 | U39: НЕ ПРОВЕРЕНО — публичным прайсом не подтверждено | Z39: 0 | AA39: =O39 -> 14 | AB39: =C39 -> 1 | AC39: =IF(B39="шт","—",P39) -> 14 | AD39: Kie | AE39: OpenRouter | AF39: seedream-4-5 | AG39: HIGH | AH39: =$B$5 -> 0.25 | AP39: да | AQ39: да
A40: seedream-5.0 Pro 1K · 0-1 реф | B40: карт | C40: 1 | D40: 1 | E40: direct | F40: 0.035 | G40: — | H40: — | I40: 3 | J40: 15 | K40: =F40*C40*IF(E40="OpenRouter",$F$3,$F$4) -> 3.5221025 | L40: =ROUNDUP(5.014*I40,0) -> 16 | M40: =ROUNDUP(K40*(C40/D40)/($B$4*(1-IF(B40="фикс",$B$6,AH40))),0) -> 15 | N40: 0 | O40: =MAX(L40,M40,N40) -> 16 | P40: =ROUND(O40/C40,0) -> 16 | Q40: =1-K40/(O40*$B$4) -> 0.33517338 | T40: 3 | U40: Диапазон 0-1 референс. kie берёт за входные картинки $0,0025 начиная СО ВТОРОЙ — первая бесплатна, и SKU image-to-image стоит столько же, сколько text-to-image. Значит один референс не меняет себестоимость и цену. Разрыв в бандах устранён 04.08.2026 переименованием, без изменения цены. | V40: =(4400/O40)/(685.5/T40)-1 -> 0.20350109 | W40: =MAX(ROUNDUP(5.014*T40,0),M40,N40) -> 16 | X40: =(4400/W40)/(685.5/T40)-1 -> 0.20350109 | Y40: =1-K40/(W40*$B$4) -> 0.33517338 | AA40: =O40 -> 16 | AB40: =C40 -> 1 | AC40: =IF(B40="шт","—",P40) -> 16 | AD40: Kie | AE40: — | AF40: seedream/5-pro-text-to-image | AG40: HIGH | AH40: =$B$5 -> 0.25 | AP40: да
A41: seedream-5.0 Pro 2K · 0-1 реф | B41: карт | C41: 1 | D41: 1 | E41: direct | F41: 0.07 | G41: — | H41: — | I41: 6 | J41: 30 | K41: =F41*C41*IF(E41="OpenRouter",$F$3,$F$4) -> 7.044205 | L41: =ROUNDUP(5.014*I41,0) -> 31 | M41: =ROUNDUP(K41*(C41/D41)/($B$4*(1-IF(B41="фикс",$B$6,AH41))),0) -> 29 | N41: 0 | O41: =MAX(L41,M41,N41) -> 31 | P41: =ROUND(O41/C41,0) -> 31 | Q41: =1-K41/(O41*$B$4) -> 0.31372736 | T41: 6 | U41: Диапазон 0-1 референс. kie берёт за входные картинки $0,0025 начиная СО ВТОРОЙ — первая бесплатна, и SKU image-to-image стоит столько же, сколько text-to-image. Значит один референс не меняет себестоимость и цену. Разрыв в бандах устранён 04.08.2026 переименованием, без изменения цены. | V41: =(4400/O41)/(685.5/T41)-1 -> 0.24232371 | W41: =MAX(ROUNDUP(5.014*T41,0),M41,N41) -> 31 | X41: =(4400/W41)/(685.5/T41)-1 -> 0.24232371 | Y41: =1-K41/(W41*$B$4) -> 0.31372736 | AA41: =O41 -> 31 | AB41: =C41 -> 1 | AC41: =IF(B41="шт","—",P41) -> 31 | AD41: Kie | AE41: — | AF41: seedream/5-pro-text-to-image | AG41: HIGH | AH41: =$B$5 -> 0.25 | AP41: да
A42: seedream-5.0 Lite 2K | B42: карт | C42: 1 | D42: 1 | E42: direct | F42: 0.0275 | G42: — | H42: — | I42: 2 | J42: 10 | K42: =F42*C42*IF(E42="OpenRouter",$F$3,$F$4) -> 2.7673662 | L42: =ROUNDUP(5.014*I42,0) -> 11 | M42: =ROUNDUP(K42*(C42/D42)/($B$4*(1-IF(B42="фикс",$B$6,AH42))),0) -> 12 | N42: 0 | O42: =MAX(L42,M42,N42) -> 12 | P42: =ROUND(O42/C42,0) -> 12 | Q42: =1-K42/(O42*$B$4) -> 0.30351497 | T42: 2 | U42: публичный прайс Syntx 28.07.2026, цена «итого», пересчёт на длину нашего клипа | V42: =(4400/O42)/(685.5/T42)-1 -> 0.06977875 | W42: =MAX(ROUNDUP(5.014*T42,0),M42,N42) -> 12 | X42: =(4400/W42)/(685.5/T42)-1 -> 0.06977875 | Y42: =1-K42/(W42*$B$4) -> 0.30351497 | Z42: 0 | AA42: =O42 -> 12 | AB42: =C42 -> 1 | AC42: =IF(B42="шт","—",P42) -> 12 | AD42: Kie | AE42: — | AF42: seedream/5-lite-text-to-image | AG42: HIGH | AH42: =$B$5 -> 0.25 | AP42: да
A43: flux-2-pro 1K | B43: карт | C43: 1 | D43: 1 | E43: direct | F43: 0.025 | G43: OpenRouter | H43: 0.03 | I43: — | J43: 50 | K43: =F43*C43*IF(E43="OpenRouter",$F$3,$F$4) -> 2.5157875 | L43: 0 | M43: =ROUNDUP(K43*(C43/D43)/($B$4*(1-IF(B43="фикс",$B$6,AH43))),0) -> 11 | N43: 0 | O43: =MAX(L43,M43,N43) -> 11 | P43: =ROUND(O43/C43,0) -> 11 | Q43: =1-K43/(O43*$B$4) -> 0.30927105 | U43: СТУПЕНЬ ОБЪЯВЛЕНА ЯВНО как 1K (10.08.2026). Раньше строка несла бэнд default. Как только у модели появилась вторая ступень (2K), резолвер цены стал ключеваться на объявленный список ['1K','2K'] — и default-строка перестала находиться, то есть 1K-запросы уходили бы в отказ биллинга. Цена не менялась: это переименование бэнда. Правило: у модели не может быть одновременно ступени default и именованной — генератор экспорта проверяет это утверждением. | AA43: =O43 -> 11 | AB43: =C43 -> 1 | AC43: =IF(B43="шт","—",P43) -> 11 | AD43: Kie | AE43: OpenRouter | AF43: flux-2-pro / black-forest-labs/flux.2-pro | AG43: ЗАМЕРЕНО — kie, 5 кредитов при $0,025; ступень объявлена явно 10.08.2026 | AH43: =$B$5 -> 0.25 | AO43: 1.049 | AP43: да | AQ43: да
A44: recraft-v4 | B44: карт | C44: 1 | D44: 1 | E44: OpenRouter | F44: 0.04 | G44: — | H44: — | I44: — | J44: 25 | K44: =F44*C44*IF(E44="OpenRouter",$F$3,$F$4) -> 4.24728 | L44: 0 | M44: =ROUNDUP(K44*(C44/D44)/($B$4*(1-IF(B44="фикс",$B$6,AH44))),0) -> 18 | N44: 0 | O44: =MAX(L44,M44,N44) -> 18 | P44: =ROUND(O44/C44,0) -> 18 | Q44: =1-K44/(O44*$B$4) -> 0.28736889 | U44: у Syntx нет такой модели — сравнение неприменимо | AA44: =O44 -> 18 | AB44: =C44 -> 1 | AC44: =IF(B44="шт","—",P44) -> 18 | AD44: OpenRouter | AE44: — | AF44: recraft-v4 | AG44: HIGH | AH44: =$B$5 -> 0.25 | AP44: да
A45: recraft-v4-vector | B45: карт | C45: 1 | D45: 1 | E45: OpenRouter | F45: 0.08 | G45: — | H45: — | I45: — | J45: 40 | K45: =F45*C45*IF(E45="OpenRouter",$F$3,$F$4) -> 8.49456 | L45: 0 | M45: =ROUNDUP(K45*(C45/D45)/($B$4*(1-IF(B45="фикс",$B$6,AH45))),0) -> 35 | N45: 0 | O45: =MAX(L45,M45,N45) -> 35 | P45: =ROUND(O45/C45,0) -> 35 | Q45: =1-K45/(O45*$B$4) -> 0.267008 | U45: у Syntx нет такой модели — сравнение неприменимо | AA45: =O45 -> 35 | AB45: =C45 -> 1 | AC45: =IF(B45="шт","—",P45) -> 35 | AD45: OpenRouter | AE45: — | AF45: recraft-v4-vector | AG45: HIGH | AH45: =$B$5 -> 0.25 | AP45: да
A46: nano-banana-pro 2K | B46: шт | C46: 1 | D46: 1 | E46: direct | F46: 0.09 | G46: — | H46: — | I46: — | K46: =F46*C46*IF(E46="OpenRouter",$F$3,$F$4) -> 9.056835 | L46: 0 | M46: =ROUNDUP(K46*(C46/D46)/($B$4*(1-IF(B46="фикс",$B$6,AH46))),0) -> 37 | N46: 0 | O46: =MAX(L46,M46,N46,Z46) -> 43 | P46: =ROUND(O46/C46,0) -> 43 | Q46: =1-K46/(O46*$B$4) -> 0.36388682 | U46: ВТОРОЙ НОГИ НЕТ. В колонках резерва стояла побайтовая копия основной ставки без имени поставщика — заглушка, которую экспорт выгружал как настоящую ногу. Убрана 10.08.2026. Модель обслуживается одним LaoZhang: при его недоступности строка не переключается, а отказывает. Это факт для бюджета отказов, а не дефект цены — цена и маржа не менялись. | Z46: =ROUNDUP(O34*1.15,0) -> 43 | AA46: =O46 -> 43 | AB46: 1 | AC46: — | AD46: LaoZhang | AE46: — | AF46: nano-banana-pro | AG46: HIGH; ЕДИНСТВЕННАЯ НОГА — резерва не существует | AH46: =$B$5 -> 0.25 | AP46: да
A47: nano-banana-2 2K | B47: шт | C47: 1 | D47: 1 | E47: direct | F47: 0.055 | G47: direct | H47: 0.06 | I47: — | K47: =F47*C47*IF(E47="OpenRouter",$F$3,$F$4) -> 5.5347325 | L47: 0 | M47: =ROUNDUP(K47*(C47/D47)/($B$4*(1-IF(B47="фикс",$B$6,AH47))),0) -> 23 | N47: =ROUNDUP(H47*C47*IF(G47="OpenRouter",$F$3,$F$4)/$B$4,0) -> 19 | O47: =MAX(L47,M47,N47,Z47) -> 23 | P47: =ROUND(O47/C47,0) -> 23 | Q47: =1-K47/(O47*$B$4) -> 0.27323301 | U47: тир качества — ступень +15% к предыдущему тиру | Z47: =ROUNDUP(O32*1.15,0) -> 20 | AA47: =O47 -> 23 | AB47: 1 | AC47: — | AD47: LaoZhang | AE47: Kie | AF47: nano-banana-2 | AG47: HIGH | AH47: =$B$5 -> 0.25 | AP47: да | AQ47: да
A48: nano-banana-2 4K | B48: шт | C48: 1 | D48: 1 | E48: direct | F48: 0.055 | G48: direct | H48: 0.09 | I48: — | K48: =F48*C48*IF(E48="OpenRouter",$F$3,$F$4) -> 5.5347325 | L48: 0 | M48: =ROUNDUP(K48*(C48/D48)/($B$4*(1-IF(B48="фикс",$B$6,AH48))),0) -> 23 | N48: =ROUNDUP(H48*C48*IF(G48="OpenRouter",$F$3,$F$4)/$B$4,0) -> 28 | O48: =MAX(L48,M48,N48,Z48) -> 28 | P48: =ROUND(O48/C48,0) -> 28 | Q48: =1-K48/(O48*$B$4) -> 0.40301283 | U48: тир качества — ступень +15% к предыдущему тиру РЕШЕНИЕ ВЛАДЕЛЬЦА 11.08.2026 — НАДБАВКА ЗА РЕЗЕРВ ОСТАЁТСЯ. Правило цены остаётся из четырёх членов: MAX(потолок +28% vs Syntx; цена по марже 25%; БЕЗУБЫТОК РЕЗЕРВА; ступень качества +15%). Вопрос ставился и закрыт: четвёртый член перебивает цену на 8 строках из 91, и на этих строках клиент оплачивает вторую ногу. Владелец рассмотрел цену решения и принял её. ЧЕГО ЭТО СТОИТ, ЧТОБЫ НИКТО НЕ ПЕРЕСЧИТЫВАЛ ЗАНОВО: на Seedance 1080p 775 вместо 727 — это −7,0% против Syntx вместо −0,9%, то есть страховка стоит 6 п.п. конкурентоспособности. На Gemini Omni 273 вместо 257 — −34,2% вместо −30,1%. На остальных строках надбавка стоит 1-2 кредита и на сравнение с конкурентом не влияет. ЧТО ЭТО ПОКУПАЕТ: переключение на резерв бесплатно для нас в момент отказа — резерв на этих строках выходит ровно в ноль, а не в минус, поэтому R-1 выполняется без исключений и бюджет отказов по R-11 не расходуется. ИЗВЕСТНОЕ ПОБОЧНОЕ СЛЕДСТВИЕ: при этом правиле добавление ЛЮБОЙ новой ноги может цену только поднять, никогда не опустить. Третья нога, под которую 11.08 открыт формат, работает против клиента до тех пор, пока это правило действует. Пересматривать при подключении первого третьего вендора. | Z48: =ROUNDUP(O47*1.15,0) -> 27 | AA48: =O48 -> 28 | AB48: 1 | AC48: — | AD48: LaoZhang | AE48: Kie | AF48: nano-banana-2 | AG48: HIGH | AH48: =$B$5 -> 0.25 | AP48: да | AQ48: да
A49: seedream-4.5 2K | B49: шт | C49: 1 | D49: 1 | E49: direct | F49: 0.0325 | G49: OpenRouter | H49: 0.04 | I49: — | K49: =F49*C49*IF(E49="OpenRouter",$F$3,$F$4) -> 3.2705238 | L49: 0 | M49: =ROUNDUP(K49*(C49/D49)/($B$4*(1-IF(B49="фикс",$B$6,AH49))),0) -> 14 | N49: =ROUNDUP(H49*C49*IF(G49="OpenRouter",$F$3,$F$4)/$B$4,0) -> 13 | O49: =MAX(L49,M49,N49,Z49) -> 17 | P49: =ROUND(O49/C49,0) -> 17 | Q49: =1-K49/(O49*$B$4) -> 0.41897506 | U49: тир качества — ступень +15% к предыдущему тиру | Z49: =ROUNDUP(O39*1.15,0) -> 17 | AA49: =O49 -> 17 | AB49: 1 | AC49: — | AD49: Kie | AE49: OpenRouter | AF49: seedream-4-5 | AG49: HIGH | AH49: =$B$5 -> 0.25 | AP49: да | AQ49: да
A50: seedream-4.5 4K | B50: шт | C50: 1 | D50: 1 | E50: direct | F50: 0.0325 | G50: OpenRouter | H50: 0.04 | I50: — | K50: =F50*C50*IF(E50="OpenRouter",$F$3,$F$4) -> 3.2705238 | L50: 0 | M50: =ROUNDUP(K50*(C50/D50)/($B$4*(1-IF(B50="фикс",$B$6,AH50))),0) -> 14 | N50: =ROUNDUP(H50*C50*IF(G50="OpenRouter",$F$3,$F$4)/$B$4,0) -> 13 | O50: =MAX(L50,M50,N50,Z50) -> 20 | P50: =ROUND(O50/C50,0) -> 20 | Q50: =1-K50/(O50*$B$4) -> 0.5061288 | U50: тир качества — ступень +15% к предыдущему тиру | Z50: =ROUNDUP(O49*1.15,0) -> 20 | AA50: =O50 -> 20 | AB50: 1 | AC50: — | AD50: Kie | AE50: OpenRouter | AF50: seedream-4-5 | AG50: HIGH | AH50: =$B$5 -> 0.25 | AP50: да | AQ50: да
A51: seedream-5.0 Lite 3K | B51: шт | C51: 1 | D51: 1 | E51: direct | F51: 0.0275 | G51: — | H51: — | I51: — | K51: =F51*C51*IF(E51="OpenRouter",$F$3,$F$4) -> 2.7673662 | L51: 0 | M51: =ROUNDUP(K51*(C51/D51)/($B$4*(1-IF(B51="фикс",$B$6,AH51))),0) -> 12 | N51: 0 | O51: =MAX(L51,M51,N51,Z51) -> 14 | P51: =ROUND(O51/C51,0) -> 14 | Q51: =1-K51/(O51*$B$4) -> 0.40301283 | U51: тир качества — ступень +15% к предыдущему тиру | Z51: =ROUNDUP(O42*1.15,0) -> 14 | AA51: =O51 -> 14 | AB51: 1 | AC51: — | AD51: Kie | AE51: — | AF51: seedream/5-lite-text-to-image | AG51: HIGH | AH51: =$B$5 -> 0.25 | AP51: да
A52: seedream-5.0 Lite 4K | B52: шт | C52: 1 | D52: 1 | E52: direct | F52: 0.0275 | G52: — | H52: — | I52: — | K52: =F52*C52*IF(E52="OpenRouter",$F$3,$F$4) -> 2.7673662 | L52: 0 | M52: =ROUNDUP(K52*(C52/D52)/($B$4*(1-IF(B52="фикс",$B$6,AH52))),0) -> 12 | N52: 0 | O52: =MAX(L52,M52,N52,Z52) -> 17 | P52: =ROUND(O52/C52,0) -> 17 | Q52: =1-K52/(O52*$B$4) -> 0.50836351 | U52: тир качества — ступень +15% к предыдущему тиру | Z52: =ROUNDUP(O51*1.15,0) -> 17 | AA52: =O52 -> 17 | AB52: 1 | AC52: — | AD52: Kie | AE52: — | AF52: seedream/5-lite-text-to-image | AG52: HIGH | AH52: =$B$5 -> 0.25 | AP52: да
A53: HappyHorse 1.1 i2v 720p | B53: сек | C53: 5 | D53: 5 | E53: OpenRouter | F53: 0.0988 | G53: direct | H53: 0.1125 | I53: — | K53: =F53*C53*IF(E53="OpenRouter",$F$3,$F$4) -> 52.453908 | L53: 0 | M53: =ROUNDUP(K53*(C53/D53)/($B$4*(1-IF(B53="фикс",$B$6,AH53))),0) -> 212 | N53: 0 | O53: =MAX(L53,M53,N53) -> 212 | P53: =ROUND(O53/C53,0) -> 42 | Q53: =1-K53/(O53*$B$4) -> 0.25274577 | U53: Основной шлюз OpenRouter, как и у t2v. Цена в паритете с t2v: формула OpenRouter входного слагаемого не содержит. kie остаётся резервом. | AA53: =O53 -> 212 | AB53: =C53 -> 5 | AC53: =IF(B53="шт","—",P53) -> 42 | AD53: OpenRouter | AE53: Kie | AF53: alibaba/happyhorse-1.1 | AG53: HIGH | AH53: =$B$5 -> 0.25 | AP53: да | AQ53: да
A54: HappyHorse 1.1 i2v 1080p | B54: сек | C54: 5 | D54: 5 | E54: OpenRouter | F54: 0.1278 | G54: direct | H54: 0.145 | I54: — | K54: =F54*C54*IF(E54="OpenRouter",$F$3,$F$4) -> 67.850298 | L54: 0 | M54: =ROUNDUP(K54*(C54/D54)/($B$4*(1-IF(B54="фикс",$B$6,AH54))),0) -> 274 | N54: 0 | O54: =MAX(L54,M54,N54) -> 274 | P54: =ROUND(O54/C54,0) -> 55 | Q54: =1-K54/(O54*$B$4) -> 0.25212746 | U54: Основной шлюз OpenRouter, как и у t2v. Цена в паритете с t2v: формула OpenRouter входного слагаемого не содержит. kie остаётся резервом. | AA54: =O54 -> 274 | AB54: =C54 -> 5 | AC54: =IF(B54="шт","—",P54) -> 55 | AD54: OpenRouter | AE54: Kie | AF54: alibaba/happyhorse-1.1 | AG54: HIGH | AH54: =$B$5 -> 0.25 | AP54: да | AQ54: да
A55: HappyHorse 1.1 r2v 720p | B55: сек | C55: 5 | D55: 5 | E55: OpenRouter | F55: 0.0988 | G55: direct | H55: 0.1125 | I55: — | K55: =F55*C55*IF(E55="OpenRouter",$F$3,$F$4) -> 52.453908 | L55: 0 | M55: =ROUNDUP(K55*(C55/D55)/($B$4*(1-IF(B55="фикс",$B$6,AH55))),0) -> 212 | N55: 0 | O55: =MAX(L55,M55,N55) -> 212 | P55: =ROUND(O55/C55,0) -> 42 | Q55: =1-K55/(O55*$B$4) -> 0.25274577 | U55: Основной шлюз OpenRouter, как и у t2v. Цена в паритете с t2v: формула OpenRouter входного слагаемого не содержит. kie остаётся резервом. | AA55: =O55 -> 212 | AB55: =C55 -> 5 | AC55: =IF(B55="шт","—",P55) -> 42 | AD55: OpenRouter | AE55: Kie | AF55: alibaba/happyhorse-1.1 | AG55: HIGH | AH55: =$B$5 -> 0.25 | AP55: да | AQ55: да
A56: HappyHorse 1.1 r2v 1080p | B56: сек | C56: 5 | D56: 5 | E56: OpenRouter | F56: 0.1278 | G56: direct | H56: 0.145 | I56: — | K56: =F56*C56*IF(E56="OpenRouter",$F$3,$F$4) -> 67.850298 | L56: 0 | M56: =ROUNDUP(K56*(C56/D56)/($B$4*(1-IF(B56="фикс",$B$6,AH56))),0) -> 274 | N56: 0 | O56: =MAX(L56,M56,N56) -> 274 | P56: =ROUND(O56/C56,0) -> 55 | Q56: =1-K56/(O56*$B$4) -> 0.25212746 | U56: Основной шлюз OpenRouter, как и у t2v. Цена в паритете с t2v: формула OpenRouter входного слагаемого не содержит. kie остаётся резервом. | AA56: =O56 -> 274 | AB56: =C56 -> 5 | AC56: =IF(B56="шт","—",P56) -> 55 | AD56: OpenRouter | AE56: Kie | AF56: alibaba/happyhorse-1.1 | AG56: HIGH | AH56: =$B$5 -> 0.25 | AP56: да | AQ56: да
A57: HappyHorse 1.0 i2v 720p — СНЯТО | B57: сек | C57: 5 | D57: 5 | E57: direct | F57: 0.14 | G57: — | H57: — | I57: — | K57: =F57*C57*IF(E57="OpenRouter",$F$3,$F$4) -> 70.44205 | L57: 0 | M57: =ROUNDUP(K57*(C57/D57)/($B$4*(1-IF(B57="фикс",$B$6,AH57))),0) -> 284 | N57: 0 | O57: =MAX(L57,M57,N57) -> 284 | P57: =ROUND(O57/C57,0) -> 57 | Q57: =1-K57/(O57*$B$4) -> 0.25089959 | U57: Маршрут только kie, посекундно по той же ставке, что t2v. Входная длительность не тарифицируется. | AA57: =O57 -> 284 | AB57: =C57 -> 5 | AC57: =IF(B57="шт","—",P57) -> 57 | AD57: Kie | AE57: — | AF57: alibaba/happyhorse-1.1 | AG57: HIGH | AH57: =$B$5 -> 0.25
A58: HappyHorse 1.0 r2v 720p — СНЯТО | B58: сек | C58: 5 | D58: 5 | E58: direct | F58: 0.14 | G58: — | H58: — | I58: — | K58: =F58*C58*IF(E58="OpenRouter",$F$3,$F$4) -> 70.44205 | L58: 0 | M58: =ROUNDUP(K58*(C58/D58)/($B$4*(1-IF(B58="фикс",$B$6,AH58))),0) -> 284 | N58: 0 | O58: =MAX(L58,M58,N58) -> 284 | P58: =ROUND(O58/C58,0) -> 57 | Q58: =1-K58/(O58*$B$4) -> 0.25089959 | U58: Маршрут только kie, посекундно по той же ставке, что t2v. Входная длительность не тарифицируется. | AA58: =O58 -> 284 | AB58: =C58 -> 5 | AC58: =IF(B58="шт","—",P58) -> 57 | AD58: Kie | AE58: — | AF58: alibaba/happyhorse-1.1 | AG58: HIGH | AH58: =$B$5 -> 0.25
A59: HappyHorse 1.0 video-edit 720p | B59: сек | C59: 5 | D59: 5 | E59: direct | F59: 0.14 | G59: — | H59: — | I59: — | K59: =F59*C59*IF(E59="OpenRouter",$F$3,$F$4) -> 70.44205 | L59: 0 | M59: =ROUNDUP(K59*(C59/D59)/($B$4*(1-IF(B59="фикс",$B$6,AH59))),0) -> 284 | N59: 0 | O59: =MAX(L59,M59,N59) -> 284 | P59: =ROUND(O59/C59,0) -> 57 | Q59: =1-K59/(O59*$B$4) -> 0.25089959 | U59: Маршрут только kie, посекундно по той же ставке, что t2v. Входная длительность не тарифицируется. | AA59: =O59 -> 284 | AB59: =C59 -> 5 | AC59: =IF(B59="шт","—",P59) -> 57 | AD59: Kie | AE59: — | AF59: alibaba/happyhorse-1.1 | AG59: HIGH | AH59: =$B$5 -> 0.25 | AP59: да
A60: HappyHorse 1.0 video-edit 1080p | B60: сек | C60: 5 | D60: 5 | E60: direct | F60: 0.24 | G60: — | H60: — | I60: — | K60: =F60*C60*IF(E60="OpenRouter",$F$3,$F$4) -> 120.7578 | L60: 0 | M60: =ROUNDUP(K60*(C60/D60)/($B$4*(1-IF(B60="фикс",$B$6,AH60))),0) -> 487 | N60: 0 | O60: =MAX(L60,M60,N60) -> 487 | P60: =ROUND(O60/C60,0) -> 97 | Q60: =1-K60/(O60*$B$4) -> 0.25111933 | U60: Маршрут только kie, посекундно по той же ставке, что t2v. Входная длительность не тарифицируется. | AA60: =O60 -> 487 | AB60: =C60 -> 5 | AC60: =IF(B60="шт","—",P60) -> 97 | AD60: Kie | AE60: — | AF60: alibaba/happyhorse-1.1 | AG60: HIGH | AH60: =$B$5 -> 0.25 | AP60: да
A61: Seedream 5.0 Pro 1K · 2-10 реф | B61: шт | C61: 1 | D61: 1 | E61: direct | F61: 0.0575 | G61: — | H61: — | I61: — | K61: =F61*C61*IF(E61="OpenRouter",$F$3,$F$4) -> 5.7863112 | L61: 0 | M61: =ROUNDUP(K61*(C61/D61)/($B$4*(1-IF(B61="фикс",$B$6,AH61))),0) -> 24 | N61: 0 | O61: =MAX(L61,M61,N61) -> 24 | P61: =ROUND(O61/C61,0) -> 24 | Q61: =1-K61/(O61*$B$4) -> 0.27185656 | U61: Строка для 2-10 референсов. 0-1 референс — по обычной строке. Себестоимость = база + 9 x $0.0025. | AA61: =O61 -> 24 | AB61: =C61 -> 1 | AC61: =IF(B61="шт","—",P61) -> — | AD61: Kie | AE61: — | AF61: seedream/5-pro-image-to-image | AG61: HIGH | AH61: =$B$5 -> 0.25 | AP61: да
A62: Seedream 5.0 Pro 2K · 2-10 реф | B62: шт | C62: 1 | D62: 1 | E62: direct | F62: 0.0925 | G62: — | H62: — | I62: — | K62: =F62*C62*IF(E62="OpenRouter",$F$3,$F$4) -> 9.3084137 | L62: 0 | M62: =ROUNDUP(K62*(C62/D62)/($B$4*(1-IF(B62="фикс",$B$6,AH62))),0) -> 38 | N62: 0 | O62: =MAX(L62,M62,N62) -> 38 | P62: =ROUND(O62/C62,0) -> 38 | Q62: =1-K62/(O62*$B$4) -> 0.26019294 | U62: Строка для 2-10 референсов. 0-1 референс — по обычной строке. Себестоимость = база + 9 x $0.0025. | AA62: =O62 -> 38 | AB62: =C62 -> 1 | AC62: =IF(B62="шт","—",P62) -> — | AD62: Kie | AE62: — | AF62: seedream/5-pro-image-to-image | AG62: HIGH | AH62: =$B$5 -> 0.25 | AP62: да
A63: Seedance 2.0 r2v 480p | B63: сек | C63: 5 | D63: 5 | E63: OpenRouter | F63: 0.067 | G63: direct | H63: 0.095 | I63: — | K63: =F63*C63*IF(E63="OpenRouter",$F$3,$F$4) -> 35.57097 | L63: 145 | M63: =ROUNDUP(K63*(C63/D63)/($B$4*(1-IF(B63="фикс",$B$6,AH63))),0) -> 144 | N63: 0 | O63: =O18 -> 145 | P63: =ROUND(O63/C63,0) -> 29 | Q63: =1-K63/(O63*$B$4) -> 0.25910938 | U63: РЕЗЕРВ KIE ВОССТАНОВЛЕН 11.08.2026 по постановлению владельца. Ставка kie на r2v равна его же ставке на t2v — правило «вход+выход», на котором строилась ред.8, в текущей карточке отсутствует. Пометка ЕДИНСТВЕННАЯ была ошибкой разметки, а не отсутствием ноги. Цена не меняется: строка зеркалит t2v, а цена t2v на этих ступенях уже держит безубыток той же ноги kie. | AA63: =O63 -> 145 | AB63: =C63 -> 5 | AC63: =IF(B63="шт","—",P63) -> 29 | AD63: OpenRouter | AE63: Kie | AF63: bytedance/seedance-2.0 | AG63: HIGH — обе ноги оплачены; резерв восстановлен 11.08.2026 | AH63: =$B$5 -> 0.25 | AP63: да | AQ63: да
A64: Seedance 2.0 r2v 720p | B64: сек | C64: 5 | D64: 5 | E64: OpenRouter | F64: 0.151 | G64: direct | H64: 0.205 | I64: — | K64: =F64*C64*IF(E64="OpenRouter",$F$3,$F$4) -> 80.16741 | L64: 323 | M64: =ROUNDUP(K64*(C64/D64)/($B$4*(1-IF(B64="фикс",$B$6,AH64))),0) -> 323 | N64: 0 | O64: =O17 -> 323 | P64: =ROUND(O64/C64,0) -> 65 | Q64: =1-K64/(O64*$B$4) -> 0.25041356 | U64: РЕЗЕРВ KIE ВОССТАНОВЛЕН 11.08.2026 по постановлению владельца. Ставка kie на r2v равна его же ставке на t2v — правило «вход+выход», на котором строилась ред.8, в текущей карточке отсутствует. Пометка ЕДИНСТВЕННАЯ была ошибкой разметки, а не отсутствием ноги. Цена не меняется: строка зеркалит t2v, а цена t2v на этих ступенях уже держит безубыток той же ноги kie. | AA64: =O64 -> 323 | AB64: =C64 -> 5 | AC64: =IF(B64="шт","—",P64) -> 65 | AD64: OpenRouter | AE64: Kie | AF64: bytedance/seedance-2.0 | AG64: HIGH — обе ноги оплачены; резерв восстановлен 11.08.2026 | AH64: =$B$5 -> 0.25 | AP64: да | AQ64: да
A65: Seedance 2.0 r2v 1080p | B65: сек | C65: 5 | D65: 5 | E65: OpenRouter | F65: 0.34 | G65: direct | H65: 0.51 | I65: — | K65: =F65*C65*IF(E65="OpenRouter",$F$3,$F$4) -> 180.5094 | L65: 776 | M65: =ROUNDUP(K65*(C65/D65)/($B$4*(1-IF(B65="фикс",$B$6,AH65))),0) -> 727 | N65: 0 | O65: =O16 -> 775 | P65: =ROUND(O65/C65,0) -> 155 | Q65: =1-K65/(O65*$B$4) -> 0.29656413 | U65: РЕЗЕРВ KIE ВОССТАНОВЛЕН 11.08.2026 по постановлению владельца. Ставка kie на r2v равна его же ставке на t2v — правило «вход+выход», на котором строилась ред.8, в текущей карточке отсутствует. Пометка ЕДИНСТВЕННАЯ была ошибкой разметки, а не отсутствием ноги. Цена не меняется: строка зеркалит t2v, а цена t2v на этих ступенях уже держит безубыток той же ноги kie. | AA65: =O65 -> 775 | AB65: =C65 -> 5 | AC65: =IF(B65="шт","—",P65) -> 155 | AD65: OpenRouter | AE65: Kie | AF65: bytedance/seedance-2.0 | AG65: HIGH — обе ноги оплачены; резерв восстановлен 11.08.2026 | AH65: =$B$5 -> 0.25 | AP65: да | AQ65: да
A66: Seedance 2.0 r2v 4K | B66: сек | C66: 5 | D66: 5 | E66: direct | F66: 1.04 | G66: — | H66: — | I66: — | K66: =F66*C66*IF(E66="OpenRouter",$F$3,$F$4) -> 523.2838 | L66: 0 | M66: =ROUNDUP(K66*(C66/D66)/($B$4*(1-IF(B66="фикс",$B$6,AH66))),0) -> 2108 | N66: 0 | O66: =O15 -> 2108 | P66: =ROUND(O66/C66,0) -> 422 | Q66: =1-K66/(O66*$B$4) -> 0.2502904 | U66: ОСНОВНАЯ НОГА СМЕНЕНА НА KIE 11.08.2026, цена зеркалит t2v той же ступени. Карточка kie тарифицирует r2v 4K по $1,040/с — столько же, сколько t2v, — то есть дешевле нашей прежней основной OpenRouter ($1,361/с). Строка стояла на дорогой ноге с ред.8, когда мы считали, что kie метрит референс как вход+выход. Снижение 2910 -> 2108, минус 27,6% клиенту, на поставщике, которому мы и так платим. OpenRouter при новой цене даёт −3,5% и в лестницу не допускается. | AA66: =O66 -> 2108 | AB66: =C66 -> 5 | AC66: =IF(B66="шт","—",P66) -> 422 | AD66: Kie | AE66: — | AF66: bytedance/seedance-2.0 | AG66: HIGH — ставка kie оплачена; смена основной ноги 11.08.2026 | AH66: =$B$5 -> 0.25 | AP66: да
A67: Seedance Fast r2v 480p | B67: сек | C67: 5 | D67: 5 | E67: OpenRouter | F67: 0.0538 | G67: direct | H67: 0.0775 | I67: — | K67: =F67*C67*IF(E67="OpenRouter",$F$3,$F$4) -> 28.562958 | L67: 118 | M67: =ROUNDUP(K67*(C67/D67)/($B$4*(1-IF(B67="фикс",$B$6,AH67))),0) -> 116 | N67: 0 | O67: =O20 -> 118 | P67: =ROUND(O67/C67,0) -> 24 | Q67: =1-K67/(O67*$B$4) -> 0.26894919 | U67: РЕЗЕРВ KIE ВОССТАНОВЛЕН 11.08.2026 по постановлению владельца — ставка kie на r2v равна его же ставке на t2v. Пометка ЕДИНСТВЕННАЯ была ошибкой разметки. Цена не меняется. | AA67: =O67 -> 118 | AB67: =C67 -> 5 | AC67: =IF(B67="шт","—",P67) -> 24 | AD67: OpenRouter | AE67: Kie | AF67: bytedance/seedance-2.0 | AG67: HIGH — обе ноги оплачены; резерв восстановлен 11.08.2026 | AH67: =$B$5 -> 0.25 | AP67: да | AQ67: да
A68: Seedance Fast r2v 720p | B68: сек | C68: 5 | D68: 5 | E68: OpenRouter | F68: 0.121 | G68: direct | H68: 0.165 | I68: — | K68: =F68*C68*IF(E68="OpenRouter",$F$3,$F$4) -> 64.24011 | L68: 259 | M68: =ROUNDUP(K68*(C68/D68)/($B$4*(1-IF(B68="фикс",$B$6,AH68))),0) -> 259 | N68: 0 | O68: =O19 -> 259 | P68: =ROUND(O68/C68,0) -> 52 | Q68: =1-K68/(O68*$B$4) -> 0.25091189 | U68: РЕЗЕРВ KIE ВОССТАНОВЛЕН 11.08.2026 по постановлению владельца — ставка kie на r2v равна его же ставке на t2v. Пометка ЕДИНСТВЕННАЯ была ошибкой разметки. Цена не меняется. | AA68: =O68 -> 259 | AB68: =C68 -> 5 | AC68: =IF(B68="шт","—",P68) -> 52 | AD68: OpenRouter | AE68: Kie | AF68: bytedance/seedance-2.0 | AG68: HIGH — обе ноги оплачены; резерв восстановлен 11.08.2026 | AH68: =$B$5 -> 0.25 | AP68: да | AQ68: да
A69: Kling v3 720p (без звука) | B69: сек | C69: 5 | D69: 5 | E69: OpenRouter | F69: 0.084 | G69: — | H69: — | I69: — | K69: =F69*C69*IF(E69="OpenRouter",$F$3,$F$4) -> 44.59644 | L69: 0 | M69: =ROUNDUP(K69*(C69/D69)/($B$4*(1-IF(B69="фикс",$B$6,AH69))),0) -> 180 | N69: 0 | O69: =MAX(L69,M69,N69) -> 180 | P69: =ROUND(O69/C69,0) -> 36 | Q69: =1-K69/(O69*$B$4) -> 0.25173733 | U69: ЕДИНСТВЕННАЯ НОГА — OpenRouter. Ноги kie у этой модели не существует: ни слага в адаптере, ни переопределения шлюза, ни в контракте маршрута. Ставка kie, по которой строка была оценена в ред.10, относилась к маршруту, которого нет. Пересчитано от реальной ноги 04.08.2026. Standard $0,126/с со звуком, $0,084/с без звука (Pro $0,168/$0,112 не продаём). | AA69: =O69 -> 180 | AB69: =C69 -> 5 | AC69: =P69 -> 36 | AD69: OpenRouter | AE69: — | AF69: kwaivgi/kling-v3.0-std | AG69: HIGH — прайс OpenRouter, Standard | AH69: =$B$5 -> 0.25 | AP69: да
A70: Kling v3 1080p (звук) — СНЯТО | B70: сек | C70: 5 | D70: 5 | E70: direct | F70: 0.135 | G70: — | H70: — | I70: — | K70: =F70*C70*IF(E70="OpenRouter",$F$3,$F$4) -> 67.926263 | L70: 0 | M70: =ROUNDUP(K70*(C70/D70)/($B$4*(1-AH70)),0) -> 274 | N70: 0 | O70: =MAX(L70,M70,N70) -> 274 | P70: =ROUND(O70/C70,0) -> 55 | Q70: =1-K70/(O70*$B$4) -> 0.25129015 | U70: СНЯТО 04.08.2026: у модели в каталоге объявлен единственный рунг 720p. Строки относились к рунгам, которых нет в продаже. | AA70: =O70 -> 274 | AB70: =C70 -> 5 | AC70: =IF(B70="за клип","—",P70) -> 55 | AD70: Kie | AE70: — | AF70: kling-v3-0-std | AG70: HIGH — карточка kie, платно проверен | AH70: 0.25
A71: Kling v3 4K (звук) — СНЯТО | B71: сек | C71: 5 | D71: 5 | E71: direct | F71: 0.335 | G71: — | H71: — | I71: — | K71: =F71*C71*IF(E71="OpenRouter",$F$3,$F$4) -> 168.55776 | L71: 0 | M71: =ROUNDUP(K71*(C71/D71)/($B$4*(1-AH71)),0) -> 679 | N71: 0 | O71: =MAX(L71,M71,N71) -> 679 | P71: =ROUND(O71/C71,0) -> 136 | Q71: =1-K71/(O71*$B$4) -> 0.25026916 | U71: СНЯТО 04.08.2026: у модели в каталоге объявлен единственный рунг 720p. Строки относились к рунгам, которых нет в продаже. | AA71: =O71 -> 679 | AB71: =C71 -> 5 | AC71: =IF(B71="за клип","—",P71) -> 136 | AD71: Kie | AE71: — | AF71: kling-v3-0-std | AG71: HIGH — карточка kie, платно проверен | AH71: 0.25
A72: Veo Quality 4K | B72: за клип | C72: 8 | D72: 8 | E72: direct | F72: 1.85 | G72: — | H72: — | I72: 148 | K72: =F72*IF(E72="OpenRouter",$F$3,$F$4) -> 186.16827 | L72: =ROUNDUP(5.014*T72,0) -> 743 | M72: =ROUNDUP(K72*(C72/D72)/($B$4*(1-AH72)),0) -> 750 | N72: 0 | O72: =MAX(M72,N72) -> 750 | P72: =ROUND(O72/C72,0) -> 94 | Q72: =1-K72/(O72*$B$4) -> 0.25032884 | T72: 148 | U72: Ставка kie, подтверждена платными вызовами. Цена по полу маржи: потолок щедрости ниже пола (Syntx продаёт 4K дешевле нашей закупки), поэтому здесь мы сознательно менее щедры. | AA72: =O72 -> 750 | AB72: =C72 -> 8 | AC72: =IF(B72="за клип","—",P72) -> — | AD72: Kie | AE72: — | AF72: veo-3-1 | AG72: HIGH — kie, платно проверен | AH72: 0.25 | AP72: да
A73: Veo Fast 4K | B73: за клип | C73: 8 | D73: 8 | E73: direct | F73: 0.9 | G73: — | H73: — | I73: 48 | K73: =F73*IF(E73="OpenRouter",$F$3,$F$4) -> 90.56835 | L73: =ROUNDUP(5.014*T73,0) -> 241 | M73: =ROUNDUP(K73*(C73/D73)/($B$4*(1-AH73)),0) -> 365 | N73: 0 | O73: =MAX(M73,N73) -> 365 | P73: =ROUND(O73/C73,0) -> 46 | Q73: =1-K73/(O73*$B$4) -> 0.2506064 | T73: 48 | U73: Ставка kie, подтверждена платными вызовами. Цена по полу маржи: потолок щедрости ниже пола (Syntx продаёт 4K дешевле нашей закупки), поэтому здесь мы сознательно менее щедры. | AA73: =O73 -> 365 | AB73: =C73 -> 8 | AC73: =IF(B73="за клип","—",P73) -> — | AD73: Kie | AE73: — | AF73: veo-3-1-fast | AG73: HIGH — kie, платно проверен | AH73: 0.25 | AP73: да
A74: Veo Lite 4K | B74: за клип | C74: 8 | D74: 8 | E74: direct | F74: 0.75 | G74: — | H74: — | I74: 29 | K74: =F74*IF(E74="OpenRouter",$F$3,$F$4) -> 75.473625 | L74: =ROUNDUP(5.014*T74,0) -> 146 | M74: =ROUNDUP(K74*(C74/D74)/($B$4*(1-AH74)),0) -> 304 | N74: 0 | O74: =MAX(M74,N74) -> 304 | P74: =ROUND(O74/C74,0) -> 38 | Q74: =1-K74/(O74*$B$4) -> 0.25019554 | T74: 29 | U74: Ставка kie, подтверждена платными вызовами. Цена по полу маржи: потолок щедрости ниже пола (Syntx продаёт 4K дешевле нашей закупки), поэтому здесь мы сознательно менее щедры. | AA74: =O74 -> 304 | AB74: =C74 -> 8 | AC74: =IF(B74="за клип","—",P74) -> — | AD74: Kie | AE74: — | AF74: veo-3-1-lite | AG74: HIGH — kie, платно проверен | AH74: 0.25 | AP74: да
A75: Kling v3 1080p (без звука) — СНЯТО | B75: сек | C75: 5 | D75: 5 | E75: direct | F75: 0.09 | G75: — | H75: — | I75: — | K75: =F75*C75*IF(E75="OpenRouter",$F$3,$F$4) -> 45.284175 | L75: 0 | M75: =ROUNDUP(K75*(C75/D75)/($B$4*(1-AH75)),0) -> 183 | N75: 0 | O75: =MAX(L75,M75,N75) -> 183 | P75: =ROUND(O75/C75,0) -> 37 | Q75: =1-K75/(O75*$B$4) -> 0.25265392 | U75: СНЯТО 04.08.2026: у модели в каталоге объявлен единственный рунг 720p. Строки относились к рунгам, которых нет в продаже. | AA75: =O75 -> 183 | AB75: =C75 -> 5 | AC75: =P75 -> 37 | AD75: Kie | AE75: — | AF75: kling-v3-0-std | AG75: HIGH — карточка kie | AH75: 0.25
A76: Kling v3 720p i2v (звук) | B76: сек | C76: 5 | D76: 5 | E76: OpenRouter | F76: 0.126 | G76: — | H76: — | I76: — | K76: =F76*C76*IF(E76="OpenRouter",$F$3,$F$4) -> 66.89466 | L76: 0 | M76: =ROUNDUP(K76*(C76/D76)/($B$4*(1-AH76)),0) -> 270 | N76: 0 | O76: =MAX(L76,M76,N76) -> 270 | P76: =ROUND(O76/C76,0) -> 54 | Q76: =1-K76/(O76*$B$4) -> 0.25173733 | U76: ЕДИНСТВЕННАЯ НОГА — OpenRouter. Ноги kie у этой модели не существует: ни слага в адаптере, ни переопределения шлюза, ни в контракте маршрута. Ставка kie, по которой строка была оценена в ред.10, относилась к маршруту, которого нет. Пересчитано от реальной ноги 04.08.2026. Standard $0,126/с со звуком, $0,084/с без звука (Pro $0,168/$0,112 не продаём). | AA76: =O76 -> 270 | AB76: =C76 -> 5 | AC76: =IF(B76="шт","—",P76) -> 54 | AD76: OpenRouter | AE76: — | AF76: kwaivgi/kling-v3.0-std | AG76: HIGH — прайс OpenRouter, Standard | AH76: 0.25 | AP76: да
A77: Wan 2.7 720p i2v | B77: сек | C77: 5 | D77: 5 | E77: direct | F77: 0.08 | G77: OpenRouter | H77: 0.1 | I77: — | K77: =F77*C77*IF(E77="OpenRouter",$F$3,$F$4) -> 40.2526 | L77: 0 | M77: =ROUNDUP(K77*(C77/D77)/($B$4*(1-AH77)),0) -> 163 | N77: 0 | O77: =O25 -> 163 | P77: =ROUND(O77/C77,0) -> 33 | Q77: =1-K77/(O77*$B$4) -> 0.25418223 | U77: ПЕРЕСЧИТАНО НА KIE 11.08.2026 ПО ПЛАТНОМУ ВЫЗОВУ. Задача d1f623742cc98f2af897ab45048eb63d: Wan 2.7 i2v, kie, 720p, 5 с, списано $0,40 = ровно $0,08/с. Совпадает с карточкой kie от 02-08 до цента, расхождение 0,00%. ВЫЗОВ ШЁЛ ЧЕРЕЗ НАШ АДАПТЕР, А НЕ ЧЕРЕЗ curl — и это то, что делает его доказательством. curl подтвердил бы, что работает вендор, и ничего не сказал бы про код, который его зовёт. Ред.18 откатывали именно потому, что вендор работал, ставка была верна, а позвать его наш код не мог. КАНАЛ УЧТЁН: kie идёт прямым каналом (100,6315 ₽/$), OpenRouter своим (106,182 ₽/$); разница каналов сама по себе 5,5%, и цена считается по множителю той ноги, которая обслуживает. РЕЖИМЫ СОШЛИСЬ: i2v теперь зеркалит t2v по ссылке, а не пересчитывается отдельно. Разница в цене между режимами реальна только тогда, когда режимы уезжают к разным ногам — здесь они больше не уезжают. | AA77: =O77 -> 163 | AB77: =C77 -> 5 | AC77: =IF(B77="шт","—",P77) -> 33 | AD77: Kie | AE77: OpenRouter | AF77: alibaba/wan-2.7 | AG77: HIGH — платный вызов через подключённый слаг 11.08.2026, ставка подтверждена до цента | AH77: 0.25 | AP77: да | AQ77: да
A78: Wan 2.7 1080p i2v | B78: сек | C78: 5 | D78: 5 | E78: direct | F78: 0.12 | G78: OpenRouter | H78: 0.15 | I78: — | K78: =F78*C78*IF(E78="OpenRouter",$F$3,$F$4) -> 60.3789 | L78: 0 | M78: =ROUNDUP(K78*(C78/D78)/($B$4*(1-AH78)),0) -> 244 | N78: 0 | O78: =O26 -> 244 | P78: =ROUND(O78/C78,0) -> 49 | Q78: =1-K78/(O78*$B$4) -> 0.25265392 | U78: ПЕРЕСЧИТАНО НА KIE 11.08.2026 ПО ПЛАТНОМУ ВЫЗОВУ. Задача d1f623742cc98f2af897ab45048eb63d: Wan 2.7 i2v, kie, 720p, 5 с, списано $0,40 = ровно $0,08/с. Совпадает с карточкой kie от 02-08 до цента, расхождение 0,00%. ВЫЗОВ ШЁЛ ЧЕРЕЗ НАШ АДАПТЕР, А НЕ ЧЕРЕЗ curl — и это то, что делает его доказательством. curl подтвердил бы, что работает вендор, и ничего не сказал бы про код, который его зовёт. Ред.18 откатывали именно потому, что вендор работал, ставка была верна, а позвать его наш код не мог. КАНАЛ УЧТЁН: kie идёт прямым каналом (100,6315 ₽/$), OpenRouter своим (106,182 ₽/$); разница каналов сама по себе 5,5%, и цена считается по множителю той ноги, которая обслуживает. РЕЖИМЫ СОШЛИСЬ: i2v теперь зеркалит t2v по ссылке, а не пересчитывается отдельно. Разница в цене между режимами реальна только тогда, когда режимы уезжают к разным ногам — здесь они больше не уезжают. | AA78: =O78 -> 244 | AB78: =C78 -> 5 | AC78: =IF(B78="шт","—",P78) -> 49 | AD78: Kie | AE78: OpenRouter | AF78: alibaba/wan-2.7 | AG78: HIGH — платный вызов через подключённый слаг 11.08.2026, ставка подтверждена до цента | AH78: 0.25 | AP78: да | AQ78: да
A79: flux-2-pro 1K · 2-8 реф | B79: шт | C79: 1 | D79: 1 | E79: direct | F79: 0.025 | G79: OpenRouter | H79: 0.0315 | I79: — | K79: =F79*C79*IF(E79="OpenRouter",$F$3,$F$4) -> 2.5157875 | L79: 0 | M79: =ROUNDUP(K79*(C79/D79)/($B$4*(1-AH79)),0) -> 11 | N79: 0 | O79: 14 | P79: =ROUND(O79/C79,0) -> 14 | Q79: =1-K79/(O79*$B$4) -> 0.45728439 | U79: СРОК 2026-08-24 СНЯТ 11.08.2026 — он был поставлен неверно. Строка не является риском: при цене 14 кредитов ОБЕ ноги выше порога — kie 45,7%, OpenRouter 27,8%. Гасить работающую строку, которая проходит порог на обеих ногах, строго хуже, чем держать её, возможно, на три кредита дороже нужного. ЧТО НА САМОМ ДЕЛЕ РЕШАЕТ ПЛАТНЫЙ ВЫЗОВ: не выживание строки, а справедливость цены. Если kie принимает 2-8 референсов, верная цена 11 и полоса схлопывается в базовую строку. Если не принимает — запрос уходит на OpenRouter, и 11 кредитов дают там 8,2%, ниже порога, то есть 14 обязательны. Обе цены не могут быть верны одновременно, и без замера безопасна только большая. КЛАССИФИКАЦИЯ: не дедлайн соответствия, а возможная переплата клиента в 3 кредита. Остаётся в списке как вопрос честности цены, а не как срок, после которого что-то отключается. | AA79: =O79 -> 14 | AB79: =C79 -> 1 | AC79: =IF(B79="шт","—",P79) -> — | AD79: Kie | AE79: OpenRouter | AF79: black-forest-labs/flux.2-pro | AG79: СРЕДНЯЯ — обе ноги подписаны и обе выше порога; не подтверждено, принимает ли kie 2-8 референсов | AH79: 0.25 | AO79: 1.049 | AP79: да | AQ79: да
A80: Veo Quality 720p i2v | B80: за клип | C80: 8 | D80: 8 | E80: direct | F80: 1.25 | G80: — | H80: — | I80: 119 | K80: =K9 -> 125.78938 | L80: 0 | M80: =M9 -> 507 | N80: =N9 -> 0 | O80: =O9 -> 597 | P80: =P9 -> 75 | Q80: =Q9 -> 0.36365004 | U80: НУЛЕВАЯ ДЕЛЬТА, подтверждено письменно 04.08.2026. Режим не меняет закупку относительно строки «Veo Quality 720p» — цена та же. | AA80: =O80 -> 597 | AB80: =C80 -> 8 | AC80: =IF(B80="шт","—",P80) -> 75 | AD80: Kie | AE80: — | AF80: veo-3-1 | AG80: HIGH — бенчмарк Syntx подтверждён владельцем 03.08.2026 | AH80: 0.25 | AP80: да
A81: Veo Quality 1080p i2v | B81: за клип | C81: 8 | D81: 8 | E81: direct | F81: 1.275 | G81: — | H81: — | I81: 119 | K81: =K10 -> 128.30516 | L81: 0 | M81: =M10 -> 517 | N81: =N10 -> 0 | O81: =O10 -> 597 | P81: =P10 -> 75 | Q81: =Q10 -> 0.35092304 | U81: НУЛЕВАЯ ДЕЛЬТА, подтверждено письменно 04.08.2026. Режим не меняет закупку относительно строки «Veo Quality 1080p» — цена та же. | AA81: =O81 -> 597 | AB81: =C81 -> 8 | AC81: =IF(B81="шт","—",P81) -> 75 | AD81: Kie | AE81: — | AF81: veo-3-1 | AG81: HIGH — бенчмарк Syntx подтверждён владельцем 03.08.2026 | AH81: 0.25 | AP81: да
A82: Veo Fast 720p i2v | B82: за клип | C82: 8 | D82: 8 | E82: direct | F82: 0.3 | G82: — | H82: — | I82: 19 | K82: =K11 -> 30.18945 | L82: 0 | M82: =M11 -> 122 | N82: =N11 -> 0 | O82: =O11 -> 122 | P82: =P11 -> 15 | Q82: =Q11 -> 0.25265392 | U82: НУЛЕВАЯ ДЕЛЬТА, подтверждено письменно 04.08.2026. Режим не меняет закупку относительно строки «Veo Fast 720p» — цена та же. | AA82: =O82 -> 122 | AB82: =C82 -> 8 | AC82: =IF(B82="шт","—",P82) -> 15 | AD82: Kie | AE82: — | AF82: veo-3-1 | AG82: HIGH — бенчмарк Syntx подтверждён владельцем 03.08.2026 | AH82: 0.25 | AP82: да
A83: Veo Fast 1080p i2v | B83: за клип | C83: 8 | D83: 8 | E83: direct | F83: 0.325 | G83: — | H83: — | I83: 19 | K83: =K12 -> 32.705238 | L83: 0 | M83: =M12 -> 132 | N83: =N12 -> 0 | O83: =O12 -> 132 | P83: =P12 -> 17 | Q83: =Q12 -> 0.2517103 | U83: НУЛЕВАЯ ДЕЛЬТА, подтверждено письменно 04.08.2026. Режим не меняет закупку относительно строки «Veo Fast 1080p» — цена та же. | AA83: =O83 -> 132 | AB83: =C83 -> 8 | AC83: =IF(B83="шт","—",P83) -> 17 | AD83: Kie | AE83: — | AF83: veo-3-1 | AG83: HIGH — бенчмарк Syntx подтверждён владельцем 03.08.2026 | AH83: 0.25 | AP83: да
A84: Veo Lite 720p i2v | B84: за клип | C84: 8 | D84: 8 | E84: direct | F84: 0.15 | G84: — | H84: — | I84: 13 | K84: =K13 -> 15.094725 | L84: 0 | M84: =M13 -> 61 | N84: =N13 -> 0 | O84: =O13 -> 66 | P84: =P13 -> 8 | Q84: =Q13 -> 0.30927105 | U84: НУЛЕВАЯ ДЕЛЬТА, подтверждено письменно 04.08.2026. Режим не меняет закупку относительно строки «Veo Lite 720p» — цена та же. | AA84: =O84 -> 66 | AB84: =C84 -> 8 | AC84: =IF(B84="шт","—",P84) -> 8 | AD84: Kie | AE84: — | AF84: veo-3-1 | AG84: HIGH — бенчмарк Syntx подтверждён владельцем 03.08.2026 | AH84: 0.25 | AP84: да
A85: Veo Lite 1080p i2v | B85: за клип | C85: 8 | D85: 8 | E85: direct | F85: 0.175 | G85: — | H85: — | I85: 13 | K85: =K14 -> 17.610512 | L85: 0 | M85: =M14 -> 71 | N85: =N14 -> 0 | O85: =O14 -> 71 | P85: =P14 -> 9 | Q85: =Q14 -> 0.25089959 | U85: НУЛЕВАЯ ДЕЛЬТА, подтверждено письменно 04.08.2026. Режим не меняет закупку относительно строки «Veo Lite 1080p» — цена та же. | AA85: =O85 -> 71 | AB85: =C85 -> 8 | AC85: =IF(B85="шт","—",P85) -> 9 | AD85: Kie | AE85: — | AF85: veo-3-1 | AG85: HIGH — бенчмарк Syntx подтверждён владельцем 03.08.2026 | AH85: 0.25 | AP85: да
A86: seedream-4.5 1K i2i | B86: карт | C86: 1 | D86: 1 | E86: direct | F86: 0.0325 | G86: OpenRouter | H86: 0.04 | I86: 2 | K86: =K39 -> 3.2705238 | L86: 0 | M86: =M39 -> 14 | N86: =N39 -> 13 | O86: =O39 -> 14 | P86: =P39 -> 14 | Q86: =Q39 -> 0.29446971 | U86: НУЛЕВАЯ ДЕЛЬТА, подтверждено письменно 04.08.2026. Режим не меняет закупку относительно строки «seedream-4.5 1K» — цена та же. | AA86: =O86 -> 14 | AB86: =C86 -> 1 | AC86: =IF(B86="шт","—",P86) -> 14 | AD86: Kie | AE86: OpenRouter | AF86: seedream-4-5 | AG86: HIGH | AH86: 0.25 | AP86: да | AQ86: да
A87: seedream-4.5 2K i2i | B87: шт | C87: 1 | D87: 1 | E87: direct | F87: 0.0325 | G87: OpenRouter | H87: 0.04 | I87: — | K87: =K49 -> 3.2705238 | L87: 0 | M87: =M49 -> 14 | N87: =N49 -> 13 | O87: =O49 -> 17 | P87: =P49 -> 17 | Q87: =Q49 -> 0.41897506 | U87: НУЛЕВАЯ ДЕЛЬТА, подтверждено письменно 04.08.2026. Режим не меняет закупку относительно строки «seedream-4.5 2K» — цена та же. | AA87: =O87 -> 17 | AB87: =C87 -> 1 | AC87: =IF(B87="шт","—",P87) -> — | AD87: Kie | AE87: OpenRouter | AF87: seedream-4-5 | AG87: HIGH | AH87: 0.25 | AP87: да | AQ87: да
A88: seedream-4.5 4K i2i | B88: шт | C88: 1 | D88: 1 | E88: direct | F88: 0.0325 | G88: OpenRouter | H88: 0.04 | I88: — | K88: =K50 -> 3.2705238 | L88: 0 | M88: =M50 -> 14 | N88: =N50 -> 13 | O88: =O50 -> 20 | P88: =P50 -> 20 | Q88: =Q50 -> 0.5061288 | U88: НУЛЕВАЯ ДЕЛЬТА, подтверждено письменно 04.08.2026. Режим не меняет закупку относительно строки «seedream-4.5 4K» — цена та же. | AA88: =O88 -> 20 | AB88: =C88 -> 1 | AC88: =IF(B88="шт","—",P88) -> — | AD88: Kie | AE88: OpenRouter | AF88: seedream-4-5 | AG88: HIGH | AH88: 0.25 | AP88: да | AQ88: да
A89: gpt-image-2 i2i (low) | B89: карт | C89: 1 | D89: 1 | E89: direct | F89: 0.03 | G89: direct | H89: 0.03 | I89: 2 | K89: =K36 -> 3.018945 | L89: 0 | M89: =M36 -> 13 | N89: 0 | O89: =O36 -> 13 | P89: =P36 -> 13 | Q89: =Q36 -> 0.29864445 | U89: Kie fallback gpt-image-2-image-to-image $0.03/low; owner list 2026-07-25. Costed reserve; quality mapping remains unarmed. | AA89: =O89 -> 13 | AB89: =C89 -> 1 | AC89: =IF(B89="шт","—",P89) -> 13 | AD89: LaoZhang | AE89: Kie | AF89: gpt-image-2-vip | AG89: ЗАМЕРЕНО 09.08.2026 — платный вызов, счётчик откалиброван | AH89: 0.25 | AP89: да
A90: gpt-image-2 i2i (medium) | B90: шт | C90: 1 | D90: 1 | E90: direct | F90: 0.03 | G90: direct | H90: 0.05 | I90: — | K90: =K37 -> 3.018945 | L90: 0 | M90: =M37 -> 13 | N90: 0 | O90: =O37 -> 21 | P90: =P37 -> 21 | Q90: =Q37 -> 0.56582751 | U90: Kie fallback gpt-image-2-image-to-image $0.05/medium; owner list 2026-07-25. Costed reserve; quality mapping remains unarmed. | AA90: =O90 -> 21 | AB90: =C90 -> 1 | AC90: =IF(B90="шт","—",P90) -> — | AD90: LaoZhang | AE90: Kie | AF90: gpt-image-2-vip | AG90: ЗАМЕРЕНО 09.08.2026 — платный вызов, счётчик откалиброван | AH90: 0.25 | AP90: да
A91: gpt-image-2 i2i (high) | B91: шт | C91: 1 | D91: 1 | E91: direct | F91: 0.03 | G91: direct | H91: 0.08 | I91: — | K91: =K38 -> 3.018945 | L91: 0 | M91: =M38 -> 13 | N91: 0 | O91: =O38 -> 33 | P91: =P38 -> 33 | Q91: =Q38 -> 0.72370842 | U91: Kie fallback gpt-image-2-image-to-image $0.08/high; owner list 2026-07-25. Costed reserve; quality mapping remains unarmed. | AA91: =O91 -> 33 | AB91: =C91 -> 1 | AC91: =IF(B91="шт","—",P91) -> — | AD91: LaoZhang | AE91: Kie | AF91: gpt-image-2-vip | AG91: ЗАМЕРЕНО 09.08.2026 — платный вызов, счётчик откалиброван | AH91: 0.25 | AP91: да
A92: nano-banana i2i | B92: карт | C92: 1 | D92: 1 | E92: direct | F92: 0.02 | G92: direct | H92: 0.02 | I92: 1.5 | K92: =K31 -> 2.01263 | L92: 0 | M92: =M31 -> 9 | N92: 0 | O92: =O31 -> 9 | P92: =P31 -> 9 | Q92: =Q31 -> 0.32462058 | U92: Kie fallback google/nano-banana-edit $0.02/edit; owner list 2026-07-25; i2i route connected. | AA92: =O92 -> 9 | AB92: =C92 -> 1 | AC92: =IF(B92="шт","—",P92) -> 9 | AD92: LaoZhang | AE92: Kie | AF92: gemini-2-5-flash-image | AG92: HIGH; ЕДИНСТВЕННАЯ НОГА — резерва не существует | AH92: 0.25 | AP92: да | AQ92: да
A93: nano-banana-2 1K i2i | B93: карт | C93: 1 | D93: 1 | E93: direct | F93: 0.04 | G93: direct | H93: 0.055 | I93: 3 | K93: =K32 -> 4.02526 | L93: 0 | M93: =M32 -> 17 | N93: =N32 -> 17 | O93: =O32 -> 17 | P93: =P32 -> 17 | Q93: =Q32 -> 0.28489238 | U93: НУЛЕВАЯ ДЕЛЬТА, подтверждено письменно 04.08.2026. Режим не меняет закупку относительно строки «nano-banana-2 1K» — цена та же. | AA93: =O93 -> 17 | AB93: =C93 -> 1 | AC93: =IF(B93="шт","—",P93) -> 17 | AD93: Kie | AE93: LaoZhang | AF93: nano-banana-2 | AG93: HIGH | AH93: 0.25 | AP93: да | AQ93: да
A94: nano-banana-2-lite i2i | B94: карт | C94: 1 | D94: 1 | E94: direct | F94: 0.02 | G94: direct | H94: 0.025 | I94: 1.3 | K94: =K33 -> 2.01263 | L94: 0 | M94: =M33 -> 9 | N94: =N33 -> 8 | O94: =O33 -> 9 | P94: =P33 -> 9 | Q94: =Q33 -> 0.32462058 | U94: НУЛЕВАЯ ДЕЛЬТА, подтверждено письменно 04.08.2026. Режим не меняет закупку относительно строки «nano-banana-2-lite» — цена та же. | AA94: =O94 -> 9 | AB94: =C94 -> 1 | AC94: =IF(B94="шт","—",P94) -> 9 | AD94: Kie | AE94: LaoZhang | AF94: nano-banana-2-lite | AG94: HIGH | AH94: 0.25 | AP94: да | AQ94: да
A95: nano-banana-pro 1K i2i | B95: карт | C95: 1 | D95: 1 | E95: direct | F95: 0.09 | G95: — | H95: — | I95: 2 | K95: =K34 -> 9.056835 | L95: 0 | M95: =M34 -> 37 | N95: 0 | O95: =O34 -> 37 | P95: =P34 -> 37 | Q95: =Q34 -> 0.26073334 | U95: ВТОРОЙ НОГИ НЕТ. В колонках резерва стояла побайтовая копия основной ставки без имени поставщика — заглушка, которую экспорт выгружал как настоящую ногу. Убрана 10.08.2026. Модель обслуживается одним LaoZhang: при его недоступности строка не переключается, а отказывает. Это факт для бюджета отказов, а не дефект цены — цена и маржа не менялись. | AA95: =O95 -> 37 | AB95: =C95 -> 1 | AC95: =IF(B95="шт","—",P95) -> 37 | AD95: LaoZhang | AE95: — | AF95: nano-banana-pro | AG95: HIGH; ЕДИНСТВЕННАЯ НОГА — резерва не существует | AH95: 0.25 | AP95: да
A96: Seedance 2.0 i2v 480p | B96: сек | C96: 5 | D96: 5 | E96: OpenRouter | F96: 0.067 | G96: direct | H96: 0.095 | I96: 20.375 | K96: =K18 -> 35.57097 | L96: 0 | M96: =M18 -> 144 | N96: =N18 -> 145 | O96: =O18 -> 145 | P96: =P18 -> 29 | Q96: =Q18 -> 0.25910938 | U96: НУЛЕВАЯ ДЕЛЬТА, подтверждено письменно 04.08.2026. Режим не меняет закупку относительно строки «Seedance 2.0 480p» — цена та же. РЕШЕНИЕ ВЛАДЕЛЬЦА 11.08.2026 — НАДБАВКА ЗА РЕЗЕРВ ОСТАЁТСЯ. Правило цены остаётся из четырёх членов: MAX(потолок +28% vs Syntx; цена по марже 25%; БЕЗУБЫТОК РЕЗЕРВА; ступень качества +15%). Вопрос ставился и закрыт: четвёртый член перебивает цену на 8 строках из 91, и на этих строках клиент оплачивает вторую ногу. Владелец рассмотрел цену решения и принял её. ЧЕГО ЭТО СТОИТ, ЧТОБЫ НИКТО НЕ ПЕРЕСЧИТЫВАЛ ЗАНОВО: на Seedance 1080p 775 вместо 727 — это −7,0% против Syntx вместо −0,9%, то есть страховка стоит 6 п.п. конкурентоспособности. На Gemini Omni 273 вместо 257 — −34,2% вместо −30,1%. На остальных строках надбавка стоит 1-2 кредита и на сравнение с конкурентом не влияет. ЧТО ЭТО ПОКУПАЕТ: переключение на резерв бесплатно для нас в момент отказа — резерв на этих строках выходит ровно в ноль, а не в минус, поэтому R-1 выполняется без исключений и бюджет отказов по R-11 не расходуется. ИЗВЕСТНОЕ ПОБОЧНОЕ СЛЕДСТВИЕ: при этом правиле добавление ЛЮБОЙ новой ноги может цену только поднять, никогда не опустить. Третья нога, под которую 11.08 открыт формат, работает против клиента до тех пор, пока это правило действует. Пересматривать при подключении первого третьего вендора. | AA96: =O96 -> 145 | AB96: =C96 -> 5 | AC96: =IF(B96="шт","—",P96) -> 29 | AD96: OpenRouter | AE96: Kie | AF96: seedance-2-0 | AG96: HIGH | AH96: 0.25 | AP96: да | AQ96: да
A97: Seedance 2.0 i2v 720p | B97: сек | C97: 5 | D97: 5 | E97: OpenRouter | F97: 0.151 | G97: direct | H97: 0.205 | I97: 45.375 | K97: =K17 -> 80.16741 | L97: 0 | M97: =M17 -> 323 | N97: =N17 -> 312 | O97: =O17 -> 323 | P97: =P17 -> 65 | Q97: =Q17 -> 0.25041356 | U97: НУЛЕВАЯ ДЕЛЬТА, подтверждено письменно 04.08.2026. Режим не меняет закупку относительно строки «Seedance 2.0 720p» — цена та же. | AA97: =O97 -> 323 | AB97: =C97 -> 5 | AC97: =IF(B97="шт","—",P97) -> 65 | AD97: OpenRouter | AE97: Kie | AF97: seedance-2-0 | AG97: HIGH | AH97: 0.25 | AP97: да | AQ97: да
A98: Seedance 2.0 i2v 1080p | B98: сек | C98: 5 | D98: 5 | E98: OpenRouter | F98: 0.34 | G98: direct | H98: 0.51 | I98: 112.25 | K98: =K16 -> 180.5094 | L98: 0 | M98: =M16 -> 727 | N98: =N16 -> 775 | O98: =O16 -> 775 | P98: =P16 -> 155 | Q98: =Q16 -> 0.29656413 | U98: НУЛЕВАЯ ДЕЛЬТА, подтверждено письменно 04.08.2026. Режим не меняет закупку относительно строки «Seedance 2.0 1080p» — цена та же. РЕШЕНИЕ ВЛАДЕЛЬЦА 11.08.2026 — НАДБАВКА ЗА РЕЗЕРВ ОСТАЁТСЯ. Правило цены остаётся из четырёх членов: MAX(потолок +28% vs Syntx; цена по марже 25%; БЕЗУБЫТОК РЕЗЕРВА; ступень качества +15%). Вопрос ставился и закрыт: четвёртый член перебивает цену на 8 строках из 91, и на этих строках клиент оплачивает вторую ногу. Владелец рассмотрел цену решения и принял её. ЧЕГО ЭТО СТОИТ, ЧТОБЫ НИКТО НЕ ПЕРЕСЧИТЫВАЛ ЗАНОВО: на Seedance 1080p 775 вместо 727 — это −7,0% против Syntx вместо −0,9%, то есть страховка стоит 6 п.п. конкурентоспособности. На Gemini Omni 273 вместо 257 — −34,2% вместо −30,1%. На остальных строках надбавка стоит 1-2 кредита и на сравнение с конкурентом не влияет. ЧТО ЭТО ПОКУПАЕТ: переключение на резерв бесплатно для нас в момент отказа — резерв на этих строках выходит ровно в ноль, а не в минус, поэтому R-1 выполняется без исключений и бюджет отказов по R-11 не расходуется. ИЗВЕСТНОЕ ПОБОЧНОЕ СЛЕДСТВИЕ: при этом правиле добавление ЛЮБОЙ новой ноги может цену только поднять, никогда не опустить. Третья нога, под которую 11.08 открыт формат, работает против клиента до тех пор, пока это правило действует. Пересматривать при подключении первого третьего вендора. | AA98: =O98 -> 775 | AB98: =C98 -> 5 | AC98: =IF(B98="шт","—",P98) -> 155 | AD98: OpenRouter | AE98: Kie | AF98: seedance-2-0 | AG98: HIGH | AH98: 0.25 | AP98: да | AQ98: да
A99: Seedance Fast i2v 480p | B99: сек | C99: 5 | D99: 5 | E99: OpenRouter | F99: 0.0538 | G99: direct | H99: 0.0775 | I99: 16.375 | K99: =K20 -> 28.562958 | L99: 0 | M99: =M20 -> 116 | N99: =N20 -> 118 | O99: =O20 -> 118 | P99: =P20 -> 24 | Q99: =Q20 -> 0.26894919 | U99: НУЛЕВАЯ ДЕЛЬТА, подтверждено письменно 04.08.2026. Режим не меняет закупку относительно строки «Seedance Fast 480p» — цена та же. РЕШЕНИЕ ВЛАДЕЛЬЦА 11.08.2026 — НАДБАВКА ЗА РЕЗЕРВ ОСТАЁТСЯ. Правило цены остаётся из четырёх членов: MAX(потолок +28% vs Syntx; цена по марже 25%; БЕЗУБЫТОК РЕЗЕРВА; ступень качества +15%). Вопрос ставился и закрыт: четвёртый член перебивает цену на 8 строках из 91, и на этих строках клиент оплачивает вторую ногу. Владелец рассмотрел цену решения и принял её. ЧЕГО ЭТО СТОИТ, ЧТОБЫ НИКТО НЕ ПЕРЕСЧИТЫВАЛ ЗАНОВО: на Seedance 1080p 775 вместо 727 — это −7,0% против Syntx вместо −0,9%, то есть страховка стоит 6 п.п. конкурентоспособности. На Gemini Omni 273 вместо 257 — −34,2% вместо −30,1%. На остальных строках надбавка стоит 1-2 кредита и на сравнение с конкурентом не влияет. ЧТО ЭТО ПОКУПАЕТ: переключение на резерв бесплатно для нас в момент отказа — резерв на этих строках выходит ровно в ноль, а не в минус, поэтому R-1 выполняется без исключений и бюджет отказов по R-11 не расходуется. ИЗВЕСТНОЕ ПОБОЧНОЕ СЛЕДСТВИЕ: при этом правиле добавление ЛЮБОЙ новой ноги может цену только поднять, никогда не опустить. Третья нога, под которую 11.08 открыт формат, работает против клиента до тех пор, пока это правило действует. Пересматривать при подключении первого третьего вендора. | AA99: =O99 -> 118 | AB99: =C99 -> 5 | AC99: =IF(B99="шт","—",P99) -> 24 | AD99: OpenRouter | AE99: Kie | AF99: seedance-2-0 | AG99: HIGH | AH99: 0.25 | AP99: да | AQ99: да
A100: Seedance Fast i2v 720p | B100: сек | C100: 5 | D100: 5 | E100: OpenRouter | F100: 0.121 | G100: direct | H100: 0.165 | I100: 36.25 | K100: =K19 -> 64.24011 | L100: 0 | M100: =M19 -> 259 | N100: =N19 -> 251 | O100: =O19 -> 259 | P100: =P19 -> 52 | Q100: =Q19 -> 0.25091189 | U100: НУЛЕВАЯ ДЕЛЬТА, подтверждено письменно 04.08.2026. Режим не меняет закупку относительно строки «Seedance Fast 720p» — цена та же. | AA100: =O100 -> 259 | AB100: =C100 -> 5 | AC100: =IF(B100="шт","—",P100) -> 52 | AD100: OpenRouter | AE100: Kie | AF100: seedance-2-0 | AG100: HIGH | AH100: 0.25 | AP100: да | AQ100: да
...

Sheet НОГИ (экспорт)
A1: ЭКСПОРТ ДЛЯ ДВИЖКА МАРШРУТИЗАЦИИ · ВЕРСИЯ 2026-08-14 · РЕД. 22 · ЛИСТ ГЕНЕРИРУЕТСЯ ЦЕЛИКОМ ИЗ «Сетка FX», НИКОГДА НЕ ПРАВИТСЯ ТОЧЕЧНО
A2: КЛЮЧ КОНФИГУРАЦИИ — A+B+C+D+E+Y (model_id | rung | mode | audio | quality | aspect); КЛЮЧ СТРОКИ добавляет ногу
A3: СТРОК ДАННЫХ: 140 · КОНТРОЛЬНАЯ СУММА КРЕДИТОВ: 26729 · КОНТРОЛЬНАЯ СУММА МАРЖИ: 35.241635 · РАЗЛИЧНЫХ КЛЮЧЕЙ СТРОК: 140
A4: РЕД. 22: добавлены восемь подписанных fallback-cost rows: gemini-2.5 flash image для t2i/i2i и GPT Image 2 для low/medium/high в t2i/i2i. GPT quality rows costed for margin governance; route remains unarmed until Kie quality mapping is approved. Workbook remains the SSOT; regenerate cost-legs.csv after every financial edit.
A5: ОТПЕЧАТОК ПОРЯДКА КОЛОНОК: da54ec1b730a358b · КОЛОНОК: 34 — четвёртая контрольная сумма, добавлена 11.08.2026. Три прежние суммы складывают числа и поэтому НЕ МЕНЯЮТСЯ при боковом сдвиге колонок. Этот отпечаток — хэш имён колонок в их порядке; он ломается от сдвига, вставки и переименования. Если он не совпал, а суммы совпали — читайте структуру, а не цифры.
A7: model_id | B7: rung | C7: mode | D7: audio | E7: quality | F7: leg | G7: Роль | H7: ПОСРЕДНИК | I7: АПСТРЕМ | J7: SKU у поставщика | K7: Канал | L7: Множ. | M7: База тарификации | N7: $ за ед. | O7: Landed ₽/ед | P7: Себест ₽ | Q7: Себест известна | R7: ДОСТОВЕРНОСТЬ | S7: Кредитов | T7: Маржа ноги | U7: ГЛУБИНА ЛЕСТНИЦЫ | V7: Источник | W7: Дата ISO | X7: Количество | Y7: aspect | Z7: refs_min | AA7: refs_max | AB7: цена_в_полосе | AC7: доплата_$_за_картинку | AD7: КЛЮЧ конфигурации | AE7: КЛЮЧ строки | AF7: РИСК МАРШРУТА | AG7: ступень_по_умолчанию | AH7: площадь_МП
A8: veo-3-1 | B8: 720p | C8: t2v | D8: да | F8: 1 | G8: основная | H8: Kie | I8: Google | J8: veo-3-1 | K8: прямой | L8: 1.1839 | M8: за клип | N8: 1.25 | O8: 100.6315 | P8: 125.79 | Q8: да | R8: HIGH — бенчмарк Syntx подтверждён владельцем 03.08.2026 | S8: 597 | T8: 0.36365 | U8: 1 | V8: Сетка FX стр.9 | W8: 2026-08-11 | X8: 1 | Y8: any | Z8: 0 | AA8: 0 | AB8: плоская | AC8: 0 | AD8: veo-3-1|720p|t2v|да|-|any | AE8: veo-3-1|720p|t2v|да|-|any|нога1 | AG8: 1080p
A9: veo-3-1 | B9: 1080p | C9: t2v | D9: да | F9: 1 | G9: основная | H9: Kie | I9: Google | J9: veo-3-1 | K9: прямой | L9: 1.1839 | M9: за клип | N9: 1.275 | O9: 100.6315 | P9: 128.31 | Q9: да | R9: HIGH — бенчмарк Syntx подтверждён владельцем 03.08.2026 | S9: 597 | T9: 0.350923 | U9: 1 | V9: Сетка FX стр.10 | W9: 2026-08-11 | X9: 1 | Y9: any | Z9: 0 | AA9: 0 | AB9: плоская | AC9: 0 | AD9: veo-3-1|1080p|t2v|да|-|any | AE9: veo-3-1|1080p|t2v|да|-|any|нога1 | AG9: 1080p
A10: veo-3-1-fast | B10: 720p | C10: t2v | D10: да | F10: 1 | G10: основная | H10: Kie | I10: Google | J10: veo-3-1 | K10: прямой | L10: 1.1839 | M10: за клип | N10: 0.3 | O10: 100.6315 | P10: 30.19 | Q10: да | R10: HIGH — бенчмарк Syntx подтверждён владельцем 03.08.2026 | S10: 122 | T10: 0.252654 | U10: 1 | V10: Сетка FX стр.11 | W10: 2026-08-11 | X10: 1 | Y10: any | Z10: 0 | AA10: 0 | AB10: плоская | AC10: 0 | AD10: veo-3-1-fast|720p|t2v|да|-|any | AE10: veo-3-1-fast|720p|t2v|да|-|any|нога1 | AG10: 720p
A11: veo-3-1-fast | B11: 1080p | C11: t2v | D11: да | F11: 1 | G11: основная | H11: Kie | I11: Google | J11: veo-3-1 | K11: прямой | L11: 1.1839 | M11: за клип | N11: 0.325 | O11: 100.6315 | P11: 32.71 | Q11: да | R11: HIGH — бенчмарк Syntx подтверждён владельцем 03.08.2026 | S11: 132 | T11: 0.25171 | U11: 1 | V11: Сетка FX стр.12 | W11: 2026-08-11 | X11: 1 | Y11: any | Z11: 0 | AA11: 0 | AB11: плоская | AC11: 0 | AD11: veo-3-1-fast|1080p|t2v|да|-|any | AE11: veo-3-1-fast|1080p|t2v|да|-|any|нога1 | AG11: 720p
A12: veo-3-1-lite | B12: 720p | C12: t2v | D12: да | F12: 1 | G12: основная | H12: Kie | I12: Google | J12: veo-3-1 | K12: прямой | L12: 1.1839 | M12: за клип | N12: 0.15 | O12: 100.6315 | P12: 15.09 | Q12: да | R12: HIGH — бенчмарк Syntx подтверждён владельцем 03.08.2026 | S12: 66 | T12: 0.309271 | U12: 1 | V12: Сетка FX стр.13 | W12: 2026-08-11 | X12: 1 | Y12: any | Z12: 0 | AA12: 0 | AB12: плоская | AC12: 0 | AD12: veo-3-1-lite|720p|t2v|да|-|any | AE12: veo-3-1-lite|720p|t2v|да|-|any|нога1 | AG12: 720p
A13: veo-3-1-lite | B13: 1080p | C13: t2v | D13: да | F13: 1 | G13: основная | H13: Kie | I13: Google | J13: veo-3-1 | K13: прямой | L13: 1.1839 | M13: за клип | N13: 0.175 | O13: 100.6315 | P13: 17.61 | Q13: да | R13: HIGH — бенчмарк Syntx подтверждён владельцем 03.08.2026 | S13: 71 | T13: 0.2509 | U13: 1 | V13: Сетка FX стр.14 | W13: 2026-08-11 | X13: 1 | Y13: any | Z13: 0 | AA13: 0 | AB13: плоская | AC13: 0 | AD13: veo-3-1-lite|1080p|t2v|да|-|any | AE13: veo-3-1-lite|1080p|t2v|да|-|any|нога1 | AG13: 720p
A14: seedance-2-0 | B14: 4K | C14: t2v | D14: нет | F14: 1 | G14: основная | H14: Kie | I14: ByteDance | J14: seedance-2-0 | K14: прямой | L14: 1.1839 | M14: за секунду | N14: 1.04 | O14: 100.6315 | P14: 523.28 | Q14: да | R14: HIGH — ставки платно подтверждены; имена посредников исправлены 10.08.2026 (были переставлены) | S14: 2108 | T14: 0.25029 | U14: 1 | V14: Сетка FX стр.15 | W14: 2026-08-11 | X14: 5 | Y14: any | Z14: 0 | AA14: 0 | AB14: плоская | AC14: 0 | AD14: seedance-2-0|4K|t2v|нет|-|any | AE14: seedance-2-0|4K|t2v|нет|-|any|нога1 | AG14: 480p
A15: seedance-2-0 | B15: 1080p | C15: t2v | D15: нет | F15: 1 | G15: основная | H15: OpenRouter | I15: ByteDance | J15: seedance-2-0 | K15: OpenRouter | L15: 1.2492 | M15: за секунду | N15: 0.34 | O15: 106.182 | P15: 180.51 | Q15: да | R15: HIGH | S15: 775 | T15: 0.296564 | U15: 2 | V15: Сетка FX стр.16 | W15: 2026-08-11 | X15: 5 | Y15: any | Z15: 0 | AA15: 0 | AB15: плоская | AC15: 0 | AD15: seedance-2-0|1080p|t2v|нет|-|any | AE15: seedance-2-0|1080p|t2v|нет|-|any|нога1 | AG15: 480p
A16: seedance-2-0 | B16: 1080p | C16: t2v | D16: нет | F16: 2 | G16: резервная | H16: Kie | I16: ByteDance | J16: seedance-2-0 | K16: прямой | L16: 1.1839 | M16: за секунду | N16: 0.51 | O16: 100.6315 | P16: 256.61 | Q16: да | R16: HIGH | S16: 775 | T16: 3e-06 | U16: 2 | V16: Сетка FX стр.16 | W16: 2026-08-11 | X16: 5 | Y16: any | Z16: 0 | AA16: 0 | AB16: плоская | AC16: 0 | AD16: seedance-2-0|1080p|t2v|нет|-|any | AE16: seedance-2-0|1080p|t2v|нет|-|any|нога2 | AG16: 480p
A17: seedance-2-0 | B17: 720p | C17: t2v | D17: нет | F17: 1 | G17: основная | H17: OpenRouter | I17: ByteDance | J17: seedance-2-0 | K17: OpenRouter | L17: 1.2492 | M17: за секунду | N17: 0.151 | O17: 106.182 | P17: 80.17 | Q17: да | R17: HIGH | S17: 323 | T17: 0.250414 | U17: 2 | V17: Сетка FX стр.17 | W17: 2026-08-11 | X17: 5 | Y17: any | Z17: 0 | AA17: 0 | AB17: плоская | AC17: 0 | AD17: seedance-2-0|720p|t2v|нет|-|any | AE17: seedance-2-0|720p|t2v|нет|-|any|нога1 | AG17: 480p
A18: seedance-2-0 | B18: 720p | C18: t2v | D18: нет | F18: 2 | G18: резервная | H18: Kie | I18: ByteDance | J18: seedance-2-0 | K18: прямой | L18: 1.1839 | M18: за секунду | N18: 0.205 | O18: 100.6315 | P18: 103.15 | Q18: да | R18: HIGH | S18: 323 | T18: 0.035546 | U18: 2 | V18: Сетка FX стр.17 | W18: 2026-08-11 | X18: 5 | Y18: any | Z18: 0 | AA18: 0 | AB18: плоская | AC18: 0 | AD18: seedance-2-0|720p|t2v|нет|-|any | AE18: seedance-2-0|720p|t2v|нет|-|any|нога2 | AG18: 480p
A19: seedance-2-0 | B19: 480p | C19: t2v | D19: нет | F19: 1 | G19: основная | H19: OpenRouter | I19: ByteDance | J19: seedance-2-0 | K19: OpenRouter | L19: 1.2492 | M19: за секунду | N19: 0.067 | O19: 106.182 | P19: 35.57 | Q19: да | R19: HIGH | S19: 145 | T19: 0.259109 | U19: 2 | V19: Сетка FX стр.18 | W19: 2026-08-11 | X19: 5 | Y19: any | Z19: 0 | AA19: 0 | AB19: плоская | AC19: 0 | AD19: seedance-2-0|480p|t2v|нет|-|any | AE19: seedance-2-0|480p|t2v|нет|-|any|нога1 | AG19: 480p
... A35: grok-imagine-video | B35: 480p | C35: t2v | D35: нет | F35: 1 | G35: основная | H35: Kie | I35: xAI | J35: grok-imagine-video | K35: прямой | L35: 1.1839 | M35: за секунду | N35: 0.012 | O35: 100.6315 | P35: 7.25 | Q35: да | R35: HIGH — прайс kie 04.08.2026. Порог 40% сохраняется по R-10: подтверждение источника снимает сомнение в чтении ставки, но не в её устойчивости. | S35: 37 | T35: 0.408587 | U35: 1 | V35: Сетка FX стр.29 | W35: 2026-08-11 | X35: 6 | Y35: any | Z35: 0 | AA35: 0 | AB35: плоская | AC35: 0 | AD35: grok-imagine-video|480p|t2v|нет|-|any | AE35: grok-imagine-video|480p|t2v|нет|-|any|нога1 | AG35: 480p
A36: gemini-omni-flash | B36: default | C36: t2v | D36: да | F36: 1 | G36: основная | H36: Kie | I36: Google | J36: gemini-omni-flash | K36: прямой | L36: 1.1839 | M36: за секунду | N36: 0.079 | O36: 100.6315 | P36: 63.6 | Q36: да | R36: HIGH — ставка подтверждена платно | S36: 273 | T36: 0.296418 | U36: 2 | V36: Сетка FX стр.30 | W36: 2026-08-11 | X36: 8 | Y36: any | Z36: 0 | AA36: 0 | AB36: плоская | AC36: 0 | AD36: gemini-omni-flash|default|t2v|да|-|any | AE36: gemini-omni-flash|default|t2v|да|-|any|нога1 | AF36: ТАРИФ МАРШРУТА AtlasCloud: $0,112/с держится только на ступени -developer. Стандартная ступень $0,125-0,135, и при 273 кредитах это −11,3% вместо +0,25%. Риск управляется нами, а не поставщиком: суффикс закреплён именованной константой с тестом на три режима. Внешнего сигнала у потери суффикса нет — Atlas отвечает, отдаёт видео и просто выставляет счёт дороже. | AG36: default
A37: gemini-omni-flash | B37: default | C37: t2v | D37: да | F37: 2 | G37: резервная | H37: AtlasCloud | I37: Google | J37: gemini-omni-flash | K37: прямой | L37: 1.1839 | M37: за секунду | N37: 0.112 | O37: 100.6315 | P37: 90.17 | Q37: да | R37: HIGH — ставка подтверждена платно | S37: 273 | T37: 0.002517 | U37: 2 | V37: Сетка FX стр.30 | W37: 2026-08-11 | X37: 8 | Y37: any | Z37: 0 | AA37: 0 | AB37: плоская | AC37: 0 | AD37: gemini-omni-flash|default|t2v|да|-|any | AE37: gemini-omni-flash|default|t2v|да|-|any|нога2 | AF37: ТАРИФ МАРШРУТА AtlasCloud: $0,112/с держится только на ступени -developer. Стандартная ступень $0,125-0,135, и при 273 кредитах это −11,3% вместо +0,25%. Риск управляется нами, а не поставщиком: суффикс закреплён именованной константой с тестом на три режима. Внешнего сигнала у потери суффикса нет — Atlas отвечает, отдаёт видео и просто выставляет счёт дороже. | AG37: default
A38: gemini-2-5-flash-image | B38: default | C38: t2i | D38: - | F38: 1 | G38: основная | H38: LaoZhang | I38: Google | J38: gemini-2-5-flash-image | K38: прямой | L38: 1.1839 | M38: за изображение | N38: 0.02 | O38: 100.6315 | P38: 2.01 | Q38: да | R38: HIGH; Kie reserve costed 2026-08-14 — LaoZhang remains primary; no longer single-leg. | S38: 9 | T38: 0.324621 | U38: 2 | V38: Сетка FX стр.31 | W38: 2026-08-11 | X38: 1 | Y38: any | Z38: 0 | AA38: 0 | AB38: плоская | AC38: 0 | AD38: gemini-2-5-flash-image|default|t2i|-|-|any | AE38: gemini-2-5-flash-image|default|t2i|-|-|any|нога1 | AG38: default
A39: gemini-3-1-flash-image | B39: 1K | C39: t2i | D39: - | F39: 1 | G39: основная | H39: Kie | I39: Google | J39: nano-banana-2 | K39: прямой | L39: 1.1839 | M39: за изображение | N39: 0.04 | O39: 100.6315 | P39: 4.03 | Q39: да | R39: HIGH | S39: 17 | T39: 0.284892 | U39: 2 | V39: Сетка FX стр.32 | W39: 2026-08-11 | X39: 1 | Y39: any | Z39: 0 | AA39: 0 | AB39: плоская | AC39: 0 | AD39: gemini-3-1-flash-image|1K|t2i|-|-|any | AE39: gemini-3-1-flash-image|1K|t2i|-|-|any|нога1 | AG39: 1K
A40: gemini-3-1-flash-image | B40: 1K | C40: t2i | D40: - | F40: 2 | G40: резервная | H40: LaoZhang | I40: Google | J40: nano-banana-2 | K40: прямой | L40: 1.1839 | M40: за изображение | N40: 0.055 | O40: 100.6315 | P40: 5.53 | Q40: да | R40: HIGH | S40: 17 | T40: 0.016727 | U40: 2 | V40: Сетка FX стр.32 | W40: 2026-08-11 | X40: 1 | Y40: any | Z40: 0 | AA40: 0 | AB40: плоская | AC40: 0 | AD40: gemini-3-1-flash-image|1K|t2i|-|-|any | AE40: gemini-3-1-flash-image|1K|t2i|-|-|any|нога2 | AG40: 1K
A41: gemini-3-1-flash-lite-image | B41: default | C41: t2i | D41: - | F41: 1 | G41: основная | H41: Kie | I41: Google | J41: nano-banana-2-lite | K41: прямой | L41: 1.1839 | M41: за изображение | N41: 0.02 | O41: 100.6315 | P41: 2.01 | Q41: да | R41: HIGH | S41: 9 | T41: 0.324621 | U41: 2 | V41: Сетка FX стр.33 | W41: 2026-08-11 | X41: 1 | Y41: any | Z41: 0 | AA41: 0 | AB41: плоская | AC41: 0 | AD41: gemini-3-1-flash-lite-image|default|t2i|-|-|any | AE41: gemini-3-1-flash-lite-image|default|t2i|-|-|any|нога1 | AG41: default
A42: gemini-3-1-flash-lite-image | B42: default | C42: t2i | D42: - | F42: 2 | G42: резервная | H42: LaoZhang | I42: Google | J42: nano-banana-2-lite | K42: прямой | L42: 1.1839 | M42: за изображение | N42: 0.025 | O42: 100.6315 | P42: 2.52 | Q42: да | R42: HIGH | S42: 9 | T42: 0.155776 | U42: 2 | V42: Сетка FX стр.33 | W42: 2026-08-11 | X42: 1 | Y42: any | Z42: 0 | AA42: 0 | AB42: плоская | AC42: 0 | AD42: gemini-3-1-flash-lite-image|default|t2i|-|-|any | AE42: gemini-3-1-flash-lite-image|default|t2i|-|-|any|нога2 | AG42: default
A43: gemini-3-pro-image | B43: 1K | C43: t2i | D43: - | F43: 1 | G43: основная | H43: LaoZhang | I43: Google | J43: nano-banana-pro | K43: прямой | L43: 1.1839 | M43: за изображение | N43: 0.09 | O43: 100.6315 | P43: 9.06 | Q43: да | R43: HIGH; ЕДИНСТВЕННАЯ НОГА — резерва не существует | S43: 37 | T43: 0.260733 | U43: 1 | V43: Сетка FX стр.34 | W43: 2026-08-11 | X43: 1 | Y43: any | Z43: 0 | AA43: 0 | AB43: плоская | AC43: 0 | AD43: gemini-3-pro-image|1K|t2i|-|-|any | AE43: gemini-3-pro-image|1K|t2i|-|-|any|нога1 | AG43: 1K
A44: gemini-3-pro-image | B44: 4K | C44: t2i | D44: - | F44: 1 | G44: основная | H44: LaoZhang | I44: Google | J44: nano-banana-pro | K44: прямой | L44: 1.1839 | M44: за изображение | N44: 0.09 | O44: 100.6315 | P44: 9.06 | Q44: да | R44: HIGH | S44: 50 | T44: 0.452943 | U44: 2 | V44: Сетка FX стр.35 | W44: 2026-08-11 | X44: 1 | Y44: any | Z44: 0 | AA44: 0 | AB44: плоская | AC44: 0 | AD44: gemini-3-pro-image|4K|t2i|-|-|any | AE44: gemini-3-pro-image|4K|t2i|-|-|any|нога1 | AG44: 1K
A45: gemini-3-pro-image | B45: 4K | C45: t2i | D45: - | F45: 2 | G45: резервная | H45: Kie | I45: Google | J45: nano-banana-pro | K45: прямой | L45: 1.1839 | M45: за изображение | N45: 0.12 | O45: 100.6315 | P45: 12.08 | Q45: да | R45: HIGH | S45: 50 | T45: 0.27059 | U45: 2 | V45: Сетка FX стр.35 | W45: 2026-08-11 | X45: 1 | Y45: any | Z45: 0 | AA45: 0 | AB45: плоская | AC45: 0 | AD45: gemini-3-pro-image|4K|t2i|-|-|any | AE45: gemini-3-pro-image|4K|t2i|-|-|any|нога2 | AG45: 1K
A46: gpt-image-2 | B46: default | C46: t2i | D46: - | E46: low | F46: 1 | G46: основная | H46: LaoZhang | I46: OpenAI | J46: gpt-image-2-vip | K46: прямой | L46: 1.1839 | M46: за изображение | N46: 0.03 | O46: 100.6315 | P46: 3.02 | Q46: да | R46: ЗАМЕРЕНО 09.08.2026 — платный вызов, счётчик откалиброван | S46: 13 | T46: 0.298644 | U46: 2 | V46: Сетка FX стр.36 | W46: 2026-08-11 | X46: 1 | Y46: any | Z46: 0 | AA46: 0 | AB46: плоская | AC46: 0 | AD46: gpt-image-2|default|t2i|-|low|any | AE46: gpt-image-2|default|t2i|-|low|any|нога1 | AG46: low
A47: gpt-image-2 | B47: default | C47: t2i | D47: - | E47: medium | F47: 1 | G47: основная | H47: LaoZhang | I47: OpenAI | J47: gpt-image-2-vip | K47: прямой | L47: 1.1839 | M47: за изображение | N47: 0.03 | O47: 100.6315 | P47: 3.02 | Q47: да | R47: ЗАМЕРЕНО 09.08.2026 — платный вызов, счётчик откалиброван | S47: 21 | T47: 0.565828 | U47: 2 | V47: Сетка FX стр.37 | W47: 2026-08-11 | X47: 1 | Y47: any | Z47: 0 | AA47: 0 | AB47: плоская | AC47: 0 | AD47: gpt-image-2|default|t2i|-|medium|any | AE47: gpt-image-2|default|t2i|-|medium|any|нога1 | AG47: low
A48: gpt-image-2 | B48: default | C48: t2i | D48: - | E48: high | F48: 1 | G48: основная | H48: LaoZhang | I48: OpenAI | J48: gpt-image-2-vip | K48: прямой | L48: 1.1839 | M48: за изображение | N48: 0.03 | O48: 100.6315 | P48: 3.02 | Q48: да | R48: ЗАМЕРЕНО 09.08.2026 — платный вызов, счётчик откалиброван | S48: 33 | T48: 0.723708 | U48: 2 | V48: Сетка FX стр.38 | W48: 2026-08-11 | X48: 1 | Y48: any | Z48: 0 | AA48: 0 | AB48: плоская | AC48: 0 | AD48: gpt-image-2|default|t2i|-|high|any | AE48: gpt-image-2|default|t2i|-|high|any|нога1 | AG48: low
A49: seedream-4-5 | B49: 1K | C49: t2i | D49: - | F49: 1 | G49: основная | H49: Kie | I49: ByteDance | J49: seedream-4-5 | K49: прямой | L49: 1.1839 | M49: за изображение | N49: 0.0325 | O49: 100.6315 | P49: 3.27 | Q49: да | R49: HIGH | S49: 14 | T49: 0.29447 | U49: 2 | V49: Сетка FX стр.39 | W49: 2026-08-11 | X49: 1 | Y49: any | Z49: 0 | AA49: 0 | AB49: плоская | AC49: 0 | AD49: seedream-4-5|1K|t2i|-|-|any | AE49: seedream-4-5|1K|t2i|-|-|any|нога1 | AG49: 1K
A50: seedream-4-5 | B50: 1K | C50: t2i | D50: - | F50: 2 | G50: резервная | H50: OpenRouter | I50: ByteDance | J50: seedream-4-5 | K50: OpenRouter | L50: 1.2492 | M50: за изображение | N50: 0.04 | O50: 106.182 | P50: 4.25 | Q50: да | R50: HIGH | S50: 14 | T50: 0.08376 | U50: 2 | V50: Сетка FX стр.39 | W50: 2026-08-11 | X50: 1 | Y50: any | Z50: 0 | AA50: 0 | AB50: плоская | AC50: 0 | AD50: seedream-4-5|1K|t2i|-|-|any | AE50: seedream-4-5|1K|t2i|-|-|any|нога2 | AG50: 1K
A51: seedream-5-0-pro | B51: 1K | C51: refs-0-1 | D51: - | F51: 1 | G51: основная | H51: Kie | I51: ByteDance | J51: seedream/5-pro-text-to-image | K51: прямой | L51: 1.1839 | M51: за изображение | N51: 0.035 | O51: 100.6315 | P51: 3.52 | Q51: да | R51: HIGH | S51: 16 | T51: 0.335173 | U51: 1 | V51: Сетка FX стр.40 | W51: 2026-08-11 | X51: 1 | Y51: any | Z51: 0 | AA51: 1 | AB51: плоская | AC51: 0 | AD51: seedream-5-0-pro|1K|refs-0-1|-|-|any | AE51: seedream-5-0-pro|1K|refs-0-1|-|-|any|нога1 | AG51: 1K
A52: seedream-5-0-pro | B52: 2K | C52: refs-0-1 | D52: - | F52: 1 | G52: основная | H52: Kie | I52: ByteDance | J52: seedream/5-pro-text-to-image | K52: прямой | L52: 1.1839 | M52: за изображение | N52: 0.07 | O52: 100.6315 | P52: 7.04 | Q52: да | R52: HIGH | S52: 31 | T52: 0.313727 | U52: 1 | V52: Сетка FX стр.41 | W52: 2026-08-11 | X52: 1 | Y52: any | Z52: 0 | AA52: 1 | AB52: плоская | AC52: 0 | AD52: seedream-5-0-pro|2K|refs-0-1|-|-|any | AE52: seedream-5-0-pro|2K|refs-0-1|-|-|any|нога1 | AG52: 1K
A53: seedream-5-0-lite | B53: 2K | C53: t2i | D53: - | F53: 1 | G53: основная | H53: Kie | I53: ByteDance | J53: seedream/5-lite-text-to-image | K53: прямой | L53: 1.1839 | M53: за изображение | N53: 0.0275 | O53: 100.6315 | P53: 2.77 | Q53: да | R53: HIGH | S53: 12 | T53: 0.303515 | U53: 1 | V53: Сетка FX стр.42 | W53: 2026-08-11 | X53: 1 | Y53: any | Z53: 0 | AA53: 0 | AB53: плоская | AC53: 0 | AD53: seedream-5-0-lite|2K|t2i|-|-|any | AE53: seedream-5-0-lite|2K|t2i|-|-|any|нога1 | AG53: 2K
A54: flux-2-pro | B54: 1K | C54: t2i | D54: - | F54: 1 | G54: основная | H54: Kie | I54: Black Forest Labs | J54: flux-2-pro / black-forest-labs/flux.2-pro | K54: прямой | L54: 1.1839 | M54: за изображение | N54: 0.025 | O54: 100.6315 | P54: 2.52 | Q54: да | R54: ЗАМЕРЕНО — kie, 5 кредитов при $0,025; ступень объявлена явно 10.08.2026 | S54: 11 | T54: 0.309271 | U54: 2 | V54: Сетка FX стр.43 | W54: 2026-08-11 | X54: 1 | Y54: any | Z54: 0 | AA54: 0 | AB54: плоская | AC54: 0 | AD54: flux-2-pro|1K|t2i|-|-|any | AE54: flux-2-pro|1K|t2i|-|-|any|нога1 | AG54: 1K | AH54: 1.049
A55: flux-2-pro | B55: 1K | C55: t2i | D55: - | F55: 2 | G55: резервная | H55: OpenRouter | I55: Black Forest Labs | J55: flux-2-pro / black-forest-labs/flux.2-pro | K55: OpenRouter | L55: 1.2492 | M55: за изображение | N55: 0.03 | O55: 106.182 | P55: 3.19 | Q55: да | R55: ЗАМЕРЕНО — kie, 5 кредитов при $0,025; ступень объявлена явно 10.08.2026 | S55: 11 | T55: 0.125407 | U55: 2 | V55: Сетка FX стр.43 | W55: 2026-08-11 | X55: 1 | Y55: any | Z55: 0 | AA55: 0 | AB55: плоская | AC55: 0 | AD55: flux-2-pro|1K|t2i|-|-|any | AE55: flux-2-pro|1K|t2i|-|-|any|нога2 | AG55: 1K | AH55: 1.049
A56: recraft-v4 | B56: default | C56: t2i | D56: - | F56: 1 | G56: основная | H56: OpenRouter | I56: Recraft | J56: recraft-v4 | K56: OpenRouter | L56: 1.2492 | M56: за изображение | N56: 0.04 | O56: 106.182 | P56: 4.25 | Q56: да | R56: HIGH | S56: 18 | T56: 0.287369 | U56: 1 | V56: Сетка FX стр.44 | W56: 2026-08-11 | X56: 1 | Y56: any | Z56: 0 | AA56: 0 | AB56: плоская | AC56: 0 | AD56: recraft-v4|default|t2i|-|-|any | AE56: recraft-v4|default|t2i|-|-|any|нога1 | AG56: default
A57: recraft-v4-vector | B57: default | C57: t2i | D57: - | F57: 1 | G57: основная | H57: OpenRouter | I57: Recraft | J57: recraft-v4-vector | K57: OpenRouter | L57: 1.2492 | M57: за изображение | N57: 0.08 | O57: 106.182 | P57: 8.49 | Q57: да | R57: HIGH | S57: 35 | T57: 0.267008 | U57: 1 | V57: Сетка FX стр.45 | W57: 2026-08-11 | X57: 1 | Y57: any | Z57: 0 | AA57: 0 | AB57: плоская | AC57: 0 | AD57: recraft-v4-vector|default|t2i|-|-|any | AE57: recraft-v4-vector|default|t2i|-|-|any|нога1 | AG57: default
A58: gemini-3-pro-image | B58: 2K | C58: t2i | D58: - | F58: 1 | G58: основная | H58: LaoZhang | I58: Google | J58: nano-banana-pro | K58: прямой | L58: 1.1839 | M58: за изображение | N58: 0.09 | O58: 100.6315 | P58: 9.06 | Q58: да | R58: HIGH; ЕДИНСТВЕННАЯ НОГА — резерва не существует | S58: 43 | T58: 0.363887 | U58: 1 | V58: Сетка FX стр.46 | W58: 2026-08-11 | X58: 1 | Y58: any | Z58: 0 | AA58: 0 | AB58: плоская | AC58: 0 | AD58: gemini-3-pro-image|2K|t2i|-|-|any | AE58: gemini-3-pro-image|2K|t2i|-|-|any|нога1 | AG58: 1K
A59: gemini-3-1-flash-image | B59: 2K | C59: t2i | D59: - | F59: 1 | G59: основная | H59: LaoZhang | I59: Google | J59: nano-banana-2 | K59: прямой | L59: 1.1839 | M59: за изображение | N59: 0.055 | O59: 100.6315 | P59: 5.53 | Q59: да | R59: HIGH | S59: 23 | T59: 0.273233 | U59: 2 | V59: Сетка FX стр.47 | W59: 2026-08-11 | X59: 1 | Y59: any | Z59: 0 | AA59: 0 | AB59: плоская | AC59: 0 | AD59: gemini-3-1-flash-image|2K|t2i|-|-|any | AE59: gemini-3-1-flash-image|2K|t2i|-|-|any|нога1 | AG59: 1K
A60: gemini-3-1-flash-image | B60: 2K | C60: t2i | D60: - | F60: 2 | G60: резервная | H60: Kie | I60: Google | J60: nano-banana-2 | K60: прямой | L60: 1.1839 | M60: за изображение | N60: 0.06 | O60: 100.6315 | P60: 6.04 | Q60: да | R60: HIGH | S60: 23 | T60: 0.207163 | U60: 2 | V60: Сетка FX стр.47 | W60: 2026-08-11 | X60: 1 | Y60: any | Z60: 0 | AA60: 0 | AB60: плоская | AC60: 0 | AD60: gemini-3-1-flash-image|2K|t2i|-|-|any | AE60: gemini-3-1-flash-image|2K|t2i|-|-|any|нога2 | AG60: 1K
A61: gemini-3-1-flash-image | B61: 4K | C61: t2i | D61: - | F61: 1 | G61: основная | H61: LaoZhang | I61: Google | J61: nano-banana-2 | K61: прямой | L61: 1.1839 | M61: за изображение | N61: 0.055 | O61: 100.6315 | P61: 5.53 | Q61: да | R61: HIGH | S61: 28 | T61: 0.403013 | U61: 2 | V61: Сетка FX стр.48 | W61: 2026-08-11 | X61: 1 | Y61: any | Z61: 0 | AA61: 0 | AB61: плоская | AC61: 0 | AD61: gemini-3-1-flash-image|4K|t2i|-|-|any | AE61: gemini-3-1-flash-image|4K|t2i|-|-|any|нога1 | AG61: 1K
A62: gemini-3-1-flash-image | B62: 4K | C62: t2i | D62: - | F62: 2 | G62: резервная | H62: Kie | I62: Google | J62: nano-banana-2 | K62: прямой | L62: 1.1839 | M62: за изображение | N62: 0.09 | O62: 100.6315 | P62: 9.06 | Q62: да | R62: HIGH | S62: 28 | T62: 0.023112 | U62: 2 | V62: Сетка FX стр.48 | W62: 2026-08-11 | X62: 1 | Y62: any | Z62: 0 | AA62: 0 | AB62: плоская | AC62: 0 | AD62: gemini-3-1-flash-image|4K|t2i|-|-|any | AE62: gemini-3-1-flash-image|4K|t2i|-|-|any|нога2 | AG62: 1K
A63: seedream-4-5 | B63: 2K | C63: t2i | D63: - | F63: 1 | G63: основная | H63: Kie | I63: ByteDance | J63: seedream-4-5 | K63: прямой | L63: 1.1839 | M63: за изображение | N63: 0.0325 | O63: 100.6315 | P63: 3.27 | Q63: да | R63: HIGH | S63: 17 | T63: 0.418975 | U63: 2 | V63: Сетка FX стр.49 | W63: 2026-08-11 | X63: 1 | Y63: any | Z63: 0 | AA63: 0 | AB63: плоская | AC63: 0 | AD63: seedream-4-5|2K|t2i|-|-|any | AE63: seedream-4-5|2K|t2i|-|-|any|нога1 | AG63: 1K
A64: seedream-4-5 | B64: 2K | C64: t2i | D64: - | F64: 2 | G64: резервная | H64: OpenRouter | I64: ByteDance | J64: seedream-4-5 | K64: OpenRouter | L64: 1.2492 | M64: за изображение | N64: 0.04 | O64: 106.182 | P64: 4.25 | Q64: да | R64: HIGH | S64: 17 | T64: 0.245449 | U64: 2 | V64: Сетка FX стр.49 | W64: 2026-08-11 | X64: 1 | Y64: any | Z64: 0 | AA64: 0 | AB64: плоская | AC64: 0 | AD64: seedream-4-5|2K|t2i|-|-|any | AE64: seedream-4-5|2K|t2i|-|-|any|нога2 | AG64: 1K
A65: seedream-4-5 | B65: 4K | C65: t2i | D65: - | F65: 1 | G65: основная | H65: Kie | I65: ByteDance | J65: seedream-4-5 | K65: прямой | L65: 1.1839 | M65: за изображение | N65: 0.0325 | O65: 100.6315 | P65: 3.27 | Q65: да | R65: HIGH | S65: 20 | T65: 0.506129 | U65: 2 | V65: Сетка FX стр.50 | W65: 2026-08-11 | X65: 1 | Y65: any | Z65: 0 | AA65: 0 | AB65: плоская | AC65: 0 | AD65: seedream-4-5|4K|t2i|-|-|any | AE65: seedream-4-5|4K|t2i|-|-|any|нога1 | AG65: 1K
A66: seedream-4-5 | B66: 4K | C66: t2i | D66: - | F66: 2 | G66: резервная | H66: OpenRouter | I66: ByteDance | J66: seedream-4-5 | K66: OpenRouter | L66: 1.2492 | M66: за изображение | N66: 0.04 | O66: 106.182 | P66: 4.25 | Q66: да | R66: HIGH | S66: 20 | T66: 0.358632 | U66: 2 | V66: Сетка FX стр.50 | W66: 2026-08-11 | X66: 1 | Y66: any | Z66: 0 | AA66: 0 | AB66: плоская | AC66: 0 | AD66: seedream-4-5|4K|t2i|-|-|any | AE66: seedream-4-5|4K|t2i|-|-|any|нога2 | AG66: 1K
A67: seedream-5-0-lite | B67: 3K | C67: t2i | D67: - | F67: 1 | G67: основная | H67: Kie | I67: ByteDance | J67: seedream/5-lite-text-to-image | K67: прямой | L67: 1.1839 | M67: за изображение | N67: 0.0275 | O67: 100.6315 | P67: 2.77 | Q67: да | R67: HIGH | S67: 14 | T67: 0.403013 | U67: 1 | V67: Сетка FX стр.51 | W67: 2026-08-11 | X67: 1 | Y67: any | Z67: 0 | AA67: 0 | AB67: плоская | AC67: 0 | AD67: seedream-5-0-lite|3K|t2i|-|-|any | AE67: seedream-5-0-lite|3K|t2i|-|-|any|нога1 | AG67: 2K
... A100: wan-2-7 | B100: 1080p | C100: i2v | D100: нет | F100: 2 | G100: резервная | H100: OpenRouter | I100: Alibaba | J100: alibaba/wan-2.7 | K100: OpenRouter | L100: 1.2492 | M100: за секунду | N100: 0.15 | O100: 106.182 | P100: 79.64 | Q100: да | R100: HIGH — платный вызов через подключённый слаг 11.08.2026, ставка подтверждена до цента | S100: 244 | T100: 0.014291 | U100: 2 | V100: Сетка FX стр.78 | W100: 2026-08-11 | X100: 5 | Y100: any | Z100: 0 | AA100: 0 | AB100: плоская | AC100: 0 | AD100: wan-2-7|1080p|i2v|нет|-|any | AE100: wan-2-7|1080p|i2v|нет|-|any|нога2 | AG100: 720p
A101: flux-2-pro | B101: 1K | C101: refs-2-8 | D101: - | F101: 1 | G101: основная | H101: Kie | I101: Black Forest Labs | J101: black-forest-labs/flux.2-pro | K101: прямой | L101: 1.1839 | M101: за изображение | N101: 0.025 | O101: 100.6315 | P101: 2.52 | Q101: да | R101: СРЕДНЯЯ — обе ноги подписаны и обе выше порога; не подтверждено, принимает ли kie 2-8 референсов | S101: 14 | T101: 0.457284 | U101: 2 | V101: Сетка FX стр.79 | W101: 2026-08-11 | X101: 1 | Y101: any | Z101: 2 | AA101: 8 | AB101: плоская | AC101: 0 | AD101: flux-2-pro|1K|refs-2-8|-|-|any | AE101: flux-2-pro|1K|refs-2-8|-|-|any|нога1 | AG101: 1K | AH101: 1.049
A102: flux-2-pro | B102: 1K | C102: refs-2-8 | D102: - | F102: 2 | G102: резервная | H102: OpenRouter | I102: Black Forest Labs | J102: black-forest-labs/flux.2-pro | K102: OpenRouter | L102: 1.2492 | M102: за изображение | N102: 0.0315 | O102: 106.182 | P102: 3.34 | Q102: да | R102: СРЕДНЯЯ — обе ноги подписаны и обе выше порога; не подтверждено, принимает ли kie 2-8 референсов | S102: 14 | T102: 0.278461 | U102: 2 | V102: Сетка FX стр.79 | W102: 2026-08-11 | X102: 1 | Y102: any | Z102: 2 | AA102: 8 | AB102: плоская | AC102: 0 | AD102: flux-2-pro|1K|refs-2-8|-|-|any | AE102: flux-2-pro|1K|refs-2-8|-|-|any|нога2 | AG102: 1K | AH102: 1.049
A103: veo-3-1 | B103: 720p | C103: i2v | D103: да | F103: 1 | G103: основная | H103: Kie | I103: Google | J103: veo-3-1 | K103: прямой | L103: 1.1839 | M103: за клип | N103: 1.25 | O103: 100.6315 | P103: 125.79 | Q103: да | R103: HIGH — бенчмарк Syntx подтверждён владельцем 03.08.2026 | S103: 597 | T103: 0.36365 | U103: 1 | V103: Сетка FX стр.80 | W103: 2026-08-11 | X103: 1 | Y103: any | Z103: 0 | AA103: 0 | AB103: плоская | AC103: 0 | AD103: veo-3-1|720p|i2v|да|-|any | AE103: veo-3-1|720p|i2v|да|-|any|нога1 | AG103: 1080p
A104: veo-3-1 | B104: 1080p | C104: i2v | D104: да | F104: 1 | G104: основная | H104: Kie | I104: Google | J104: veo-3-1 | K104: прямой | L104: 1.1839 | M104: за клип | N104: 1.275 | O104: 100.6315 | P104: 128.31 | Q104: да | R104: HIGH — бенчмарк Syntx подтверждён владельцем 03.08.2026 | S104: 597 | T104: 0.350923 | U104: 1 | V104: Сетка FX стр.81 | W104: 2026-08-11 | X104: 1 | Y104: any | Z104: 0 | AA104: 0 | AB104: плоская | AC104: 0 | AD104: veo-3-1|1080p|i2v|да|-|any | AE104: veo-3-1|1080p|i2v|да|-|any|нога1 | AG104: 1080p
A105: veo-3-1-fast | B105: 720p | C105: i2v | D105: да | F105: 1 | G105: основная | H105: Kie | I105: Google | J105: veo-3-1 | K105: прямой | L105: 1.1839 | M105: за клип | N105: 0.3 | O105: 100.6315 | P105: 30.19 | Q105: да | R105: HIGH — бенчмарк Syntx подтверждён владельцем 03.08.2026 | S105: 122 | T105: 0.252654 | U105: 1 | V105: Сетка FX стр.82 | W105: 2026-08-11 | X105: 1 | Y105: any | Z105: 0 | AA105: 0 | AB105: плоская | AC105: 0 | AD105: veo-3-1-fast|720p|i2v|да|-|any | AE105: veo-3-1-fast|720p|i2v|да|-|any|нога1 | AG105: 720p
A106: veo-3-1-fast | B106: 1080p | C106: i2v | D106: да | F106: 1 | G106: основная | H106: Kie | I106: Google | J106: veo-3-1 | K106: прямой | L106: 1.1839 | M106: за клип | N106: 0.325 | O106: 100.6315 | P106: 32.71 | Q106: да | R106: HIGH — бенчмарк Syntx подтверждён владельцем 03.08.2026 | S106: 132 | T106: 0.25171 | U106: 1 | V106: Сетка FX стр.83 | W106: 2026-08-11 | X106: 1 | Y106: any | Z106: 0 | AA106: 0 | AB106: плоская | AC106: 0 | AD106: veo-3-1-fast|1080p|i2v|да|-|any | AE106: veo-3-1-fast|1080p|i2v|да|-|any|нога1 | AG106: 720p
A107: veo-3-1-lite | B107: 720p | C107: i2v | D107: да | F107: 1 | G107: основная | H107: Kie | I107: Google | J107: veo-3-1 | K107: прямой | L107: 1.1839 | M107: за клип | N107: 0.15 | O107: 100.6315 | P107: 15.09 | Q107: да | R107: HIGH — бенчмарк Syntx подтверждён владельцем 03.08.2026 | S107: 66 | T107: 0.309271 | U107: 1 | V107: Сетка FX стр.84 | W107: 2026-08-11 | X107: 1 | Y107: any | Z107: 0 | AA107: 0 | AB107: плоская | AC107: 0 | AD107: veo-3-1-lite|720p|i2v|да|-|any | AE107: veo-3-1-lite|720p|i2v|да|-|any|нога1 | AG107: 720p
A108: veo-3-1-lite | B108: 1080p | C108: i2v | D108: да | F108: 1 | G108: основная | H108: Kie | I108: Google | J108: veo-3-1 | K108: прямой | L108: 1.1839 | M108: за клип | N108: 0.175 | O108: 100.6315 | P108: 17.61 | Q108: да | R108: HIGH — бенчмарк Syntx подтверждён владельцем 03.08.2026 | S108: 71 | T108: 0.2509 | U108: 1 | V108: Сетка FX стр.85 | W108: 2026-08-11 | X108: 1 | Y108: any | Z108: 0 | AA108: 0 | AB108: плоская | AC108: 0 | AD108: veo-3-1-lite|1080p|i2v|да|-|any | AE108: veo-3-1-lite|1080p|i2v|да|-|any|нога1 | AG108: 720p
A109: seedream-4-5 | B109: 1K | C109: i2i | D109: - | F109: 1 | G109: основная | H109: Kie | I109: ByteDance | J109: seedream-4-5 | K109: прямой | L109: 1.1839 | M109: за изображение | N109: 0.0325 | O109: 100.6315 | P109: 3.27 | Q109: да | R109: HIGH | S109: 14 | T109: 0.29447 | U109: 2 | V109: Сетка FX стр.86 | W109: 2026-08-11 | X109: 1 | Y109: any | Z109: 0 | AA109: 0 | AB109: плоская | AC109: 0 | AD109: seedream-4-5|1K|i2i|-|-|any | AE109: seedream-4-5|1K|i2i|-|-|any|нога1 | AG109: 1K
A110: seedream-4-5 | B110: 1K | C110: i2i | D110: - | F110: 2 | G110: резервная | H110: OpenRouter | I110: ByteDance | J110: seedream-4-5 | K110: OpenRouter | L110: 1.2492 | M110: за изображение | N110: 0.04 | O110: 106.182 | P110: 4.25 | Q110: да | R110: HIGH | S110: 14 | T110: 0.08376 | U110: 2 | V110: Сетка FX стр.86 | W110: 2026-08-11 | X110: 1 | Y110: any | Z110: 0 | AA110: 0 | AB110: плоская | AC110: 0 | AD110: seedream-4-5|1K|i2i|-|-|any | AE110: seedream-4-5|1K|i2i|-|-|any|нога2 | AG110: 1K
A111: seedream-4-5 | B111: 2K | C111: i2i | D111: - | F111: 1 | G111: основная | H111: Kie | I111: ByteDance | J111: seedream-4-5 | K111: прямой | L111: 1.1839 | M111: за изображение | N111: 0.0325 | O111: 100.6315 | P111: 3.27 | Q111: да | R111: HIGH | S111: 17 | T111: 0.418975 | U111: 2 | V111: Сетка FX стр.87 | W111: 2026-08-11 | X111: 1 | Y111: any | Z111: 0 | AA111: 0 | AB111: плоская | AC111: 0 | AD111: seedream-4-5|2K|i2i|-|-|any | AE111: seedream-4-5|2K|i2i|-|-|any|нога1 | AG111: 1K
A112: seedream-4-5 | B112: 2K | C112: i2i | D112: - | F112: 2 | G112: резервная | H112: OpenRouter | I112: ByteDance | J112: seedream-4-5 | K112: OpenRouter | L112: 1.2492 | M112: за изображение | N112: 0.04 | O112: 106.182 | P112: 4.25 | Q112: да | R112: HIGH | S112: 17 | T112: 0.245449 | U112: 2 | V112: Сетка FX стр.87 | W112: 2026-08-11 | X112: 1 | Y112: any | Z112: 0 | AA112: 0 | AB112: плоская | AC112: 0 | AD112: seedream-4-5|2K|i2i|-|-|any | AE112: seedream-4-5|2K|i2i|-|-|any|нога2 | AG112: 1K
A113: seedream-4-5 | B113: 4K | C113: i2i | D113: - | F113: 1 | G113: основная | H113: Kie | I113: ByteDance | J113: seedream-4-5 | K113: прямой | L113: 1.1839 | M113: за изображение | N113: 0.0325 | O113: 100.6315 | P113: 3.27 | Q113: да | R113: HIGH | S113: 20 | T113: 0.506129 | U113: 2 | V113: Сетка FX стр.88 | W113: 2026-08-11 | X113: 1 | Y113: any | Z113: 0 | AA113: 0 | AB113: плоская | AC113: 0 | AD113: seedream-4-5|4K|i2i|-|-|any | AE113: seedream-4-5|4K|i2i|-|-|any|нога1 | AG113: 1K
A114: seedream-4-5 | B114: 4K | C114: i2i | D114: - | F114: 2 | G114: резервная | H114: OpenRouter | I114: ByteDance | J114: seedream-4-5 | K114: OpenRouter | L114: 1.2492 | M114: за изображение | N114: 0.04 | O114: 106.182 | P114: 4.25 | Q114: да | R114: HIGH | S114: 20 | T114: 0.358632 | U114: 2 | V114: Сетка FX стр.88 | W114: 2026-08-11 | X114: 1 | Y114: any | Z114: 0 | AA114: 0 | AB114: плоская | AC114: 0 | AD114: seedream-4-5|4K|i2i|-|-|any | AE114: seedream-4-5|4K|i2i|-|-|any|нога2 | AG114: 1K
A115: gpt-image-2 | B115: default | C115: i2i | D115: - | E115: low | F115: 1 | G115: основная | H115: LaoZhang | I115: OpenAI | J115: gpt-image-2-vip | K115: прямой | L115: 1.1839 | M115: за изображение | N115: 0.03 | O115: 100.6315 | P115: 3.02 | Q115: да | R115: ЗАМЕРЕНО 09.08.2026 — платный вызов, счётчик откалиброван | S115: 13 | T115: 0.298644 | U115: 2 | V115: Сетка FX стр.89 | W115: 2026-08-11 | X115: 1 | Y115: any | Z115: 0 | AA115: 0 | AB115: плоская | AC115: 0 | AD115: gpt-image-2|default|i2i|-|low|any | AE115: gpt-image-2|default|i2i|-|low|any|нога1 | AG115: low
A116: gpt-image-2 | B116: default | C116: i2i | D116: - | E116: medium | F116: 1 | G116: основная | H116: LaoZhang | I116: OpenAI | J116: gpt-image-2-vip | K116: прямой | L116: 1.1839 | M116: за изображение | N116: 0.03 | O116: 100.6315 | P116: 3.02 | Q116: да | R116: ЗАМЕРЕНО 09.08.2026 — платный вызов, счётчик откалиброван | S116: 21 | T116: 0.565828 | U116: 2 | V116: Сетка FX стр.90 | W116: 2026-08-11 | X116: 1 | Y116: any | Z116: 0 | AA116: 0 | AB116: плоская | AC116: 0 | AD116: gpt-image-2|default|i2i|-|medium|any | AE116: gpt-image-2|default|i2i|-|medium|any|нога1 | AG116: low
A117: gpt-image-2 | B117: default | C117: i2i | D117: - | E117: high | F117: 1 | G117: основная | H117: LaoZhang | I117: OpenAI | J117: gpt-image-2-vip | K117: прямой | L117: 1.1839 | M117: за изображение | N117: 0.03 | O117: 100.6315 | P117: 3.02 | Q117: да | R117: ЗАМЕРЕНО 09.08.2026 — платный вызов, счётчик откалиброван | S117: 33 | T117: 0.723708 | U117: 2 | V117: Сетка FX стр.91 | W117: 2026-08-11 | X117: 1 | Y117: any | Z117: 0 | AA117: 0 | AB117: плоская | AC117: 0 | AD117: gpt-image-2|default|i2i|-|high|any | AE117: gpt-image-2|default|i2i|-|high|any|нога1 | AG117: low
A118: gemini-2-5-flash-image | B118: default | C118: i2i | D118: - | F118: 1 | G118: основная | H118: LaoZhang | I118: Google | J118: gemini-2-5-flash-image | K118: прямой | L118: 1.1839 | M118: за изображение | N118: 0.02 | O118: 100.6315 | P118: 2.01 | Q118: да | R118: HIGH; Kie reserve costed 2026-08-14 — LaoZhang remains primary; no longer single-leg. | S118: 9 | T118: 0.324621 | U118: 2 | V118: Сетка FX стр.92 | W118: 2026-08-11 | X118: 1 | Y118: any | Z118: 0 | AA118: 0 | AB118: плоская | AC118: 0 | AD118: gemini-2-5-flash-image|default|i2i|-|-|any | AE118: gemini-2-5-flash-image|default|i2i|-|-|any|нога1 | AG118: default
A119: gemini-3-1-flash-image | B119: 1K | C119: i2i | D119: - | F119: 1 | G119: основная | H119: Kie | I119: Google | J119: nano-banana-2 | K119: прямой | L119: 1.1839 | M119: за изображение | N119: 0.04 | O119: 100.6315 | P119: 4.03 | Q119: да | R119: HIGH | S119: 17 | T119: 0.284892 | U119: 2 | V119: Сетка FX стр.93 | W119: 2026-08-11 | X119: 1 | Y119: any | Z119: 0 | AA119: 0 | AB119: плоская | AC119: 0 | AD119: gemini-3-1-flash-image|1K|i2i|-|-|any | AE119: gemini-3-1-flash-image|1K|i2i|-|-|any|нога1 | AG119: 1K
A120: gemini-3-1-flash-image | B120: 1K | C120: i2i | D120: - | F120: 2 | G120: резервная | H120: LaoZhang | I120: Google | J120: nano-banana-2 | K120: прямой | L120: 1.1839 | M120: за изображение | N120: 0.055 | O120: 100.6315 | P120: 5.53 | Q120: да | R120: HIGH | S120: 17 | T120: 0.016727 | U120: 2 | V120: Сетка FX стр.93 | W120: 2026-08-11 | X120: 1 | Y120: any | Z120: 0 | AA120: 0 | AB120: плоская | AC120: 0 | AD120: gemini-3-1-flash-image|1K|i2i|-|-|any | AE120: gemini-3-1-flash-image|1K|i2i|-|-|any|нога2 | AG120: 1K
A121: gemini-3-1-flash-lite-image | B121: default | C121: i2i | D121: - | F121: 1 | G121: основная | H121: Kie | I121: Google | J121: nano-banana-2-lite | K121: прямой | L121: 1.1839 | M121: за изображение | N121: 0.02 | O121: 100.6315 | P121: 2.01 | Q121: да | R121: HIGH | S121: 9 | T121: 0.324621 | U121: 2 | V121: Сетка FX стр.94 | W121: 2026-08-11 | X121: 1 | Y121: any | Z121: 0 | AA121: 0 | AB121: плоская | AC121: 0 | AD121: gemini-3-1-flash-lite-image|default|i2i|-|-|any | AE121: gemini-3-1-flash-lite-image|default|i2i|-|-|any|нога1 | AG121: default
A122: gemini-3-1-flash-lite-image | B122: default | C122: i2i | D122: - | F122: 2 | G122: резервная | H122: LaoZhang | I122: Google | J122: nano-banana-2-lite | K122: прямой | L122: 1.1839 | M122: за изображение | N122: 0.025 | O122: 100.6315 | P122: 2.52 | Q122: да | R122: HIGH | S122: 9 | T122: 0.155776 | U122: 2 | V122: Сетка FX стр.94 | W122: 2026-08-11 | X122: 1 | Y122: any | Z122: 0 | AA122: 0 | AB122: плоская | AC122: 0 | AD122: gemini-3-1-flash-lite-image|default|i2i|-|-|any | AE122: gemini-3-1-flash-lite-image|default|i2i|-|-|any|нога2 | AG122: default
A123: gemini-3-pro-image | B123: 1K | C123: i2i | D123: - | F123: 1 | G123: основная | H123: LaoZhang | I123: Google | J123: nano-banana-pro | K123: прямой | L123: 1.1839 | M123: за изображение | N123: 0.09 | O123: 100.6315 | P123: 9.06 | Q123: да | R123: HIGH; ЕДИНСТВЕННАЯ НОГА — резерва не существует | S123: 37 | T123: 0.260733 | U123: 1 | V123: Сетка FX стр.95 | W123: 2026-08-11 | X123: 1 | Y123: any | Z123: 0 | AA123: 0 | AB123: плоская | AC123: 0 | AD123: gemini-3-pro-image|1K|i2i|-|-|any | AE123: gemini-3-pro-image|1K|i2i|-|-|any|нога1 | AG123: 1K
A124: seedance-2-0 | B124: 480p | C124: i2v | D124: нет | F124: 1 | G124: основная | H124: OpenRouter | I124: ByteDance | J124: seedance-2-0 | K124: OpenRouter | L124: 1.2492 | M124: за секунду | N124: 0.067 | O124: 106.182 | P124: 35.57 | Q124: да | R124: HIGH | S124: 145 | T124: 0.259109 | U124: 2 | V124: Сетка FX стр.96 | W124: 2026-08-11 | X124: 5 | Y124: any | Z124: 0 | AA124: 0 | AB124: плоская | AC124: 0 | AD124: seedance-2-0|480p|i2v|нет|-|any | AE124: seedance-2-0|480p|i2v|нет|-|any|нога1 | AG124: 480p
A125: seedance-2-0 | B125: 480p | C125: i2v | D125: нет | F125: 2 | G125: резервная | H125: Kie | I125: ByteDance | J125: seedance-2-0 | K125: прямой | L125: 1.1839 | M125: за секунду | N125: 0.095 | O125: 100.6315 | P125: 47.8 | Q125: да | R125: HIGH | S125: 145 | T125: 0.004398 | U125: 2 | V125: Сетка FX стр.96 | W125: 2026-08-11 | X125: 5 | Y125: any | Z125: 0 | AA125: 0 | AB125: плоская | AC125: 0 | AD125: seedance-2-0|480p|i2v|нет|-|any | AE125: seedance-2-0|480p|i2v|нет|-|any|нога2 | AG125: 480p
A126: seedance-2-0 | B126: 720p | C126: i2v | D126: нет | F126: 1 | G126: основная | H126: OpenRouter | I126: ByteDance | J126: seedance-2-0 | K126: OpenRouter | L126: 1.2492 | M126: за секунду | N126: 0.151 | O126: 106.182 | P126: 80.17 | Q126: да | R126: HIGH | S126: 323 | T126: 0.250414 | U126: 2 | V126: Сетка FX стр.97 | W126: 2026-08-11 | X126: 5 | Y126: any | Z126: 0 | AA126: 0 | AB126: плоская | AC126: 0 | AD126: seedance-2-0|720p|i2v|нет|-|any | AE126: seedance-2-0|720p|i2v|нет|-|any|нога1 | AG126: 480p
A127: seedance-2-0 | B127: 720p | C127: i2v | D127: нет | F127: 2 | G127: резервная | H127: Kie | I127: ByteDance | J127: seedance-2-0 | K127: прямой | L127: 1.1839 | M127: за секунду | N127: 0.205 | O127: 100.6315 | P127: 103.15 | Q127: да | R127: HIGH | S127: 323 | T127: 0.035546 | U127: 2 | V127: Сетка FX стр.97 | W127: 2026-08-11 | X127: 5 | Y127: any | Z127: 0 | AA127: 0 | AB127: плоская | AC127: 0 | AD127: seedance-2-0|720p|i2v|нет|-|any | AE127: seedance-2-0|720p|i2v|нет|-|any|нога2 | AG127: 480p
A128: seedance-2-0 | B128: 1080p | C128: i2v | D128: нет | F128: 1 | G128: основная | H128: OpenRouter | I128: ByteDance | J128: seedance-2-0 | K128: OpenRouter | L128: 1.2492 | M128: за секунду | N128: 0.34 | O128: 106.182 | P128: 180.51 | Q128: да | R128: HIGH | S128: 775 | T128: 0.296564 | U128: 2 | V128: Сетка FX стр.98 | W128: 2026-08-11 | X128: 5 | Y128: any | Z128: 0 | AA128: 0 | AB128: плоская | AC128: 0 | AD128: seedance-2-0|1080p|i2v|нет|-|any | AE128: seedance-2-0|1080p|i2v|нет|-|any|нога1 | AG128: 480p
A129: seedance-2-0 | B129: 1080p | C129: i2v | D129: нет | F129: 2 | G129: резервная | H129: Kie | I129: ByteDance | J129: seedance-2-0 | K129: прямой | L129: 1.1839 | M129: за секунду | N129: 0.51 | O129: 100.6315 | P129: 256.61 | Q129: да | R129: HIGH | S129: 775 | T129: 3e-06 | U129: 2 | V129: Сетка FX стр.98 | W129: 2026-08-11 | X129: 5 | Y129: any | Z129: 0 | AA129: 0 | AB129: плоская | AC129: 0 | AD129: seedance-2-0|1080p|i2v|нет|-|any | AE129: seedance-2-0|1080p|i2v|нет|-|any|нога2 | AG129: 480p
... A136: grok-imagine-video | B136: 480p | C136: i2v | D136: нет | F136: 1 | G136: основная | H136: Kie | I136: xAI | J136: grok-imagine-video | K136: прямой | L136: 1.1839 | M136: за секунду | N136: 0.012 | O136: 100.6315 | P136: 7.25 | Q136: да | R136: ГИПОТЕЗА — kie на 68-76% ниже прайс-листа xAI. Перепроверка каждые 14 дней (R-8). | S136: 37 | T136: 0.408587 | U136: 1 | V136: Сетка FX стр.103 | W136: 2026-08-11 | X136: 6 | Y136: any | Z136: 0 | AA136: 0 | AB136: плоская | AC136: 0 | AD136: grok-imagine-video|480p|i2v|нет|-|any | AE136: grok-imagine-video|480p|i2v|нет|-|any|нога1 | AG136: 480p
A137: flux-2-pro | B137: 2K | C137: t2i | D137: - | F137: 1 | G137: основная | H137: Kie | I137: Black Forest Labs | J137: flux-2-pro | K137: прямой | L137: 1.1839 | M137: за изображение | N137: 0.035 | O137: 100.6315 | P137: 3.52 | Q137: да | R137: ЗАМЕРЕНО 09.08.2026 — 7 кредитов kie, кредит откалиброван по ступени 1K | S137: 15 | T137: 0.290852 | U137: 1 | V137: Сетка FX стр.104 | W137: 2026-08-11 | X137: 1 | Y137: any | Z137: 0 | AA137: 0 | AB137: плоская | AC137: 0 | AD137: flux-2-pro|2K|t2i|-|-|any | AE137: flux-2-pro|2K|t2i|-|-|any|нога1 | AG137: 1K | AH137: 2.359
A138: flux-2-pro | B138: 2K | C138: i2i | D138: - | F138: 1 | G138: основная | H138: Kie | I138: Black Forest Labs | J138: flux-2-pro | K138: прямой | L138: 1.1839 | M138: за изображение | N138: 0.035 | O138: 100.6315 | P138: 3.52 | Q138: да | R138: HIGH — ставка kie замерена 09.08.2026; нулевая дельта ко входу | S138: 15 | T138: 0.290852 | U138: 1 | V138: Сетка FX стр.105 | W138: 2026-08-11 | X138: 1 | Y138: any | Z138: 0 | AA138: 0 | AB138: плоская | AC138: 0 | AD138: flux-2-pro|2K|i2i|-|-|any | AE138: flux-2-pro|2K|i2i|-|-|any|нога1 | AG138: 1K | AH138: 2.359
A139: flux-2-pro | B139: 2K | C139: refs-2-8 | D139: - | F139: 1 | G139: основная | H139: Kie | I139: Black Forest Labs | J139: flux-2-pro | K139: прямой | L139: 1.1839 | M139: за изображение | N139: 0.035 | O139: 100.6315 | P139: 3.52 | Q139: да | R139: HIGH — ставка kie замерена 09.08.2026; нулевая дельта ко входу | S139: 15 | T139: 0.290852 | U139: 1 | V139: Сетка FX стр.106 | W139: 2026-08-11 | X139: 1 | Y139: any | Z139: 2 | AA139: 8 | AB139: плоская | AC139: 0 | AD139: flux-2-pro|2K|refs-2-8|-|-|any | AE139: flux-2-pro|2K|refs-2-8|-|-|any|нога1 | AG139: 1K | AH139: 2.359
A140: gpt-image-2 | B140: default | C140: t2i | D140: - | E140: low | F140: 2 | G140: резервная | H140: Kie | I140: OpenAI | J140: gpt-image-2-text-to-image | K140: прямой | L140: 1.1839 | M140: за изображение | N140: 0.03 | O140: 100.6315 | P140: 3.02 | Q140: да | R140: HIGH — owner list 2026-07-25; fallback rate signed; live probe not run in this change | S140: 13 | T140: 0.298644 | U140: 2 | V140: Сетка FX стр.36; fallback cost row | W140: 2026-08-14 | X140: 1 | Y140: any | Z140: 0 | AA140: 0 | AB140: плоская | AC140: 0 | AD140: gpt-image-2|default|t2i|-|low|any | AE140: gpt-image-2|default|t2i|-|low|any|нога2 | AG140: low | AF140: COSTED RESERVE ONLY — Kie spec has resolution, not OpenAI quality; fallback is not armed for low until mapping is approved.
A141: gpt-image-2 | B141: default | C141: t2i | D141: - | E141: medium | F141: 2 | G141: резервная | H141: Kie | I141: OpenAI | J141: gpt-image-2-text-to-image | K141: прямой | L141: 1.1839 | M141: за изображение | N141: 0.05 | O141: 100.6315 | P141: 5.03 | Q141: да | R141: HIGH — owner list 2026-07-25; fallback rate signed; live probe not run in this change | S141: 21 | T141: 0.276379 | U141: 2 | V141: Сетка FX стр.37; fallback cost row | W141: 2026-08-14 | X141: 1 | Y141: any | Z141: 0 | AA141: 0 | AB141: плоская | AC141: 0 | AD141: gpt-image-2|default|t2i|-|medium|any | AE141: gpt-image-2|default|t2i|-|medium|any|нога2 | AG141: low | AF141: COSTED RESERVE ONLY — Kie spec has resolution, not OpenAI quality; fallback is not armed for medium until mapping is approved.
A142: gpt-image-2 | B142: default | C142: t2i | D142: - | E142: high | F142: 2 | G142: резервная | H142: Kie | I142: OpenAI | J142: gpt-image-2-text-to-image | K142: прямой | L142: 1.1839 | M142: за изображение | N142: 0.08 | O142: 100.6315 | P142: 8.05 | Q142: да | R142: HIGH — owner list 2026-07-25; fallback rate signed; live probe not run in this change | S142: 33 | T142: 0.263222 | U142: 2 | V142: Сетка FX стр.38; fallback cost row | W142: 2026-08-14 | X142: 1 | Y142: any | Z142: 0 | AA142: 0 | AB142: плоская | AC142: 0 | AD142: gpt-image-2|default|t2i|-|high|any | AE142: gpt-image-2|default|t2i|-|high|any|нога2 | AG142: low | AF142: COSTED RESERVE ONLY — Kie spec has resolution, not OpenAI quality; fallback is not armed for high until mapping is approved.
A143: gpt-image-2 | B143: default | C143: i2i | D143: - | F143: 2 | G143: резервная | H143: Kie | I143: OpenAI | J143: gpt-image-2-image-to-image | K143: прямой | L143: 1.1839 | M143: за изображение | N143: 0.03 | O143: 100.6315 | P143: 3.02 | Q143: да | R143: HIGH — owner list 2026-07-25; fallback rate signed; live probe not run in this change | S143: 13 | T143: 0.298644 | U143: 2 | V143: Сетка FX стр.89; fallback cost row | W143: 2026-08-14 | X143: 1 | Y143: any | Z143: 0 | AA143: 0 | AB143: плоская | AC143: 0 | AD143: gpt-image-2|default|i2i|-|low|any | AE143: gpt-image-2|default|i2i|-|low|any|нога2 | AG143: low | E143: low | AF143: COSTED RESERVE ONLY — Kie spec has resolution, not OpenAI quality; fallback is not armed for low until mapping is approved.
A144: gpt-image-2 | B144: default | C144: i2i | D144: - | F144: 2 | G144: резервная | H144: Kie | I144: OpenAI | J144: gpt-image-2-image-to-image | K144: прямой | L144: 1.1839 | M144: за изображение | N144: 0.05 | O144: 100.6315 | P144: 5.03 | Q144: да | R144: HIGH — owner list 2026-07-25; fallback rate signed; live probe not run in this change | S144: 21 | T144: 0.276379 | U144: 2 | V144: Сетка FX стр.90; fallback cost row | W144: 2026-08-14 | X144: 1 | Y144: any | Z144: 0 | AA144: 0 | AB144: плоская | AC144: 0 | AD144: gpt-image-2|default|i2i|-|medium|any | AE144: gpt-image-2|default|i2i|-|medium|any|нога2 | AG144: low | E144: medium | AF144: COSTED RESERVE ONLY — Kie spec has resolution, not OpenAI quality; fallback is not armed for medium until mapping is approved.
A145: gpt-image-2 | B145: default | C145: i2i | D145: - | F145: 2 | G145: резервная | H145: Kie | I145: OpenAI | J145: gpt-image-2-image-to-image | K145: прямой | L145: 1.1839 | M145: за изображение | N145: 0.08 | O145: 100.6315 | P145: 8.05 | Q145: да | R145: HIGH — owner list 2026-07-25; fallback rate signed; live probe not run in this change | S145: 33 | T145: 0.263222 | U145: 2 | V145: Сетка FX стр.91; fallback cost row | W145: 2026-08-14 | X145: 1 | Y145: any | Z145: 0 | AA145: 0 | AB145: плоская | AC145: 0 | AD145: gpt-image-2|default|i2i|-|high|any | AE145: gpt-image-2|default|i2i|-|high|any|нога2 | AG145: low | E145: high | AF145: COSTED RESERVE ONLY — Kie spec has resolution, not OpenAI quality; fallback is not armed for high until mapping is approved.
A146: gemini-2-5-flash-image | B146: default | C146: t2i | D146: - | F146: 2 | G146: резервная | H146: Kie | I146: Google | J146: google/nano-banana | K146: прямой | L146: 1.1839 | M146: за изображение | N146: 0.02 | O146: 100.6315 | P146: 2.01 | Q146: да | R146: HIGH — owner list 2026-07-25; fallback rate signed; live probe not run in this change | S146: 9 | T146: 0.324621 | U146: 2 | V146: Сетка FX стр.31; fallback cost row | W146: 2026-08-14 | X146: 1 | Y146: any | Z146: 0 | AA146: 0 | AB146: плоская | AC146: 0 | AD146: gemini-2-5-flash-image|default|t2i|-|-|any | AE146: gemini-2-5-flash-image|default|t2i|-|-|any|нога2 | AG146: default
A147: gemini-2-5-flash-image | B147: default | C147: i2i | D147: - | F147: 2 | G147: резервная | H147: Kie | I147: Google | J147: google/nano-banana-edit | K147: прямой | L147: 1.1839 | M147: за изображение | N147: 0.02 | O147: 100.6315 | P147: 2.01 | Q147: да | R147: HIGH — owner list 2026-07-25; fallback rate signed; live probe not run in this change | S147: 9 | T147: 0.324621 | U147: 2 | V147: Сетка FX стр.92; fallback cost row | W147: 2026-08-14 | X147: 1 | Y147: any | Z147: 0 | AA147: 0 | AB147: плоская | AC147: 0 | AD147: gemini-2-5-flash-image|default|i2i|-|-|any | AE147: gemini-2-5-flash-image|default|i2i|-|-|any|нога2 | AG147: default

Sheet СООТНОШЕНИЕ СТОРОН
A1: СООТНОШЕНИЕ СТОРОН — ценовое измерение, введено 03.08.2026
A2: Поставщик тарифицирует по РЕАЛЬНЫМ ПИКСЕЛЯМ, а не по названию рунга: токены = (высота × ширина × секунды × 24) / 1024 по $0,000007. Формула воспроизводит нашу ставку Seedance 1080p до четвёртого знака ($0,3402 против $0,34), поэтому принята как верная. Следствие: «1080p» в 21:9 стоит нам в 1,31 раза дороже, чем в 16:9, а в 9:16 — в 3,16 раза дешевле. Цена при этом одна.
A4: Соотношение | B4: Кадр при рунге 1080p | C4: Пикселей | D4: Множитель к 16:9 | E4: Себест 5 с, ₽ | F4: Маржа при 727 кред | G4: НАДБАВКА К ЦЕНЕ | H4: Цена 1080p
A5: 21:9 | B5: 2520x1080 | C5: 2721600 | D5: 1.3125 | E5: 237.06 | F5: 0.015 | G5: 1.35 | H5: 982
A6: 16:9 | B6: 1920x1080 | C6: 2073600 | D6: 1 | E6: 180.62 | F6: 0.25 | G6: 1 | H6: 727
A7: 4:3 | B7: 1440x1080 | C7: 1555200 | D7: 0.75 | E7: 135.46 | F7: 0.437 | G7: 1 | H7: 727
A8: 3:4 | B8: 1080x1440 | C8: 1555200 | D8: 0.75 | E8: 135.46 | F8: 0.437 | G8: 1 | H8: 727
A9: 1:1 | B9: 1080x1080 | C9: 1166400 | D9: 0.5625 | E9: 101.6 | F9: 0.578 | G9: 1 | H9: 727
A10: 9:16 | B10: 608x1080 | C10: 656640 | D10: 0.3167 | E10: 57.19 | F10: 0.762 | G10: 1 | H10: 727
A12: РЕШЕНИЕ: надбавка только вверх
A13: Соотношения ШИРЕ 16:9 получают надбавку 1,35 к цене рунга. Всё остальное продаётся по базовой цене.
A14: Почему не зеркально. Симметричный множитель по себестоимости математически честнее, но означает снижение цены вертикального формата в три раза — а 9:16 это доминирующий формат нашей аудитории и там мы сегодня зарабатываем 76%. Отдавать это по своей воле не за что: мы не обязаны продавать по себестоимости, мы обязаны не продавать ниже себестоимости.
A15: Надбавка 1,35 при множителе себестоимости 1,3125 оставляет 21:9 маржу 27% — на уровне базовой строки.
A16: Что это меняет в объяснении клиенту: широкий кадр дороже. Это понятно и проверяемо, в отличие от «одна цена, разная себестоимость».
A18: ЧТО ЭТО ЗНАЧИТ ДЛЯ ФИНМОДЕЛИ — не применено, вынесено в чувствительность
A19: Если 60% потребления вертикальное, средняя себестоимость клипа 106,6 ₽ вместо 180,6 — то есть себестоимость кредита НИЖЕ заложенной на 41%.
A20: В базовый сценарий это не заводится: доля вертикального формата не измерена. Учитывать выгоду по неизмеренному допущению — та же ошибка, что и не учитывать риск.
A21: Как только появится реальная статистика по соотношениям, это первый кандидат на пересчёт себестоимости кредита — и он идёт в нашу пользу.

Sheet ЛЕСТНИЦА НОГ
A1: ЛЕСТНИЦА НОГ — предпросмотр по новому правилу. НЕ ПРИМЕНЕНО.
A2: НОВОЕ ПРАВИЛО (принято 03.08.2026): цену задаёт САМАЯ ДЕШЁВАЯ нога рунга при целевой марже. Каждая следующая нога входит в лестницу, если держит 0%, и выпадает, если нет. Дорогой поставщик больше не тянет цену вверх для всех — он просто уходит из лестницы. ОГРАНИЧЕНИЕ: если после исключения остаётся ОДНА нога, правило не применяется — держим прежнюю цену до появления второго источника. НИЖЕ НЕ ПРИМЕНЕНО: Pixazo и SeeGen не проверены платными вызовами и платёжный канал не подтверждён.
A4: ПРАВИЛО R-11 — что делать, когда переключение уходит в минус | B4: Лидер | C4: Себест лидера, ₽ | D4: ЦЕНА по правилу | E4: Цена сейчас | F4: Изм. | G4: Лестница (нога · маржа) | H4: Выпадает | I4: Статус
A5: Резервные ноги посчитаны по безубыточности при курсе 85. Это значит, что при любом росте курса они уходят в минус — по построению, а не по недосмотру. | B5: Pixazo | C5: 35.2 | D5: 142 | E5: 145 | F5: -2% | G5: Pixazo 25,1% · OpenRouter 24,3% · SeeGen 9,0% | H5: kie −1,7% | I5: ждём платную проверку и платёжный канал
A6: РЕШЕНИЕ: переключение НЕ запрещается. Отказ переключиться превращает аварию поставщика в нашу аварию, а это дороже. Убыток поглощается в пределах лимита: 5 000 ₽ в сутки, 30 000 ₽ в скользящий месяц накопленного отрицательного результата по всему каталогу. Лимит исчерпан — строки уходят офлайн до возврата основного поставщика. | B6: Pixazo | C6: 76.1 | D6: 307 | E6: 323 | F6: -5% | G6: Pixazo 25,2% · OpenRouter 21,1% · SeeGen 20,8% | H6: kie −1,5% | I6: ждём платную проверку и платёжный канал
A7: ИСКЛЮЧЕНИЕ: Seedance 4K не переключается никогда. Убыток 84,8 ₽ на генерацию при курсе 95 — в десять раз больше следующей худшей строки. При недоступности основного поставщика 4K не отдаётся вовсе, клиенту предлагается 1080p. | B7: OpenRouter | C7: 180.5 | D7: 727 | E7: 776 | F7: -6% | G7: OpenRouter 25,0% · Pixazo 21,8% · SeeGen 16,4% | H7: kie −6,6% | I7: ждём платную проверку и платёжный канал
A8: ОБОСНОВАНИЕ ЛИМИТА: один ушедший клиент стоит 22 575 ₽ вклада, что равно 49 часам простоя одной модели. Страховка окупается, если предотвращает одного ушедшего на каждые двое суток простоя. | B8: SeeGen | C8: 402.5 | D8: 1621 | E8: 2183 | F8: -26% | G8: SeeGen 25,0% · kie 2,5% | H8: OpenRouter −34,6% | I8: ждём платную проверку и платёжный канал
A9: Лимит считается счётчиком в коде: каждое переключение прибавляет (себестоимость − выручка) к сумме; сумма перевалила порог — маршрут перестаёт отвечать.
A10: ПРИМЕНЕНО СЕГОДНЯ (kie проверен платно): Kling переведён на kie — 720p со звуком 270→203, без звука 180→136, добавлены 1080p 284 и 4K 446. Veo 4K заведён: Quality 750, Fast 365, Lite 304.
A12: ПРАВИЛО ЦЕНЫ — ПОДТВЕРЖДЕНО 11.08.2026
A13: РЕШЕНИЕ ВЛАДЕЛЬЦА 11.08.2026 — НАДБАВКА ЗА РЕЗЕРВ ОСТАЁТСЯ. Правило цены остаётся из четырёх членов: MAX(потолок +28% vs Syntx; цена по марже 25%; БЕЗУБЫТОК РЕЗЕРВА; ступень качества +15%). Вопрос ставился и закрыт: четвёртый член перебивает цену на 8 строках из 91, и на этих строках клиент оплачивает вторую ногу. Владелец рассмотрел цену решения и принял её. ЧЕГО ЭТО СТОИТ, ЧТОБЫ НИКТО НЕ ПЕРЕСЧИТЫВАЛ ЗАНОВО: на Seedance 1080p 775 вместо 727 — это −7,0% против Syntx вместо −0,9%, то есть страховка стоит 6 п.п. конкурентоспособности. На Gemini Omni 273 вместо 257 — −34,2% вместо −30,1%. На остальных строках надбавка стоит 1-2 кредита и на сравнение с конкурентом не влияет. ЧТО ЭТО ПОКУПАЕТ: переключение на резерв бесплатно для нас в момент отказа — резерв на этих строках выходит ровно в ноль, а не в минус, поэтому R-1 выполняется без исключений и бюджет отказов по R-11 не расходуется. ИЗВЕСТНОЕ ПОБОЧНОЕ СЛЕДСТВИЕ: при этом правиле добавление ЛЮБОЙ новой ноги может цену только поднять, никогда не опустить. Третья нога, под которую 11.08 открыт формат, работает против клиента до тех пор, пока это правило действует. Пересматривать при подключении первого третьего вендора.

Sheet ЖУРНАЛ ЦЕН
A1: ЖУРНАЛ ИЗМЕНЕНИЙ ЦЕН — каждое изменение с датой, причиной и полномочием
A2: Правило с 03.08.2026: ни одна цена не меняется без строки в этом журнале, включая снижения. Изменение, пришедшее как побочный эффект правки данных, — такое же изменение цены, как и намеренное. Каждая строка подписывается построчно принимающей стороной перед применением.
A4: Дата | B4: Позиция | C4: Было | D4: Стало | E4: Δ | F4: Причина | G4: Полномочие | H4: Тип | I4: Подпись
A5: 2026-08-03 | B5: Seedance 2.0 480p | C5: 564 | D5: 145 | E5: -74% | F5: Бенчмарк Syntx для 480p был скопирован с 1080p. Проверенное значение 20,375 токена вместо 112,25 опускает потолок. | G5: Ответ #2, Ask 3 | H5: исправление ошибки
A6: 2026-08-03 | B6: Seedance 2.0 720p | C6: 564 | D6: 323 | E6: -43% | F6: То же: проверенный бенчмарк 45,375 вместо 112,25. | G6: Ответ #2, Ask 3 | H6: исправление ошибки
A7: 2026-08-03 | B7: Seedance Fast 480p | C7: 183 | D7: 118 | E7: -36% | F7: То же: проверенный бенчмарк 16,375 вместо 36,25. | G7: Ответ #2, Ask 3 | H7: исправление ошибки
A8: 2026-08-03 | B8: Wan 2.7 720p | C8: 251 | D8: 163 | E8: -35% | F8: То же: проверенный бенчмарк 30 вместо 50. | G8: Ответ #2, Ask 3 | H8: исправление ошибки
A9: 2026-08-03 | B9: Wan 2.7 1080p | C9: 251 | D9: 244 | E9: -3% | F9: То же: проверенный бенчмарк 40 вместо 50. | G9: Ответ #2, Ask 3 | H9: исправление ошибки
A10: 2026-08-03 | B10: Grok 480p | C10: 41 | D10: 26 | E10: -37% | F10: То же: проверенный бенчмарк 5 вместо 8. | G10: Ответ #2, Ask 3 | H10: исправление ошибки
A11: 2026-08-03 | B11: HappyHorse 1.1 720p | C11: 226 | D11: 212 | E11: -6% | F11: То же: проверенный бенчмарк 25 вместо 45. | G11: Ответ #2, Ask 3 | H11: исправление ошибки
A12: 2026-08-03 | B12: seedream-5.0 Pro 2K | C12: 29 | D12: 31 | E12: +7% | F12: ПОВЫШЕНИЕ. Проверенный бенчмарк 6 токенов вместо 3. При 29 кредитах мы щедрее Syntx на 32,8%, выше собственного потолка 28%. ОТМЕНЯЕТ решение R-5, где стояло 29 — тот текст написан до исправления бенчмарка. | G12: Ответ #4 + поправка R-5 | H12: ПОВЫШЕНИЕ ЦЕНЫ
A13: 2026-08-03 | B13: Gemini Omni | C13: 273 | D13: 257 | E13: -6% | F13: AtlasCloud подорожал 0,112 -> 0,125-0,135, резерв ушёл в минус 11-20%. Резерв снят, ограничение безубыточности перестало связывать. | G13: Ответ #4, §3.2 | H13: следствие снятия резерва
A14: 2026-08-03 | B14: flux-2-pro | C14: 13 | D14: 11 | E14: -15% | F14: Основной поставщик переключён с OpenRouter $0,03 на kie $0,025. | G14: Ответ #2, Ask 1 | H14: смена поставщика
A15: 2026-08-03 | B15: nano-banana-2 1K | C15: 23 | D15: 17 | E15: -26% | F15: Резерв оказался дешевле основного: kie $0,04 по опубликованной лестнице против LaoZhang $0,055. Ноги поменяны местами. | G15: Ответ #5, п.2 | H15: смена поставщика
A16: 2026-08-03 | B16: nano-banana-2 2K | C16: 27 | D16: 23 | E16: -15% | F16: Каскад по лестнице качества +15% от изменившейся цены 1K. | G16: Ответ #5, п.2 | H16: каскад
... A19: 2026-08-03 | B19: HappyHorse 1.0 720p | C19: 284 | D19: 212 | E19: -25% | F19: Переведён на OpenRouter $0,0988 вместо kie $0,14 — на 26% дешевле. Затем строка снята целиком. | G19: Ответ #3, Q8 | H19: снято с продажи
A20: 2026-08-03 | B20: HappyHorse 1.0 1080p | C20: 365 | D20: снято | E20: — | F20: Снято с продажи: версия 1.0 дороже 1.1 при том же результате. | G20: Ответ #3, Q8 | H20: снято с продажи
A21: 2026-08-03 | B21: Grok 480p | C21: 26 | D21: 37 | E21: +42% | F21: kie поднял ставку с $0,008 до $0,012 за секунду, +50%. Плюс применён порог 40% по новому правилу R-10: посредник на 76% ниже прайс-листа xAI и второй ноги нет. При пороге 25% цена была бы 30. | G21: kie pricing card 03.08.2026 + правило R-10 | H21: ПОВЫШЕНИЕ ЦЕНЫ
A22: 2026-08-03 | B22: Grok 720p | C22: 41 | D22: 69 | E22: +68% | F22: kie поднял ставку с $0,015 до $0,0225 за секунду, +50%. При старой цене 41 маржа минус 0,1% — продавали бы ниже себестоимости. Порог 40% по R-10. При пороге 25% цена была бы 55. | G22: kie pricing card 03.08.2026 + правило R-10 | H22: ПОВЫШЕНИЕ ЦЕНЫ
B23: Seedance 2.0 4K | D23: 2183
B24: Seedance 2.0 r2v 480p/720p/1080p/4K | D24: 232/507/1257/2595
B25: Seedance Fast r2v 480p/720p | D25: 183/406
B26: HappyHorse 1.1 i2v 720p/1080p | D26: 229/294
B27: HappyHorse 1.1 r2v 720p/1080p | D27: 229/294
B28: HappyHorse 1.0 video-edit 720p/1080p | D28: 284/487
B29: gpt-image-2 2K/4K | D29: 21/33
B30: Seedream 5.0 Pro референсы 1K/2K | D30: 24/38
B31: nano-banana-pro 2K, seedream-4.5 2K/4K, seedream-5.0 Lite 3K/4K | D31: лестницы качества
A32: 2026-08-03 | B32: Veo Quality 720p | C32: 895 | D32: 597 | E32: -33% | F32: Единая цена за клип любой длительности. Вендор берёт фикс за клип, значит удвоение ставки под худший случай 4 секунды больше не нужно — оговорка про порог 15% снята. Цена встала на потолок щедрости +28% относительно Syntx (бенчмарк подтверждён владельцем 03.08). Выбор длительности клиенту сохраняется — у Syntx его нет. | G32: решение владельца 03.08.2026 | H32: СНИЖЕНИЕ + смена базы
A33: 2026-08-03 | B33: Veo Quality 1080p | C33: 913 | D33: 597 | E33: -35% | F33: Единая цена за клип любой длительности. Вендор берёт фикс за клип, значит удвоение ставки под худший случай 4 секунды больше не нужно — оговорка про порог 15% снята. Цена встала на потолок щедрости +28% относительно Syntx (бенчмарк подтверждён владельцем 03.08). Выбор длительности клиенту сохраняется — у Syntx его нет. | G33: решение владельца 03.08.2026 | H33: СНИЖЕНИЕ + смена базы
A34: 2026-08-03 | B34: Veo Fast 720p | C34: 215 | D34: 122 | E34: -43% | F34: Единая цена за клип любой длительности. Вендор берёт фикс за клип, значит удвоение ставки под худший случай 4 секунды больше не нужно — оговорка про порог 15% снята. Цена встала на потолок щедрости +28% относительно Syntx (бенчмарк подтверждён владельцем 03.08). Выбор длительности клиенту сохраняется — у Syntx его нет. | G34: решение владельца 03.08.2026 | H34: СНИЖЕНИЕ + смена базы
A35: 2026-08-03 | B35: Veo Fast 1080p | C35: 233 | D35: 132 | E35: -43% | F35: Единая цена за клип любой длительности. Вендор берёт фикс за клип, значит удвоение ставки под худший случай 4 секунды больше не нужно — оговорка про порог 15% снята. Цена встала на потолок щедрости +28% относительно Syntx (бенчмарк подтверждён владельцем 03.08). Выбор длительности клиенту сохраняется — у Syntx его нет. | G35: решение владельца 03.08.2026 | H35: СНИЖЕНИЕ + смена базы
A36: 2026-08-03 | B36: Veo Lite 720p | C36: 108 | D36: 66 | E36: -39% | F36: Единая цена за клип любой длительности. Вендор берёт фикс за клип, значит удвоение ставки под худший случай 4 секунды больше не нужно — оговорка про порог 15% снята. Цена встала на потолок щедрости +28% относительно Syntx (бенчмарк подтверждён владельцем 03.08). Выбор длительности клиенту сохраняется — у Syntx его нет. | G36: решение владельца 03.08.2026 | H36: СНИЖЕНИЕ + смена базы
A37: 2026-08-03 | B37: Veo Lite 1080p | C37: 126 | D37: 71 | E37: -44% | F37: Единая цена за клип любой длительности. Вендор берёт фикс за клип, значит удвоение ставки под худший случай 4 секунды больше не нужно — оговорка про порог 15% снята. Цена встала на потолок щедрости +28% относительно Syntx (бенчмарк подтверждён владельцем 03.08). Выбор длительности клиенту сохраняется — у Syntx его нет. | G37: решение владельца 03.08.2026 | H37: СНИЖЕНИЕ + смена базы
A38: 2026-08-03 | B38: Kling v3 4K (звук) | C38: 446 | D38: 679 | E38: +52% | F38: ИСПРАВЛЕНИЕ ОШИБКИ ФИНАНСОВ. Ставка была выведена по образцу младших рунгов ($0,22) вместо чтения карточки kie ($0,335). При 446 кредитах строка давала −14,1%, то есть продавалась ниже себестоимости. | G38: карточка kie + аудит разработки | H38: ИСПРАВЛЕНИЕ
A39: 2026-08-03 | B39: Kling v3 720p (без звука) | C39: 136 | D39: 142 | E39: +4% | F39: Ставка уточнена по карточке: $0,07 вместо принятых $0,067. | G39: карточка kie + аудит разработки | H39: ИСПРАВЛЕНИЕ
A40: 2026-08-03 | B40: Kling v3 1080p (звук) | C40: 284 | D40: 274 | E40: -4% | F40: Ставка уточнена по карточке: $0,135 вместо принятых $0,14. | G40: карточка kie + аудит разработки | H40: ИСПРАВЛЕНИЕ
A41: 2026-08-03 | B41: Seedance 2.0 r2v 480p | C41: 232 | D41: 145 | E41: -38% | F41: ИСПРАВЛЕНИЕ ОШИБКИ ФИНАНСОВ. Наценка за референс была построена на правиле kie «вход + выход». Карточка OpenRouter от 03.08.2026: модель поддерживает multimodal reference-to-video, ставка одна на обе колонки (Video+Audio и Video Only, обе $0,1512/сек), формула токенов (высота × ширина × длительность × 24)/1024 входного слагаемого не содержит. Референс на OpenRouter не тарифицируется — значит наценка ничем не обеспечена. Цена приравнена к t2v. | G41: карточка OpenRouter + аудит разработки | H41: ИСПРАВЛЕНИЕ — снятие необеспеченной наценки
A42: 2026-08-03 | B42: Seedance 2.0 r2v 720p | C42: 507 | D42: 323 | E42: -36% | F42: ИСПРАВЛЕНИЕ ОШИБКИ ФИНАНСОВ. Наценка за референс была построена на правиле kie «вход + выход». Карточка OpenRouter от 03.08.2026: модель поддерживает multimodal reference-to-video, ставка одна на обе колонки (Video+Audio и Video Only, обе $0,1512/сек), формула токенов (высота × ширина × длительность × 24)/1024 входного слагаемого не содержит. Референс на OpenRouter не тарифицируется — значит наценка ничем не обеспечена. Цена приравнена к t2v. | G42: карточка OpenRouter + аудит разработки | H42: ИСПРАВЛЕНИЕ — снятие необеспеченной наценки
A43: 2026-08-03 | B43: Seedance 2.0 r2v 1080p | C43: 1257 | D43: 776 | E43: -38% | F43: ИСПРАВЛЕНИЕ ОШИБКИ ФИНАНСОВ. Наценка за референс была построена на правиле kie «вход + выход». Карточка OpenRouter от 03.08.2026: модель поддерживает multimodal reference-to-video, ставка одна на обе колонки (Video+Audio и Video Only, обе $0,1512/сек), формула токенов (высота × ширина × длительность × 24)/1024 входного слагаемого не содержит. Референс на OpenRouter не тарифицируется — значит наценка ничем не обеспечена. Цена приравнена к t2v. | G43: карточка OpenRouter + аудит разработки | H43: ИСПРАВЛЕНИЕ — снятие необеспеченной наценки
... A47: 2026-08-04 | B47: Gemini Omni | C47: 257 | D47: 273 | E47: +6% | F47: Резервная нога AtlasCloud восстановлена. Решение 03.08 снять её принималось при ставке $0,125-0,135, требовавшей 329 кредитов (+21% клиенту). Разработка подтвердила $0,112 — требуется 273, то есть +6%. Модель несёт 8% потребления, альтернативы дешевле $0,084/с на рынке нет: за вторую ногу на такой строке 6% платить стоит. | G47: решение финансов 04.08.2026, ставка подтверждена разработкой | H47: ПОВЫШЕНИЕ — восстановление второй ноги

Sheet Тарифы
B2: ТАРИФЫ — ЦЕНА СЧИТАЕТСЯ ИЗ ЦЕЛЕЙ ПРИБЫЛИ
B3: Тариф задаётся КРЕДИТАМИ (строка 18). Цена считается из целей прибыли («Технический» сверху) и округляется до …99. Сколько генераций каждой модели входит — матрица ниже.
B5: СЕТКА
B6: Тариф | C6: Start | D6: Pro | E6: Studio | F6: Elite | G6: Ultra
B7: Цена, ₽/мес — утвержденная сетка запуска | C7: 599 | D7: 1649 | E7: 3799 | F7: 5799 | G7: 11699
B8: CM2 при 100% расходовании лимита | C8: =1-C9-C18*Технический!$C$47/C7 -> 0.32307421 | D8: =1-D9-D18*Технический!$C$47/D7 -> 0.11316117 | E8: =1-E9-E18*Технический!$C$47/E7 -> 0.10040149 | F8: =1-F9-F18*Технический!$C$47/F7 -> 0.091308413 | G8: =1-G9-G18*Технический!$C$47/G7 -> 0.08056648
B9: Комиссии платежей + УСН, % от цены (само) | C9: =Технический!C61+Технический!C65 -> 0.09425 | D9: =Технический!C61+Технический!C65 -> 0.09425 | E9: =Технический!C61+Технический!C65 -> 0.09425 | F9: =Технический!C61+Технический!C65 -> 0.09425 | G9: =Технический!C61+Технический!C65 -> 0.09425
B10: Лимит тарифа, ₽ себестоимости (сам = кредиты × себест. кредита) | C10: =C18*Технический!$C$43 -> 257.325 | D10: =D18*Технический!$C$43 -> 963.6 | E10: =E18*Технический!$C$43 -> 2255.7 | F10: =F18*Технический!$C$43 -> 3482.1 | G10: =G18*Технический!$C$43 -> 7117.5
B11: (инфо) видео-генераций veo-3-1-fast (8с) в тарифе | C11: =C18/$G$67 -> 5.5164319 | D11: =D18/$G$67 -> 20.657277 | E11: =E18/$G$67 -> 48.356808 | F11: =F18/$G$67 -> 74.647887 | G11: =G18/$G$67 -> 152.58216
B15: (инфо) картинок gemini-3-pro-image в тарифе | C15: =C18/$G$60 -> 37.903226 | D15: =D18/$G$60 -> 141.93548 | E15: =E18/$G$60 -> 332.25806 | F15: =F18/$G$60 -> 512.90323 | G15: =G18/$G$60 -> 1048.3871
B17: Цена 1 видео-генерации (veo-fast) для клиента, ₽ | C17: =C7/C11 -> 108.58468 | D17: =D7/D11 -> 79.826591 | E17: =E7/E11 -> 78.561845 | F17: =F7/F11 -> 77.684717 | G17: =G7/G11 -> 76.673446
B18: КРЕДИТОВ В ТАРИФЕ — МЕНЯЙ (задаёт размер тарифа) | C18: 1175 | D18: 4400 | E18: 10300 | F18: 15900 | G18: 32500
B19: ₽ за 1 кредит подписки (сам) | C19: =C7/C18 -> 0.50978723 | D19: =D7/D18 -> 0.37477273 | E19: =E7/E18 -> 0.36883495 | F19: =F7/F18 -> 0.36471698 | G19: =G7/G18 -> 0.35996923
B20: CM2 при 100% расходовании, средняя по портфелю: | C20: =Технический!C82*C8+Технический!C83*D8+Технический!C84*E8+Технический!C85*F8+Технический!C95*G8 -> 0.19237896
B21: Поправка маржи тарифа, ±п.п. — МЕНЯЙ (дорогие тарифы дают больше генераций за рубль) | C21: 0.039 | D21: -0.084 | E21: -0.011 | F21: -0.029 | G21: -0.035 | H21: (развязано: поправки независимы, не зеро-сум) | I21: ← среднее (вычитается автоматически)
B23: ДОКУПКА КРЕДИТОВ — БЕЗ СРОКА СГОРАНИЯ, ПОЭТОМУ ДОРОЖЕ ULTRA
B24: Пакет | C24: Кредитов | D24: ₽/кредит | E24: Цена | F24: ≈ видео-ген (veo-fast) | G24: vs подписка Ultra
B25: S | C25: 500 | D25: =E25/C25 -> 0.598 | E25: 299 | F25: =C25/$G$67 -> 2.3474178 | G25: =D25/$G$19-1 -> 0.6612531
B26: M | C26: 1500 | D26: =E26/C26 -> 0.53266667 | E26: 799 | F26: =C26/$G$67 -> 7.0422535 | G26: =D26/$G$19-1 -> 0.4797561
B27: L | C27: 4000 | D27: =E27/C27 -> 0.47475 | E27: 1899 | F27: =C27/$G$67 -> 18.779343 | G27: =D27/$G$19-1 -> 0.31886272
B28: XL | C28: 10000 | D28: =E28/C28 -> 0.4499 | E28: 4499 | F28: =C28/$G$67 -> 46.948357 | G28: =D28/$G$19-1 -> 0.24982905
B29: XXL | C29: 25000 | D29: =E29/C29 -> 0.43996 | E29: 10999 | F29: =C29/$G$67 -> 117.37089 | G29: =D29/$G$19-1 -> 0.22221557
B31: Сравнение с конкурентами по этим же моделям — в матрице ниже (колонки Syntx).
B49: УСТАРЕВШИЙ СЛОЙ — НЕ ИСПОЛЬЗОВАТЬ ДЛЯ ЦЕН. Блок ниже посчитан при курсе 76,5, цене кредита 0,36 ₽ и БЕЗ правила отказоустойчивости. Это состояние «ДО» перепрайсинга 25.07.2026 — оно перенесено в лист «Сетка FX» колонкой «Сейчас кр/клип» и там же пересчитано. Закон — «Сетка FX», колонка «КРЕДИТОВ/КЛИП». Актуальны на этом листе только строки 6–21: цены тарифов и кредиты в тарифе.
M50: VERTOV — генераций/мес | S50: SYNTX — генераций/мес (заполни колонку R) | X50: HIGGSFIELD — генераций/мес
B51: Кредитов в тарифе → | M51: =Тарифы!C18 -> 1175 | N51: =Тарифы!D18 -> 4400 | O51: =Тарифы!E18 -> 10300 | P51: =Тарифы!F18 -> 15900 | Q51: =Тарифы!G18 -> 32500 | S51: =Технический!C108 -> 260 | T51: =Технический!D108 -> 685.5 | U51: =Технический!E108 -> 1700 | V51: =Технический!F108 -> 2600 | W51: =Технический!G108 -> 3000 | Y51: =Технический!I112 -> 270 | Z51: =Технический!I110 -> 1200 | AA51: =Технический!I111 -> 3000
B52: Модель | C52: Тип | D52: Единица | E52: Кредитов за ед. | F52: Ед. в 1 ген | G52: Кредитов за 1 ген | H52: Провайдер $/ед. | I52: Канал 1=OR 2=direct | J52: Себест. 1 ген, ₽ (всё вкл.) | K52: Себест. 1 кредита, ₽ | L52: Валовая маржа кредита (Ultra) | M52: Start | N52: Pro | O52: Studio | P52: Elite | Q52: Ultra | R52: Syntx ток/ген | S52: Basic | T52: Pro | U52: VIP | V52: Elite | W52: Ultra El. | X52: Higgs кр за 1 нашу ген | Y52: Starter | Z52: Plus | AA52: Ultra | AB52: Перевес /₽ vs Syntx (ср. по тарифам) | AC52: Fallback ₽/ген | AD52: Fallback себест/кредит | AE52: Floor-check маржа при failover
B53: — КАРТИНКИ (за картинку) —
B54: nano-banana | C54: карт | D54: за картинку | E54: =G54/F54 -> 8 | F54: 1 | G54: 8 | H54: 0.02 | I54: 2 | J54: =H54*F54*IF(I54=1,Технический!$C$26,Технический!$C$27) -> 2.0127794 | K54: =J54/G54 -> 0.25159742 | L54: =1-K54/Тарифы!$G$19 -> 0.30105853 | M54: =Тарифы!C$18/$G54 -> 146.875 | N54: =Тарифы!D$18/$G54 -> 550 | O54: =Тарифы!E$18/$G54 -> 1287.5 | P54: =Тарифы!F$18/$G54 -> 1987.5 | Q54: =Тарифы!G$18/$G54 -> 4062.5 | R54: 1.5 | S54: =IF(ISNUMBER($R54),Технический!C$108/$R54,"") -> 173.33333 | T54: =IF(ISNUMBER($R54),Технический!D$108/$R54,"") -> 457 | U54: =IF(ISNUMBER($R54),Технический!E$108/$R54,"") -> 1133.3333 | V54: =IF(ISNUMBER($R54),Технический!F$108/$R54,"") -> 1733.3333 | W54: =IF(ISNUMBER($R54),Технический!G$108/$R54,"") -> 2000 | X54: 1 | Y54: =IF(ISNUMBER($X54),Технический!$I$112/$X54,"") -> 270 | Z54: =IF(ISNUMBER($X54),Технический!$I$110/$X54,"") -> 1200 | AA54: =IF(ISNUMBER($X54),Технический!$I$111/$X54,"") -> 3000 | AB54: =IFERROR(AVERAGE((M54/$C$7)/((Технический!$C$108/$R54)/Технический!$C$107),(N54/$D$7)/((Технический!$D$108/$R54)/Технический!$D$107),(O54/$E$7)/((Технический!$E$108/$R54)/Технический!$E$107),(P54/$F$7)/((Технический!$F$108/$R54)/Технический!$F$107),(Q54/$G$7)/((Технический!$G$108/$R54)/Технический!$G$107))-1,"") -> 0.39035097 | AC54: 1.8 | AD54: =AC54/G54 -> 0.225 | AE54: =(Тарифы!$G$19-AD54)/Тарифы!$G$19 -> 0.37494658
B55: recraft-v4 | C55: карт | D55: за картинку | E55: =G55/F55 -> 25 | F55: 1 | G55: 25 | H55: 0.04 | I55: 1 | J55: =H55*F55*IF(I55=1,Технический!$C$26,Технический!$C$27) -> 4.2469645 | K55: =J55/G55 -> 0.16987858 | L55: =1-K55/Тарифы!$G$19 -> 0.52807472 | M55: =Тарифы!C$18/$G55 -> 47 | N55: =Тарифы!D$18/$G55 -> 176 | O55: =Тарифы!E$18/$G55 -> 412 | P55: =Тарифы!F$18/$G55 -> 636 | Q55: =Тарифы!G$18/$G55 -> 1300 | R55: нет | S55: =IF(ISNUMBER($R55),Технический!C$108/$R55,"") | T55: =IF(ISNUMBER($R55),Технический!D$108/$R55,"") | U55: =IF(ISNUMBER($R55),Технический!E$108/$R55,"") | V55: =IF(ISNUMBER($R55),Технический!F$108/$R55,"") | W55: =IF(ISNUMBER($R55),Технический!G$108/$R55,"") | X55: 1.25 | Y55: =IF(ISNUMBER($X55),Технический!$I$112/$X55,"") -> 216 | Z55: =IF(ISNUMBER($X55),Технический!$I$110/$X55,"") -> 960 | AA55: =IF(ISNUMBER($X55),Технический!$I$111/$X55,"") -> 2400 | AB55: =IFERROR(AVERAGE((M55/$C$7)/((Технический!$C$108/$R55)/Технический!$C$107),(N55/$D$7)/((Технический!$D$108/$R55)/Технический!$D$107),(O55/$E$7)/((Технический!$E$108/$R55)/Технический!$E$107),(P55/$F$7)/((Технический!$F$108/$R55)/Технический!$F$107),(Q55/$G$7)/((Технический!$G$108/$R55)/Технический!$G$107))-1,"") | AC55: single-vendor | AD55: OR sole
B56: gpt-image-2 | C56: карт | D56: за картинку | E56: =G56/F56 -> 10 | F56: 1 | G56: 10 | H56: 0.03 | I56: 2 | J56: =H56*F56*IF(I56=1,Технический!$C$26,Технический!$C$27) -> 3.0191691 | K56: =J56/G56 -> 0.30191691 | L56: =1-K56/Тарифы!$G$19 -> 0.16127024 | M56: =Тарифы!C$18/$G56 -> 117.5 | N56: =Тарифы!D$18/$G56 -> 440 | O56: =Тарифы!E$18/$G56 -> 1030 | P56: =Тарифы!F$18/$G56 -> 1590 | Q56: =Тарифы!G$18/$G56 -> 3250 | R56: 2 | S56: =IF(ISNUMBER($R56),Технический!C$108/$R56,"") -> 130 | T56: =IF(ISNUMBER($R56),Технический!D$108/$R56,"") -> 342.75 | U56: =IF(ISNUMBER($R56),Технический!E$108/$R56,"") -> 850 | V56: =IF(ISNUMBER($R56),Технический!F$108/$R56,"") -> 1300 | W56: =IF(ISNUMBER($R56),Технический!G$108/$R56,"") -> 1500 | X56: 2 | Y56: =IF(ISNUMBER($X56),Технический!$I$112/$X56,"") -> 135 | Z56: =IF(ISNUMBER($X56),Технический!$I$110/$X56,"") -> 600 | AA56: =IF(ISNUMBER($X56),Технический!$I$111/$X56,"") -> 1500 | AB56: =IFERROR(AVERAGE((M56/$C$7)/((Технический!$C$108/$R56)/Технический!$C$107),(N56/$D$7)/((Технический!$D$108/$R56)/Технический!$D$107),(O56/$E$7)/((Технический!$E$108/$R56)/Технический!$E$107),(P56/$F$7)/((Технический!$F$108/$R56)/Технический!$F$107),(Q56/$G$7)/((Технический!$G$108/$R56)/Технический!$G$107))-1,"") -> 0.48304103 | AC56: 2.7 | AD56: =AC56/G56 -> 0.27 | AE56: =(Тарифы!$G$19-AD56)/Тарифы!$G$19 -> 0.24993589
B57: recraft-v4-vector | C57: карт | D57: за картинку | E57: =G57/F57 -> 40 | F57: 1 | G57: 40 | H57: 0.08 | I57: 1 | J57: =H57*F57*IF(I57=1,Технический!$C$26,Технический!$C$27) -> 8.493929 | K57: =J57/G57 -> 0.21234822 | L57: =1-K57/Тарифы!$G$19 -> 0.4100934 | M57: =Тарифы!C$18/$G57 -> 29.375 | N57: =Тарифы!D$18/$G57 -> 110 | O57: =Тарифы!E$18/$G57 -> 257.5 | P57: =Тарифы!F$18/$G57 -> 397.5 | Q57: =Тарифы!G$18/$G57 -> 812.5 | R57: нет | S57: =IF(ISNUMBER($R57),Технический!C$108/$R57,"") | T57: =IF(ISNUMBER($R57),Технический!D$108/$R57,"") | U57: =IF(ISNUMBER($R57),Технический!E$108/$R57,"") | V57: =IF(ISNUMBER($R57),Технический!F$108/$R57,"") | W57: =IF(ISNUMBER($R57),Технический!G$108/$R57,"") | X57: 2.5 | Y57: =IF(ISNUMBER($X57),Технический!$I$112/$X57,"") -> 108 | Z57: =IF(ISNUMBER($X57),Технический!$I$110/$X57,"") -> 480 | AA57: =IF(ISNUMBER($X57),Технический!$I$111/$X57,"") -> 1200 | AB57: =IFERROR(AVERAGE((M57/$C$7)/((Технический!$C$108/$R57)/Технический!$C$107),(N57/$D$7)/((Технический!$D$108/$R57)/Технический!$D$107),(O57/$E$7)/((Технический!$E$108/$R57)/Технический!$E$107),(P57/$F$7)/((Технический!$F$108/$R57)/Технический!$F$107),(Q57/$G$7)/((Технический!$G$108/$R57)/Технический!$G$107))-1,"") | AC57: single-vendor | AD57: OR sole
B58: nano-banana-2-lite | C58: карт | D58: за картинку | E58: =G58/F58 -> 8 | F58: 1 | G58: 8 | H58: 0.025 | I58: 2 | J58: =H58*F58*IF(I58=1,Технический!$C$26,Технический!$C$27) -> 2.5159742 | K58: =J58/G58 -> 0.31449678 | L58: =1-K58/Тарифы!$G$19 -> 0.12632317 | M58: =Тарифы!C$18/$G58 -> 146.875 | N58: =Тарифы!D$18/$G58 -> 550 | O58: =Тарифы!E$18/$G58 -> 1287.5 | P58: =Тарифы!F$18/$G58 -> 1987.5 | Q58: =Тарифы!G$18/$G58 -> 4062.5 | R58: 1.3 | S58: =IF(ISNUMBER($R58),Технический!C$108/$R58,"") -> 200 | T58: =IF(ISNUMBER($R58),Технический!D$108/$R58,"") -> 527.30769 | U58: =IF(ISNUMBER($R58),Технический!E$108/$R58,"") -> 1307.6923 | V58: =IF(ISNUMBER($R58),Технический!F$108/$R58,"") -> 2000 | W58: =IF(ISNUMBER($R58),Технический!G$108/$R58,"") -> 2307.6923 | X58: 1 | Y58: =IF(ISNUMBER($X58),Технический!$I$112/$X58,"") -> 270 | Z58: =IF(ISNUMBER($X58),Технический!$I$110/$X58,"") -> 1200 | AA58: =IF(ISNUMBER($X58),Технический!$I$111/$X58,"") -> 3000 | AB58: =IFERROR(AVERAGE((M58/$C$7)/((Технический!$C$108/$R58)/Технический!$C$107),(N58/$D$7)/((Технический!$D$108/$R58)/Технический!$D$107),(O58/$E$7)/((Технический!$E$108/$R58)/Технический!$E$107),(P58/$F$7)/((Технический!$F$108/$R58)/Технический!$F$107),(Q58/$G$7)/((Технический!$G$108/$R58)/Технический!$G$107))-1,"") -> 0.20497084 | AC58: single-vendor | AD58: lao sole
B59: nano-banana-2 | C59: карт | D59: за картинку | E59: =G59/F59 -> 17 | F59: 1 | G59: 17 | H59: 0.055 | I59: 2 | J59: =H59*F59*IF(I59=1,Технический!$C$26,Технический!$C$27) -> 5.5351433 | K59: =J59/G59 -> 0.32559666 | L59: =1-K59/Тарифы!$G$19 -> 0.095487514 | M59: =Тарифы!C$18/$G59 -> 69.117647 | N59: =Тарифы!D$18/$G59 -> 258.82353 | O59: =Тарифы!E$18/$G59 -> 605.88235 | P59: =Тарифы!F$18/$G59 -> 935.29412 | Q59: =Тарифы!G$18/$G59 -> 1911.7647 | R59: 3 | S59: =IF(ISNUMBER($R59),Технический!C$108/$R59,"") -> 86.666667 | T59: =IF(ISNUMBER($R59),Технический!D$108/$R59,"") -> 228.5 | U59: =IF(ISNUMBER($R59),Технический!E$108/$R59,"") -> 566.66667 | V59: =IF(ISNUMBER($R59),Технический!F$108/$R59,"") -> 866.66667 | W59: =IF(ISNUMBER($R59),Технический!G$108/$R59,"") -> 1000 | X59: 2 | Y59: =IF(ISNUMBER($X59),Технический!$I$112/$X59,"") -> 135 | Z59: =IF(ISNUMBER($X59),Технический!$I$110/$X59,"") -> 600 | AA59: =IF(ISNUMBER($X59),Технический!$I$111/$X59,"") -> 1500 | AB59: =IFERROR(AVERAGE((M59/$C$7)/((Технический!$C$108/$R59)/Технический!$C$107),(N59/$D$7)/((Технический!$D$108/$R59)/Технический!$D$107),(O59/$E$7)/((Технический!$E$108/$R59)/Технический!$E$107),(P59/$F$7)/((Технический!$F$108/$R59)/Технический!$F$107),(Q59/$G$7)/((Технический!$G$108/$R59)/Технический!$G$107))-1,"") -> 0.30856561 | AC59: single-vendor | AD59: lao sole
B60: nano-banana-pro | C60: карт | D60: за картинку | E60: =G60/F60 -> 31 | F60: 1 | G60: 31 | H60: 0.09 | I60: 2 | J60: =H60*F60*IF(I60=1,Технический!$C$26,Технический!$C$27) -> 9.0575072 | K60: =J60/G60 -> 0.29217765 | L60: =1-K60/Тарифы!$G$19 -> 0.18832604 | M60: =Тарифы!C$18/$G60 -> 37.903226 | N60: =Тарифы!D$18/$G60 -> 141.93548 | O60: =Тарифы!E$18/$G60 -> 332.25806 | P60: =Тарифы!F$18/$G60 -> 512.90323 | Q60: =Тарифы!G$18/$G60 -> 1048.3871 | R60: 2 | S60: =IF(ISNUMBER($R60),Технический!C$108/$R60,"") -> 130 | T60: =IF(ISNUMBER($R60),Технический!D$108/$R60,"") -> 342.75 | U60: =IF(ISNUMBER($R60),Технический!E$108/$R60,"") -> 850 | V60: =IF(ISNUMBER($R60),Технический!F$108/$R60,"") -> 1300 | W60: =IF(ISNUMBER($R60),Технический!G$108/$R60,"") -> 1500 | X60: 2 | Y60: =IF(ISNUMBER($X60),Технический!$I$112/$X60,"") -> 135 | Z60: =IF(ISNUMBER($X60),Технический!$I$110/$X60,"") -> 600 | AA60: =IF(ISNUMBER($X60),Технический!$I$111/$X60,"") -> 1500 | AB60: =IFERROR(AVERAGE((M60/$C$7)/((Технический!$C$108/$R60)/Технический!$C$107),(N60/$D$7)/((Технический!$D$108/$R60)/Технический!$D$107),(O60/$E$7)/((Технический!$E$108/$R60)/Технический!$E$107),(P60/$F$7)/((Технический!$F$108/$R60)/Технический!$F$107),(Q60/$G$7)/((Технический!$G$108/$R60)/Технический!$G$107))-1,"") -> -0.52159967 | AC60: 10.9 | AD60: =AC60/G60 -> 0.3516129 | AE60: =(Тарифы!$G$19-AD60)/Тарифы!$G$19 -> 0.023214005
B61: flux-2-pro · 2MP | C61: карт | D61: за картинку | E61: =G61/F61 -> 50 | F61: 1 | G61: 50 | H61: 0.03 | I61: 2 | J61: =H61*F61*IF(I61=1,Технический!$C$26,Технический!$C$27) -> 3.0191691 | K61: =J61/G61 -> 0.060383381 | L61: =1-K61/Тарифы!$G$19 -> 0.83225405 | M61: =Тарифы!C$18/$G61 -> 23.5 | N61: =Тарифы!D$18/$G61 -> 88 | O61: =Тарифы!E$18/$G61 -> 206 | P61: =Тарифы!F$18/$G61 -> 318 | Q61: =Тарифы!G$18/$G61 -> 650 | R61: нет | S61: =IF(ISNUMBER($R61),Технический!C$108/$R61,"") | T61: =IF(ISNUMBER($R61),Технический!D$108/$R61,"") | U61: =IF(ISNUMBER($R61),Технический!E$108/$R61,"") | V61: =IF(ISNUMBER($R61),Технический!F$108/$R61,"") | W61: =IF(ISNUMBER($R61),Технический!G$108/$R61,"") | X61: 1.5 | Y61: =IF(ISNUMBER($X61),Технический!$I$112/$X61,"") -> 180 | Z61: =IF(ISNUMBER($X61),Технический!$I$110/$X61,"") -> 800 | AA61: =IF(ISNUMBER($X61),Технический!$I$111/$X61,"") -> 2000 | AB61: =IFERROR(AVERAGE((M61/$C$7)/((Технический!$C$108/$R61)/Технический!$C$107),(N61/$D$7)/((Технический!$D$108/$R61)/Технический!$D$107),(O61/$E$7)/((Технический!$E$108/$R61)/Технический!$E$107),(P61/$F$7)/((Технический!$F$108/$R61)/Технический!$F$107),(Q61/$G$7)/((Технический!$G$108/$R61)/Технический!$G$107))-1,"") | AC61: 5.7 | AD61: =AC61/G61 -> 0.114 | AE61: =(Тарифы!$G$19-AD61)/Тарифы!$G$19 -> 0.68330627
B62: seedream-4-5 · до 4K | C62: карт | D62: за картинку | E62: =G62/F62 -> 15 | F62: 1 | G62: 15 | H62: 0.0325 | I62: 2 | J62: =H62*F62*IF(I62=1,Технический!$C$26,Технический!$C$27) -> 3.2707665 | K62: =J62/G62 -> 0.2180511 | L62: =1-K62/Тарифы!$G$19 -> 0.39425073 | M62: =Тарифы!C$18/$G62 -> 78.333333 | N62: =Тарифы!D$18/$G62 -> 293.33333 | O62: =Тарифы!E$18/$G62 -> 686.66667 | P62: =Тарифы!F$18/$G62 -> 1060 | Q62: =Тарифы!G$18/$G62 -> 2166.6667 | R62: 2 | S62: =IF(ISNUMBER($R62),Технический!C$108/$R62,"") -> 130 | T62: =IF(ISNUMBER($R62),Технический!D$108/$R62,"") -> 342.75 | U62: =IF(ISNUMBER($R62),Технический!E$108/$R62,"") -> 850 | V62: =IF(ISNUMBER($R62),Технический!F$108/$R62,"") -> 1300 | W62: =IF(ISNUMBER($R62),Технический!G$108/$R62,"") -> 1500 | X62: 1 | Y62: =IF(ISNUMBER($X62),Технический!$I$112/$X62,"") -> 270 | Z62: =IF(ISNUMBER($X62),Технический!$I$110/$X62,"") -> 1200 | AA62: =IF(ISNUMBER($X62),Технический!$I$111/$X62,"") -> 3000 | AB62: =IFERROR(AVERAGE((M62/$C$7)/((Технический!$C$108/$R62)/Технический!$C$107),(N62/$D$7)/((Технический!$D$108/$R62)/Технический!$D$107),(O62/$E$7)/((Технический!$E$108/$R62)/Технический!$E$107),(P62/$F$7)/((Технический!$F$108/$R62)/Технический!$F$107),(Q62/$G$7)/((Технический!$G$108/$R62)/Технический!$G$107))-1,"") -> -0.01130598 | AC62: 4.1 | AD62: =AC62/G62 -> 0.27333333 | AE62: =(Тарифы!$G$19-AD62)/Тарифы!$G$19 -> 0.24067584
B63: — ВИДЕО (за секунду; «Ед. в 1 ген» = типовая длина клипа — МЕНЯЙ) —
B64: happyhorse-1-0 | C64: видео | D64: за секунду | E64: =G64/F64 -> 46.4 | F64: 5 | G64: 232 | H64: 0.0988 | I64: 1 | J64: =H64*F64*IF(I64=1,Технический!$C$26,Технический!$C$27) -> 52.450011 | K64: =J64/G64 -> 0.22607764 | L64: =1-K64/Тарифы!$G$19 -> 0.37195289 | M64: =Тарифы!C$18/$G64 -> 5.0646552 | N64: =Тарифы!D$18/$G64 -> 18.965517 | O64: =Тарифы!E$18/$G64 -> 44.396552 | P64: =Тарифы!F$18/$G64 -> 68.534483 | Q64: =Тарифы!G$18/$G64 -> 140.08621 | R64: 45 | S64: =IF(ISNUMBER($R64),Технический!C$108/$R64,"") -> 5.7777778 | T64: =IF(ISNUMBER($R64),Технический!D$108/$R64,"") -> 15.233333 | U64: =IF(ISNUMBER($R64),Технический!E$108/$R64,"") -> 37.777778 | V64: =IF(ISNUMBER($R64),Технический!F$108/$R64,"") -> 57.777778 | W64: =IF(ISNUMBER($R64),Технический!G$108/$R64,"") -> 66.666667 | X64: 22.5 | Y64: =IF(ISNUMBER($X64),Технический!$I$112/$X64,"") -> 12 | Z64: =IF(ISNUMBER($X64),Технический!$I$110/$X64,"") -> 53.333333 | AA64: =IF(ISNUMBER($X64),Технический!$I$111/$X64,"") -> 133.33333 | AB64: =IFERROR(AVERAGE((M64/$C$7)/((Технический!$C$108/$R64)/Технический!$C$107),(N64/$D$7)/((Технический!$D$108/$R64)/Технический!$D$107),(O64/$E$7)/((Технический!$E$108/$R64)/Технический!$E$107),(P64/$F$7)/((Технический!$F$108/$R64)/Технический!$F$107),(Q64/$G$7)/((Технический!$G$108/$R64)/Технический!$G$107))-1,"") -> 0.4382941 | AC64: 63.4 | AD64: =AC64/G64 -> 0.27327586 | AE64: =(Тарифы!$G$19-AD64)/Тарифы!$G$19 -> 0.2408355
B65: happyhorse-1-1 | C65: видео | D65: за секунду | E65: =G65/F65 -> 46.4 | F65: 5 | G65: 232 | H65: 0.0988 | I65: 1 | J65: =H65*F65*IF(I65=1,Технический!$C$26,Технический!$C$27) -> 52.450011 | K65: =J65/G65 -> 0.22607764 | L65: =1-K65/Тарифы!$G$19 -> 0.37195289 | M65: =Тарифы!C$18/$G65 -> 5.0646552 | N65: =Тарифы!D$18/$G65 -> 18.965517 | O65: =Тарифы!E$18/$G65 -> 44.396552 | P65: =Тарифы!F$18/$G65 -> 68.534483 | Q65: =Тарифы!G$18/$G65 -> 140.08621 | R65: 45 | S65: =IF(ISNUMBER($R65),Технический!C$108/$R65,"") -> 5.7777778 | T65: =IF(ISNUMBER($R65),Технический!D$108/$R65,"") -> 15.233333 | U65: =IF(ISNUMBER($R65),Технический!E$108/$R65,"") -> 37.777778 | V65: =IF(ISNUMBER($R65),Технический!F$108/$R65,"") -> 57.777778 | W65: =IF(ISNUMBER($R65),Технический!G$108/$R65,"") -> 66.666667 | X65: 22.5 | Y65: =IF(ISNUMBER($X65),Технический!$I$112/$X65,"") -> 12 | Z65: =IF(ISNUMBER($X65),Технический!$I$110/$X65,"") -> 53.333333 | AA65: =IF(ISNUMBER($X65),Технический!$I$111/$X65,"") -> 133.33333 | AB65: =IFERROR(AVERAGE((M65/$C$7)/((Технический!$C$108/$R65)/Технический!$C$107),(N65/$D$7)/((Технический!$D$108/$R65)/Технический!$D$107),(O65/$E$7)/((Технический!$E$108/$R65)/Технический!$E$107),(P65/$F$7)/((Технический!$F$108/$R65)/Технический!$F$107),(Q65/$G$7)/((Технический!$G$108/$R65)/Технический!$G$107))-1,"") -> 0.4382941 | AC65: 50.9 | AD65: =AC65/G65 -> 0.21939655 | AE65: =(Тарифы!$G$19-AD65)/Тарифы!$G$19 -> 0.39051304
B66: veo-3-1 Quality · 720p | C66: видео | D66: за клип | E66: =G66/F66 -> 850 | F66: 1 | G66: 850 | H66: 1.25 | I66: 2 | J66: =H66*F66*IF(I66=1,Технический!$C$26,Технический!$C$27) -> 125.79871 | K66: =J66/G66 -> 0.14799848 | L66: =1-K66/Тарифы!$G$19 -> 0.58885796 | M66: =Тарифы!M$18/$G66 -> 0 | N66: =Тарифы!N$18/$G66 -> 0 | O66: =Тарифы!O$18/$G66 -> 0 | P66: =Тарифы!P$18/$G66 -> 0 | Q66: =Тарифы!Q$18/$G66 -> 0
B67: veo-3-1-fast · 720p | C67: видео | D67: за клип | E67: =G67/F67 -> 213 | F67: 1 | G67: 213 | H67: 0.3 | I67: 2 | J67: =H67*F67*IF(I67=1,Технический!$C$26,Технический!$C$27) -> 30.191691 | K67: =J67/G67 -> 0.14174503 | L67: =1-K67/Тарифы!$G$19 -> 0.60623016 | M67: =Тарифы!M$18/$G67 -> 0 | N67: =Тарифы!N$18/$G67 -> 0 | O67: =Тарифы!O$18/$G67 -> 0 | P67: =Тарифы!P$18/$G67 -> 0 | Q67: =Тарифы!Q$18/$G67 -> 0
B68: veo-3-1-lite · 720p | C68: видео | D68: за клип | E68: =G68/F68 -> 107 | F68: 1 | G68: 107 | H68: 0.15 | I68: 2 | J68: =H68*F68*IF(I68=1,Технический!$C$26,Технический!$C$27) -> 15.095845 | K68: =J68/G68 -> 0.14108267 | L68: =1-K68/Тарифы!$G$19 -> 0.60807021 | M68: =Тарифы!M$18/$G68 -> 0 | N68: =Тарифы!N$18/$G68 -> 0 | O68: =Тарифы!O$18/$G68 -> 0 | P68: =Тарифы!P$18/$G68 -> 0 | Q68: =Тарифы!Q$18/$G68 -> 0
B69: sora-2-pro — УДАЛЕНА (geoblock; не продаётся, исключена из каталога)
